Workbook
Name SegmentaçãodeDados_ESTRATO_DE_PRODUÇÃO__L_DIA: #N/A
Name SegmentaçãodeDados_Município: #N/A
Name SegmentaçãodeDados_TIPOLOGIA_DA_PRODUÇÃO_DE_LEITE: #N/A

Sheet DADOS 1
A1: Nome | B1: Município | C1: TIPOLOGIA DA PRODUÇÃO DE LEITE | D1: ESTRATO DE PRODUÇÃO (L/DIA) | E1: 1.2. Topografia/relevo predominante da propriedade rural: | F1: 1.5. Sistema de produção de leite cru? | G1: 1.6. Tipos de benfeitorias na propriedade rural (Marque o tipo de construção para cada benfeitoria) [Casa sede] | H1: 1.6. Tipos de benfeitorias na propriedade rural (Marque o tipo de construção para cada benfeitoria) [Casa/alojamento de empregado] | I1: 1.6. Tipos de benfeitorias na propriedade rural (Marque o tipo de construção para cada benfeitoria) [Galpão para máquinas, implementos e afins] | J1: 1.7. Existência de recursos hídricos e serviços na propriedade rural: | K1: CAR - Cadastro Ambiental Rural | L1: Cursos d’água/riacho/nascentes/mina | M1: Vegetação nativa/mata/floresta | N1: Área de preservação permanentes | O1: Área de reserva legal | P1: Serviço de água potável | Q1: Serviço de esgoto doméstico tratado | R1: Serviço de telefonia | S1: 2.1. Idade (anos) | T1: 2.2. Tempo que é produtor(a) de leite (anos) | U1: 2.3. Sexo | V1: 2.4. Escolaridade: | W1: 2.5. Residência principal (mais de 50% do tempo): | X1: 2.6. Distribuição da área utilizada na produção leiteira: Própria (%) | Y1: 2.6. Distribuição da área utilizada na produção leiteira: Arrendada (%) | Z1: 2.6. Distribuição da área utilizada na produção leiteira: Parceria (%) | AA1: 2.6. Distribuição da área utilizada na produção leiteira: Comodato (%) | AB1: 2.6. Distribuição da área utilizada na produção leiteira: Assentamento (%) | AC1: 2.6. Distribuição da área utilizada na produção leiteira: Como posseiro (%) | AD1: 2.7. Origem da área própria utilizada na atividade leiteira: Herança ou doação (%) | AE1: 2.7. Origem da área própria utilizada na atividade leiteira: Compra (%) | AF1: 2.7. Origem da área própria utilizada na atividade leiteira: Posse ou usucapião (%) | AG1: 2.7. Origem da área própria utilizada na atividade leiteira: Titulação ou licença de ocupação (%) | AH1: 2.7. Origem da área própria utilizada na atividade leiteira: Outro (%) | AI1: 2.8. Faz parte de alguma associação ou cooperativa relacionada à produção de leite? | AJ1: 2.9. Composição da renda bruta do produtor rural: Pecuária de leite (%) | AK1: 2.9. Composição da renda bruta do produtor rural: Outras criações (%) | AL1: 2.9. Composição da renda bruta do produtor rural: Culturas permanentes (%) | AM1: 2.9. Composição da renda bruta do produtor rural: Culturas anuais (%) | AN1: 2.9. Composição da renda bruta do produtor rural: Fora da propriedade (%) | AO1: 2.10. Composição da renda bruta da atividade leiteira: Venda e consumo de leite (%) | AP1: 2.10. Composição da renda bruta da atividade leiteira: Venda e consumo de animais (%) | AQ1: 2.10. Composição da renda bruta da atividade leiteira: Outro (%) | AR1: 2.11. Recebe ou acessa algum benefício social no âmbito do governo? (Pode marcar mais de uma opção) | AS1: Bolsa família | AT1: Aposentadoria | AU1: PRONAF | AV1: PRONAMPE | AW1: Seguro Safra | AX1: Programa de Aquisição de Alimentos (PAA) | AY1: Programa de Garantia de Preços para a Agricultura Familiar (PGPAF) | AZ1: Benefício de Prestação Continuada | BA1: Outro programa municipal/estadual | BB1: Não recebe benefício do governo | BC1: 3.1. Atualmente, seu retorno financeiro na produção de leite pode ser considerado: | BD1: 3.2. Sua atividade leiteira se mantém sem recursos externos? | BE1: 3.3. Por que está na atividade do leite? (Marque no máximo 3 alternativas) | BF1: Por gostar | BG1: Por ser uma atividade lucrativa | BH1: Por proporcionar renda mensal | BI1: A atividade leiteira é uma tradição na família | BJ1: Combina com outras explorações da propriedade | BK1: Tem mercado garantido | BL1: Não sabe fazer outra coisa | BM1: Emprega a família | BN1: Não sabe | BO1: 3.4. Excluindo o preço do leite, quais os principais problemas que influenciam na sua produção? (Marque no máximo 3 alternativas) | BP1: Falta de mão de obra | BQ1: Deficiência na qualificação da mão de obra | BR1: Falta de crédito rural, com taxas de juros compatíveis com a atividade | BS1: Deficiência de informações técnicas sobre a produção de leite | BT1: Deficiência de informações de mercado | BU1: Custo dos insumos | BV1: Deficiência na infraestrutura de transporte/estradas | BW1: Instabilidade de políticas públicas | BX1: Legislação ambiental | BY1: Legislação trabalhista | BZ1: Baixa capacidade de endividamento | CA1: Não sabe | CB1: 3.6. Na sua opinião, quais os pontos mais importantes para uma produção de leite rentável? (Marque no máximo 3 alternativas) | CC1: Mão de obra qualificada | CD1: Sanidade do rebanho | CE1: Qualidade genética dos animais | CF1: Alimentação do rebanho | CG1: Manejo do rebanho | CH1: Reprodução do rebanho | CI1: Preço do leite | CJ1: Conhecimento de técnicas eficientes | CK1: Não sabe | CL1: 3.7. Para os próximos 5 anos, o que pretende fazer com a produção de leite? | CM1: 3.8. Opinião do produtor sobre a sucessão em sua propriedade: | CN1: 4.1. Utilizou crédito rural nos últimos 12 meses? | CO1: 4.2. Se utilizou, quais as principais linhas de crédito? (Pode marcar mais de uma opção) | CP1: PRONAF | CQ1: INOVAGRO | CR1: PRONAMPE | CS1: Cooperativas de crédito ou bancos privados | CT1: Plano Safra | CU1: Crédito Informal | CV1: Não utilizou crédito | CW1: 4.3. Se não utilizou crédito, por quê? (Pode marcar mais de uma opção) | CX1: Documentação pessoal incompleta | CY1: Falta de regularização fundiária | CZ1: Não tem capacidade para endividamento | DA1: Dificuldade para obter financiamento | DB1: Não precisou de crédito | DC1: Utilizou crédito | DD1: 5.2. Produção de leite média dos últimos 12 meses (consumido + vendido) (litros/dia) | DE1: 5.2.1. Produção nas águas (litros/dia) | DF1: 5.2.2. Produção na seca (litros/dia) | DG1: 5.3. Produtividade média / vaca em lactação (litros/vaca/dia) | DH1: 5.3.1. Produtividade nas águas (litros/vaca/dia) | DI1: 5.3.2 Produtividade na seca (litros/vaca/dia) | DJ1: 5.4. Distribuição da produção de leite nos últimos 12 meses: Vendida para laticínio/cooperativa (leite fluído) (%) | DK1: 5.4. Distribuição da produção de leite nos últimos 12 meses: Vendida diretamente para consumidor (leite fluído) (%) | DL1: 5.4. Distribuição da produção de leite nos últimos 12 meses: Vendida na forma de derivados (queijos, requeijão, etc.) (%) | DM1: 5.4. Distribuição da produção de leite nos últimos 12 meses: Autoconsumo humano (%) | DN1: 5.4. Distribuição da produção de leite nos últimos 12 meses: Aleitamento (%) | DO1: 5.5. Área própria total da propriedade (hectares) | DP1: 5.6. Área destinada ao gado de leite (hectares) | DQ1: 5.7.1. Possui cônjuge ou companheiro(a)? | DR1: Tem filhos | DS1: Tem filhos que trabalham na propriedade rural | DT1: TOTAL FAMILIAR (TRABALHADOR/DIA) | DU1: TOTAL CONTRATADA (TRABALHADOR/DIA) | DV1: MDO TOTAL (TRABALHADOR/DIA) | DW1: 5.11.1. Número atual de cabeças no rebanho: Vaca em lactação | DX1: 5.11.1. Número atual de cabeças no rebanho: Vaca seca | DY1: 5.11.1. Número atual de cabeças no rebanho: Bezerra em aleitamento | DZ1: 5.11.1. Número atual de cabeças no rebanho: Bezerro em aleitamento | EA1: 5.11.1. Número atual de cabeças no rebanho: Novilha em recria | EB1: 5.11.1. Número atual de cabeças no rebanho: Novilha em reprodução | EC1: 5.11.1. Número atual de cabeças no rebanho: Garrote | ED1: 5.11.1. Número atual de cabeças no rebanho: Touro | EE1: 5.11.1. Número atual de cabeças no rebanho: Animal de serviço | EF1: 5.11.2.a. Composição % do rebanho - Reprodutores (touro/sêmen): Menos de 1/2 HZ (azebuado) (%) | EG1: 5.11.2.a. Composição % do rebanho - Reprodutores (touro/sêmen): De 1/2 a 3/4 HZ (%) | EH1: 5.11.2.a. Composição % do rebanho - Reprodutores (touro/sêmen): De 3/4 a 7/8 HZ (%) | EI1: 5.11.2.a. Composição % do rebanho - Reprodutores (touro/sêmen): De 7/8 HZ a puro holandês (%) | EJ1: 5.11.2.a. Composição % do rebanho - Reprodutores (touro/sêmen): Puro holandês (%) | EK1: 5.11.2.a. Composição % do rebanho - Reprodutores (touro/sêmen): Puro outras raças europeias (%) | EL1: 5.11.2.a. Composição % do rebanho - Reprodutores (touro/sêmen): Puro raças zebuínas (%) | EM1: 5.11.2.a. Composição % do rebanho - Reprodutores (touro/sêmen): Sem padrão definido (%) | EN1: 5.11.2.b. Composição % do rebanho - Vacas (lactação + secas): Menos de 1/2 HZ (azebuado) (%) | EO1: 5.11.2.b. Composição % do rebanho - Vacas (lactação + secas): De 1/2 a 3/4 HZ (%) | EP1: 5.11.2.b. Composição % do rebanho - Vacas (lactação + secas): De 3/4 a 7/8 HZ (%) | EQ1: 5.11.2.b. Composição % do rebanho - Vacas (lactação + secas): De 7/8 HZ a puro holandês (%) | ER1: 5.11.2.b. Composição % do rebanho - Vacas (lactação + secas): Puro holandês (%) | ES1: 5.11.2.b. Composição % do rebanho - Vacas (lactação + secas): Puro outras raças europeias (%) | ET1: 5.11.2.b. Composição % do rebanho - Vacas (lactação + secas): Puro raças zebuínas (%) | EU1: 5.11.2.b. Composição % do rebanho - Vacas (lactação + secas): Sem padrão definido (%) | EV1: 6.1. Como é feito o resfriamento do leite na fazenda? | EW1: 6.4. Tem fonte de água no curral? | EX1: 6.5. Tem cobertura no curral? | EY1: 6.6. Estrutura do local de ordenha: | EZ1: 6.7. Tem fonte de água no local de ordenha? | FA1: 6.8. A Sala de ordenha é coberta? | FB1: 6.9. Tipo de ordenha: | FC1: 6.10. Número de ordenhas nas águas | FD1: 6.10. Número de ordenhas na seca | FE1: 6.12. O leite é enviado ao laticínio: | FF1: 6.15. Tipo de pastagem na propriedade rural: | FG1: 6.16. Tipo de pastagem plantada na propriedade rural: (Pode marcar mais de uma opção) | FH1: Brachiaria | FI1: Panicum | FJ1: Capim-elefante | FK1: Colonião | FL1: Jaraguá | FM1: Andropogon | FN1: Cynodon | FO1: Tifton | FP1: Não tem pastagem plantada | FQ1: 6.17. Quais dessas práticas são utilizadas nas pastagens? (Pode marcar mais de uma opção) | FR1: Correção e adubação do solo na implantação | FS1: Adubação anual de cobertura | FT1: Controle de plantas invasoras | FU1: Rotação de pastagens | FV1: Divisão em piquetes | FW1: Cerca elétrica nos piquetes | FX1: Nenhuma das anteriores | FY1: Não utiliza pastagens | FZ1: 7.1. Quem faz a administração/direção da atividade leiteira? | GA1: 7.2. Quais metas anuais são estabelecidas para a atividade leiteira? (Pode marcar mais de uma opção) | GB1: Produção de leite | GC1: Produtividade | GD1: Receitas | GE1: Despesas | GF1: Venda de genética | GG1: Venda de animais | GH1: Não estabelece metas | GI1: 7.4. Realização de controle financeiro da produção: | GJ1: 7.5. Sabe qual o custo médio da sua produção de leite? | GK1: 7.6. Se sim, qual o valor médio anual do seu custo de produção? (R$/litro) | GL1: 8.1. Quais as principais fontes de informações sobre gado de leite? (Marque no máximo 3 alternativas) | GM1: Assistência técnica | GN1: Vizinho, amigo ou parente | GO1: Treinamento (curso, palestra, etc.) | GP1: Jornais e revistas agropecuários | GQ1: Programas de TV | GR1: Outras mídias sociais | GS1: 8.4. Nos últimos 12 meses, quantas vezes um técnico visitou sua propriedade para orientá-lo(a) sobre a produção de leite? (visitas/ano) | GT1: 8.6. Quais informações sobre a produção de leite mais recebeu? (Marque no máximo 3 alternativas) | GU1: Planejamento da empresa rural | GV1: Cálculo do custo de produção | GW1: Mercado do leite | GX1: Alimentação do rebanho | GY1: Sanidade do rebanho | GZ1: Manejo do rebanho | HA1: Melhoramento genético | HB1: Gerenciamento da produção | HC1: Produção de leite e meio ambiente | HD1: Qualidade do leite | HE1: Não sabe | HF1: 8.7. Quais informações sobre a produção de leite tem mais carência? (Marque no máximo 3 alternativas) | HG1: Planejamento da empresa rural | HH1: Cálculo do custo de produção | HI1: Mercado do leite | HJ1: Alimentação do rebanho | HK1: Sanidade do rebanho | HL1: Manejo do rebanho | HM1: Melhoramento genético | HN1: Gerenciamento da produção | HO1: Produção de leite e meio ambiente | HP1: Qualidade do leite | HQ1: Não sabe | HR1: 9.1. Distribuição % aproximada das vacas em lactação em cada tipo de sistema: Freestall (%) | HS1: 9.1. Distribuição % aproximada das vacas em lactação em cada tipo de sistema: Compost Barn (%) | HT1: 9.1. Distribuição % aproximada das vacas em lactação em cada tipo de sistema: Semiconfinado (%) | HU1: 9.1. Distribuição % aproximada das vacas em lactação em cada tipo de sistema: Piquete rotacionado (%) | HV1: 9.1. Distribuição % aproximada das vacas em lactação em cada tipo de sistema: Pasto extensivo (%) | HW1: 9.2. Utiliza técnicas para conforto dos animais? (Pode marcar mais de uma opção) | HX1: Galpão coberto | HY1: Sombrite ou tela de sombreamento | HZ1: Cobertura vegetal (árvores, sombra natural) | IA1: Exaustores | IB1: Ventiladores mecânicos | IC1: Aspersores ou nebulizadores | ID1: Sistema de resfriamento evaporativo | IE1: Bebedouros | IF1: Controle automatizado de temperatura/umidade | IG1: Piso emborrachado ou drenante nas áreas de espera | IH1: 9.3. Possui energia elétrica na propriedade? | II1: 9.4. Possui internet na propriedade? | IJ1: 9.7. Quais desses equipamentos próprios são utilizados na produção de leite: (Pode marcar mais de uma opção) | IK1: Picadeira | IL1: Balança para os animais | IM1: Trator | IN1: Vagão forrageiro | IO1: Plantadeira | IP1: Grade | IQ1: Arado | IR1: Ensiladeira | IS1: Distribuidor de calcário | IT1: Misturador de ração | IU1: 9.8. Qual o destino de dejetos líquidos e sólidos? (Pode marcar mais de uma opção) | IV1: 9.9. Quais dessas técnicas sustentáveis são utilizadas? (Pode marcar mais de uma opção) | IW1: Plantio direto | IX1: Cobertura do solo | IY1: Descarte adequado de embalagens (herbicida e defensivos) | IZ1: Tratamento de efluentes da residência | JA1: Rotação de culturas | JB1: 10.1. Idade média que desfaz dos machos (meses) | JC1: 10.2. Idade média de desmama dos bezerros(as) (meses) | JD1: 10.3. Peso médio ao desmame dos bezerros(as) (Kg) | JE1: 10.4. Idade média das novilhas ao primeiro parto (meses) | JF1: 10.5. Intervalo entre partos médio (meses) | JG1: 10.6. Taxa de mortalidade média de bezerros (%) | JH1: 10.7. Taxa de mortalidade média de animais adultos (%) | JI1: 10.9. Quais critérios sanitários contra enfermidades são aplicados ao rebanho: (Pode marcar mais de uma opção) | JJ1: Manqueira | JK1: Brucelose | JL1: Paratifo | JM1: Raiva | JN1: Enterotoxemia | JO1: Botulismo | JP1: Vermifugação | JQ1: Carrapaticida | JR1: IBR/BVD | JS1: Leptospirose | JT1: 10.10. Técnicas utilizadas no manejo de ordenha: (Pode marcar mais de uma opção) | JU1: Teste da caneca | JV1: Pré-dipping | JW1: Pós-dipping | JX1: Linha de ordenha | JY1: Alimentação durante a ordenha | JZ1: Alimentação após a ordenha | KA1: Identificação de animais tratados com antibiótico | KB1: 10.11. Sistema de reprodução: (Pode marcar mais de uma opção) | KC1: FIV/TE | KD1: Inseminação artificial/IATF | KE1: Natural controlada | KF1: Natural não controlada | KG1: 10.12. Tipo de aleitamento: | KH1: 10.13. Critério para primeira cobertura: | KI1: 10.14. Frequência de uso do concentrado para vacas em lactação: | KJ1: 10.15. Quando usa concentrado ele é distribuído de acordo com a produção das vacas? | KK1: 10.16. Tipo de suplementação volumosa utilizado: (Pode marcar mais de uma opção) | KL1: Cana-de-açúcar | KM1: Capineira | KN1: Silagem de capim | KO1: Silagem de milho | KP1: Silagem de sorgo | KQ1: Outra silagem | KR1: Feno | KS1: Palma | KT1: Não fornece suplementação | KU1: 11.2. Há quanto tempo vende para o mesmo comprador? (anos) | KV1: 11.3. Preço recebido no último mês? (R$/litro) | KW1: 11.4. Preço médio recebido nas águas? (R$/litro) | KX1: 11.5. Preço médio recebido na seca? (R$/litro) | KY1: 11.7. Quais bonificações são realizadas pelo laticínio que compra seu leite: (Pode marcar mais de uma opção) | KZ1: Volume de leite entregue | LA1: Nível de CCS | LB1: Nível de CBT | LC1: Teor de gordura | LD1: Teor de proteína | LE1: Critérios de sustentabilidade e BPA | LF1: Não sabe | LG1: 11.8. Qual sua opinião sobre o sistema de pagamento com bonificação? [Por volume de leite] | LH1: 11.8. Qual sua opinião sobre o sistema de pagamento com bonificação? [Por qualidade do leite] | LI1: 11.8. Qual sua opinião sobre o sistema de pagamento com bonificação? [Por critérios de sustentabilidade] | LJ1: 11.9. Tem contrato formal com o laticínio que compra seu leite? | LK1: 11.10. Como avalia a importância de um contrato formal com o laticínio?
B2: Coimbra | C2: Não familiar | D2: 4) 1001 a 2500 | E2: Suavemente acidentado ou acidentado | F2: Intensivo | G2: Alvenaria | H2: Alvenaria | I2: Alvenaria | J2: CAR - Cadastro Ambiental Rural, Cursos d’água/riacho/nascentes/mina, Área de preservação permanentes, Área de reserva legal, Serviço de telefonia | K2: Sim | L2: Sim | N2: Sim | O2: Sim | R2: Sim | S2: 65 | T2: 34 | U2: Masculino | V2: Pós-graduação | W2: Na cidade | X2: 100 | Y2: 0 | Z2: 0 | AA2: 0 | AB2: 0 | AC2: 0 | AD2: 0 | AE2: 100 | AF2: 0 | AG2: 0 | AH2: 0 | AI2: Não | AJ2: 10 | AK2: 0 | AL2: 0 | AM2: 70 | AN2: 20 | AO2: 95 | AP2: 5 | AQ2: 0 | AR2: Aposentadoria | AT2: Sim | BC2: Regular | BD2: Não | BE2: Por gostar | BF2: Sim | BO2: Falta de crédito rural, com taxas de juros compatíveis com a atividade, Instabilidade de políticas públicas, Legislação trabalhista | BR2: Sim | BW2: Sim | BY2: Sim | CB2: Qualidade genética dos animais, Alimentação do rebanho, Reprodução do rebanho | CE2: Sim | CF2: Sim | CH2: Sim | CL2: Aumentar a produção | CM2: Filhos continuarão com a produção de leite | CN2: Sim | CO2: PRONAMPE, Plano Safra | CR2: Sim | CT2: Sim | CW2: Utilizou crédito | DC2: Sim | DD2: 2000 | DE2: 2000 | DF2: 2000 | DG2: 31 | DH2: 28 | DI2: 34 | DJ2: 95 | DK2: 0 | DL2: 0 | DM2: 0.2 | DN2: 4.8 | DO2: 60 | DP2: 45 | DQ2: Sim | DR2: Sim | DS2: Sim | DT2: 0.21369863 | DU2: 6 | DV2: =DT2+DU2 -> 6.2136986 | DW2: 71 | DX2: 9 | DY2: 19 | DZ2: 1 | EA2: 22 | EB2: 34 | EC2: 1 | ED2: 0 | EE2: 2 | EF2: 0 | EG2: 0 | EH2: 0 | EI2: 0 | EJ2: 100 | EK2: 0 | EL2: 0 | EM2: 0 | EN2: 0 | EO2: 2 | EP2: 7 | EQ2: 63 | ER2: 28 | ES2: 0 | ET2: 0 | EU2: 0 | EV2: Tanque de expansão | EW2: Sim | EX2: Sim | EY2: Sala de ordenha com fosso | EZ2: Sim | FA2: Sim | FB2: Mecânica | FC2: 3 | FD2: 3 | FE2: Todos os dias | FF2: Mista | FG2: Brachiaria, Tifton | FH2: Sim | FO2: Sim | FQ2: Nenhuma das anteriores | FX2: Sim | FZ2: Proprietário(a) e família | GA2: Produção de leite, Produtividade | GB2: Sim | GC2: Sim | GI2: Utiliza os indicadores econômicos de forma sistemática para tomada de decisão | GJ2: Sim | GK2: 2.43 | GL2: Assistência técnica, Treinamento (curso, palestra, etc.), Outras mídias sociais | GM2: Sim | GO2: Sim | GR2: Sim | GS2: 150 | GT2: Alimentação do rebanho, Manejo do rebanho, Gerenciamento da produção | GX2: Sim | GZ2: Sim | HB2: Sim | HF2: Cálculo do custo de produção, Mercado do leite | HH2: Sim | HI2: Sim | HR2: 60 | HS2: 40 | HT2: 0 | HU2: 0 | HV2: 0 | HW2: Galpão coberto, Ventiladores mecânicos, Aspersores ou nebulizadores, Sistema de resfriamento evaporativo, Bebedouros, Controle automatizado de temperatura/umidade | HX2: Sim | IB2: Sim | ID2: Sim | IE2: Sim | IF2: Sim | IH2: Residência e locais de produção | II2: Em toda fazenda | IJ2: Balança para os animais, Trator, Vagão forrageiro, Ensiladeira, Misturador de ração | IL2: Sim | IM2: Sim | IN2: Sim | IR2: Sim | IT2: Sim | IU2: Chorumeira | IV2: Plantio direto, Cobertura do solo, Descarte adequado de embalagens (herbicida e defensivos), Tratamento de efluentes da residência | IW2: Sim | IX2: Sim | IY2: Sim | IZ2: Sim | JB2: 1 | JC2: 3 | JD2: 110 | JE2: 27 | JF2: 16 | JG2: 15 | JH2: 10 | JI2: Manqueira, Brucelose, Paratifo, Raiva, Enterotoxemia, Botulismo, Vermifugação, Carrapaticida, IBR/BVD, Leptospirose | JJ2: Sim | JK2: Sim | JL2: Sim | JM2: Sim | JN2: Sim | JO2: Sim | JP2: Sim | JQ2: Sim | JR2: Sim | JS2: Sim | JT2: Teste da caneca, Pré-dipping, Pós-dipping, Linha de ordenha, Alimentação após a ordenha, Identificação de animais tratados com antibiótico | JU2: Sim | JV2: Sim | JW2: Sim | JX2: Sim | JZ2: Sim | KA2: Sim | KB2: Inseminação artificial/IATF | KD2: Sim | KG2: Artificial | KH2: Idade e peso das novilhas | KI2: Ano todo | KJ2: Sim | KK2: Silagem de milho | KO2: Sim | KU2: 5 | KV2: 3.07 | KW2: 2.77 | KX2: 3.15 | KY2: Nível de CCS, Nível de CBT, Teor de gordura | LA2: Sim | LB2: Sim | LC2: Sim | LG2: Concorda | LH2: Concorda | LI2: Concorda | LJ2: Sim | LK2: Muito importante
B3: Coimbra | C3: Não familiar | D3: 4) 1001 a 2500 | E3: Fortemente acidentado | F3: Intensivo | G3: Alvenaria | H3: Alvenaria | I3: Alvenaria | J3: CAR - Cadastro Ambiental Rural, Cursos d’água/riacho/nascentes/mina, Vegetação nativa/mata/floresta, Área de preservação permanentes, Área de reserva legal, Serviço de água potável, Serviço de esgoto doméstico tratado, Serviço de telefonia | K3: Sim | L3: Sim | M3: Sim | N3: Sim | O3: Sim | P3: Sim | Q3: Sim | R3: Sim | S3: 62 | T3: 21 | U3: Masculino | V3: Ensino médio incompleto | W3: Na propriedade rural | X3: 40 | Y3: 60 | Z3: 0 | AA3: 0 | AB3: 0 | AC3: 0 | AD3: 5 | AE3: 95 | AF3: 0 | AG3: 0 | AH3: 0 | AI3: Não | AJ3: 5 | AK3: 5 | AL3: 30 | AM3: 60 | AN3: 0 | AO3: 50 | AP3: 50 | AQ3: 0 | AR3: Aposentadoria, PRONAMPE | AT3: Sim | AV3: Sim | BC3: Regular | BD3: Não | BE3: Por gostar, Por proporcionar renda mensal, Combina com outras explorações da propriedade | BF3: Sim | BH3: Sim | BJ3: Sim | BO3: Falta de mão de obra, Custo dos insumos, Instabilidade de políticas públicas | BP3: Sim | BU3: Sim | BW3: Sim | CB3: Mão de obra qualificada, Sanidade do rebanho, Preço do leite | CC3: Sim | CD3: Sim | CI3: Sim | CL3: Não sabe | CM3: Filhos deixarão o meio rural | CN3: Sim | CO3: PRONAMPE, Plano Safra | CR3: Sim | CT3: Sim | CW3: Utilizou crédito | DC3: Sim | DD3: 2500 | DE3: 2500 | DF3: 2500 | DG3: 19 | DH3: 19 | DI3: 19 | DJ3: 94.5 | DK3: 0 | DL3: 0 | DM3: 0.5 | DN3: 5 | DO3: 170 | DP3: 40 | DQ3: Sim | DR3: Sim | DS3: Não | DT3: 0.73972603 | DU3: 6 | DV3: =DT3+DU3 -> 6.739726 | DW3: 145 | DX3: 52 | DY3: 15 | DZ3: 6 | EA3: 46 | EB3: 114 | EC3: 0 | ED3: 0 | EE3: 4 | EF3: 0 | EG3: 0 | EH3: 40 | EI3: 0 | EJ3: 60 | EK3: 0 | EL3: 0 | EM3: 0 | EN3: 0 | EO3: 0 | EP3: 25 | EQ3: 25 | ER3: 50 | ES3: 0 | ET3: 0 | EU3: 0 | EV3: Tanque de expansão | EW3: Sim | EX3: Sim | EY3: Sala de ordenha com fosso | EZ3: Sim | FA3: Sim | FB3: Mecânica | FC3: 2 | FD3: 2 | FE3: Todos os dias | FF3: Plantada | FG3: Brachiaria, Tifton | FH3: Sim | FO3: Sim | FQ3: Controle de plantas invasoras, Rotação de pastagens, Divisão em piquetes, Cerca elétrica nos piquetes | FU3: Sim | FV3: Sim | FW3: Sim | FZ3: Administrador(a) e proprietário(a) | GA3: Produção de leite, Produtividade, Despesas | GB3: Sim | GC3: Sim | GE3: Sim | GI3: Utiliza os indicadores econômicos de forma sistemática para tomada de decisão | GJ3: Sim | GK3: 2.4 | GL3: Assistência técnica, Jornais e revistas agropecuários, Outras mídias sociais | GM3: Sim | GP3: Sim | GR3: Sim | GS3: 216 | GT3: Sanidade do rebanho, Melhoramento genético, Qualidade do leite | GY3: Sim | HA3: Sim | HD3: Sim | HF3: Mercado do leite, Produção de leite e meio ambiente | HI3: Sim | HO3: Sim | HR3: 0 | HS3: 100 | HT3: 0 | HU3: 0 | HV3: 0 | HW3: Galpão coberto, Ventiladores mecânicos, Bebedouros | HX3: Sim | IB3: Sim | IE3: Sim | IH3: Residência e locais de produção | II3: Em toda fazenda | IJ3: Trator, Vagão forrageiro, Plantadeira, Grade, Ensiladeira, Distribuidor de calcário, Misturador de ração | IM3: Sim | IN3: Sim | IO3: Sim | IP3: Sim | IR3: Sim | IS3: Sim | IT3: Sim | IU3: Chorumeira | IV3: Plantio direto, Cobertura do solo, Descarte adequado de embalagens (herbicida e defensivos), Tratamento de efluentes da residência, Rotação de culturas | IW3: Sim | IX3: Sim | IY3: Sim | IZ3: Sim | JA3: Sim | JB3: 1 | JC3: 3 | JD3: 100 | JE3: 24 | JF3: 12 | JG3: 5 | JH3: 2 | JI3: Manqueira, Brucelose, Paratifo, Raiva, Enterotoxemia, Botulismo, Vermifugação, Carrapaticida, IBR/BVD, Leptospirose | JJ3: Sim | JK3: Sim | JL3: Sim | JM3: Sim | JN3: Sim | JO3: Sim | JP3: Sim | JQ3: Sim | JR3: Sim | JS3: Sim | JT3: Teste da caneca, Pré-dipping, Pós-dipping, Alimentação após a ordenha, Identificação de animais tratados com antibiótico | JU3: Sim | JV3: Sim | JW3: Sim | JZ3: Sim | KA3: Sim | KB3: FIV/TE, Inseminação artificial/IATF | KC3: Sim | KD3: Sim | KG3: Artificial | KH3: Peso das novilhas | KI3: Ano todo | KJ3: Sim | KK3: Silagem de milho | KO3: Sim | KU3: 3 | KV3: 2.75 | KW3: 2.75 | KX3: 2.75 | KY3: Volume de leite entregue, Nível de CCS, Nível de CBT, Teor de gordura, Teor de proteína | KZ3: Sim | LA3: Sim | LB3: Sim | LC3: Sim | LD3: Sim | LG3: Concorda | LH3: Concorda | LI3: Concorda | LJ3: Sim | LK3: Muito importante
B4: Paula Cândido | C4: Familiar | D4: 2) 201 a 500 | E4: Fortemente acidentado | F4: Semiextensivo | G4: Alvenaria | H4: Não possui | I4: Madeira | J4: CAR - Cadastro Ambiental Rural, Cursos d’água/riacho/nascentes/mina, Vegetação nativa/mata/floresta, Área de preservação permanentes, Área de reserva legal, Serviço de água potável, Serviço de telefonia | K4: Sim | L4: Sim | M4: Sim | N4: Sim | O4: Sim | P4: Sim | R4: Sim | S4: 43 | T4: 20 | U4: Masculino | V4: Ensino médio completo | W4: Na propriedade rural | X4: 50 | Y4: 50 | Z4: 0 | AA4: 0 | AB4: 0 | AC4: 0 | AD4: 0 | AE4: 100 | AF4: 0 | AG4: 0 | AH4: 0 | AI4: Sim | AJ4: 95 | AK4: 0 | AL4: 0 | AM4: 0 | AN4: 5 | AO4: 90 | AP4: 10 | AQ4: 0 | AR4: Bolsa família, PRONAF | AS4: Sim | AU4: Sim | BC4: Regular | BD4: Sim | BE4: Por gostar, Por proporcionar renda mensal, Emprega a família | BF4: Sim | BH4: Sim | BM4: Sim | BO4: Falta de mão de obra | BP4: Sim | CB4: Mão de obra qualificada, Preço do leite | CC4: Sim | CI4: Sim | CL4: Continuar como está | CM4: Filhos continuarão com a produção de leite | CN4: Sim | CO4: PRONAF | CP4: Sim | CW4: Utilizou crédito | DC4: Sim | DD4: 500 | DE4: 500 | DF4: 500 | DG4: 22 | DH4: 22 | DI4: 22 | DJ4: 100 | DK4: 0 | DL4: 0 | DM4: 0 | DN4: 0 | DO4: 34 | DP4: 15 | DQ4: Sim | DR4: Sim | DS4: Não | DT4: 3.0575342 | DU4: 1 | DV4: =DT4+DU4 -> 4.0575342 | DW4: 22 | DX4: 8 | DY4: 4 | DZ4: 1 | EA4: 20 | EB4: 2 | EC4: 0 | ED4: 0 | EE4: 1 | EF4: 0 | EG4: 0 | EH4: 0 | EI4: 0 | EJ4: 100 | EK4: 0 | EL4: 0 | EM4: 0 | EN4: 0 | EO4: 0 | EP4: 0 | EQ4: 100 | ER4: 0 | ES4: 0 | ET4: 0 | EU4: 0 | EV4: Tanque de expansão | EW4: Sim | EX4: Sim | EY4: Sala de ordenha com fosso | EZ4: Sim | FA4: Sim | FB4: Mecânica | FC4: 2 | FD4: 2 | FE4: De 2 em 2 dias | FF4: Mista | FG4: Brachiaria | FH4: Sim | FQ4: Nenhuma das anteriores | FX4: Sim | FZ4: Apenas o(a) proprietário(a) | GA4: Produção de leite, Produtividade, Receitas, Despesas | GB4: Sim | GC4: Sim | GD4: Sim | GE4: Sim | GI4: Utiliza os indicadores econômicos de forma sistemática para tomada de decisão | GJ4: Sim | GK4: 2 | GL4: Assistência técnica, Vizinho, amigo ou parente | GM4: Sim | GN4: Sim | GS4: 24 | GT4: Planejamento da empresa rural, Alimentação do rebanho, Sanidade do rebanho | GU4: Sim | GX4: Sim | GY4: Sim | HF4: Não sabe | HQ4: Sim | HR4: 0 | HS4: 100 | HT4: 0 | HU4: 0 | HV4: 0 | HW4: Galpão coberto, Cobertura vegetal (árvores, sombra natural), Ventiladores mecânicos, Bebedouros | HX4: Sim | HZ4: Sim | IB4: Sim | IE4: Sim | IH4: Residência e locais de produção | II4: Somente na residência | IJ4: Picadeira, Trator, Plantadeira, Grade, Arado, Ensiladeira, Distribuidor de calcário, Misturador de ração | IK4: Sim | IM4: Sim | IO4: Sim | IP4: Sim | IQ4: Sim | IR4: Sim | IS4: Sim | IT4: Sim | IU4: “Raspado” e/ou armazenado | IV4: Plantio direto, Cobertura do solo, Descarte adequado de embalagens (herbicida e defensivos) | IW4: Sim | IX4: Sim | IY4: Sim | JB4: 0 | JC4: 3 | JD4: 100 | JE4: 26 | JF4: 13 | JG4: 0 | JH4: 2 | JI4: Manqueira, Brucelose, Paratifo, Raiva, Enterotoxemia, Botulismo, Vermifugação, Carrapaticida, IBR/BVD, Leptospirose | JJ4: Sim | JK4: Sim | JL4: Sim | JM4: Sim | JN4: Sim | JO4: Sim | JP4: Sim | JQ4: Sim | JR4: Sim | JS4: Sim | JT4: Pré-dipping, Pós-dipping, Linha de ordenha | JV4: Sim | JW4: Sim | JX4: Sim | KB4: FIV/TE, Inseminação artificial/IATF | KC4: Sim | KD4: Sim | KG4: Artificial | KH4: Idade e peso das novilhas | KI4: Ano todo | KJ4: Sim | KK4: Silagem de milho | KO4: Sim | KU4: 5 | KV4: 2.8 | KW4: 1.8 | KX4: 3 | KY4: Volume de leite entregue, Nível de CCS, Nível de CBT, Teor de gordura, Teor de proteína | KZ4: Sim | LA4: Sim | LB4: Sim | LC4: Sim | LD4: Sim | LG4: Concorda | LH4: Concorda | LI4: Concorda | LJ4: Sim | LK4: Muito importante
B5: Paula Cândido | C5: Familiar | D5: 1) Até 200 | E5: Fortemente acidentado | F5: Semiextensivo | G5: Alvenaria | H5: Não possui | I5: Mista | J5: CAR - Cadastro Ambiental Rural, Cursos d’água/riacho/nascentes/mina, Vegetação nativa/mata/floresta, Área de preservação permanentes, Área de reserva legal, Serviço de água potável, Serviço de telefonia | K5: Sim | L5: Sim | M5: Sim | N5: Sim | O5: Sim | P5: Sim | R5: Sim | S5: 27 | T5: 7 | U5: Masculino | V5: Ensino médio completo | W5: Na cidade | X5: 100 | Y5: 0 | Z5: 0 | AA5: 0 | AB5: 0 | AC5: 0 | AD5: 100 | AE5: 0 | AF5: 0 | AG5: 0 | AH5: 0 | AI5: Sim | AJ5: 50 | AK5: 50 | AL5: 0 | AM5: 0 | AN5: 0 | AO5: 60 | AP5: 40 | AQ5: 0 | AR5: Não recebe benefício do governo | BB5: Sim | BC5: Regular | BD5: Sim | BE5: Por proporcionar renda mensal, Tem mercado garantido | BH5: Sim | BK5: Sim | BO5: Instabilidade de políticas públicas | BW5: Sim | CB5: Qualidade genética dos animais, Alimentação do rebanho, Preço do leite | CE5: Sim | CF5: Sim | CI5: Sim | CL5: Aumentar a produção | CM5: Filhos continuarão com a produção de leite | CN5: Não | CO5: Não utilizou crédito | CV5: Sim | CW5: Não tem capacidade para endividamento | CZ5: Sim | DD5: 130 | DE5: 130 | DF5: 130 | DG5: 19.666667 | DH5: 18 | DI5: 22 | DJ5: 100 | DK5: 0 | DL5: 0 | DM5: 0 | DN5: 0 | DO5: 34 | DP5: 10 | DQ5: Sim | DR5: Sim | DS5: Não | DT5: 0.50958904 | DU5: 0 | DV5: =DT5+DU5 -> 0.50958904 | DW5: 5 | DX5: 2 | DY5: 0 | DZ5: 0 | EA5: 3 | EB5: 1 | EC5: 0 | ED5: 0 | EE5: 1 | EF5: 0 | EG5: 0 | EH5: 0 | EI5: 0 | EJ5: 50 | EK5: 0 | EL5: 50 | EM5: 0 | EN5: 0 | EO5: 80 | EP5: 20 | EQ5: 0 | ER5: 0 | ES5: 0 | ET5: 0 | EU5: 0 | EV5: Tanque de expansão | EW5: Sim | EX5: Sim | EY5: Sala de ordenha com fosso | EZ5: Sim | FA5: Sim | FB5: Mecânica | FC5: 2 | FD5: 2 | FE5: De 2 em 2 dias | FF5: Plantada | FG5: Brachiaria, Panicum, Tifton | FH5: Sim | FI5: Sim | FO5: Sim | FQ5: Correção e adubação do solo na implantação, Adubação anual de cobertura, Controle de plantas invasoras, Rotação de pastagens, Divisão em piquetes, Cerca elétrica nos piquetes | FR5: Sim | FU5: Sim | FV5: Sim | FW5: Sim | FZ5: Apenas o(a) proprietário(a) | GA5: Produção de leite, Produtividade, Receitas, Despesas | GB5: Sim | GC5: Sim | GD5: Sim | GE5: Sim | GI5: Utiliza os indicadores econômicos de forma sistemática para tomada de decisão | GJ5: Sim | GK5: 2 | GL5: Assistência técnica, Vizinho, amigo ou parente, Treinamento (curso, palestra, etc.), Jornais e revistas agropecuários, Outras mídias sociais | GM5: Sim | GN5: Sim | GO5: Sim | GP5: Sim | GR5: Sim | GS5: 28 | GT5: Planejamento da empresa rural, Cálculo do custo de produção, Manejo do rebanho | GU5: Sim | GV5: Sim | GZ5: Sim | HF5: Mercado do leite | HI5: Sim | HR5: 0 | HS5: 0 | HT5: 50 | HU5: 50 | HV5: 0 | HW5: Cobertura vegetal (árvores, sombra natural), Ventiladores mecânicos, Aspersores ou nebulizadores, Bebedouros | HZ5: Sim | IB5: Sim | IE5: Sim | IH5: Residência e locais de produção | II5: Somente na residência | IJ5: Misturador de ração | IT5: Sim | IU5: “Raspado” e/ou armazenado | IV5: Plantio direto, Cobertura do solo, Descarte adequado de embalagens (herbicida e defensivos), Rotação de culturas | IW5: Sim | IX5: Sim | IY5: Sim | JA5: Sim | JB5: 0 | JC5: 3 | JD5: 110 | JE5: 27 | JF5: 14 | JG5: 0 | JH5: 0 | JI5: Manqueira, Brucelose, Paratifo, Raiva, Enterotoxemia, Botulismo, Vermifugação, Carrapaticida, IBR/BVD, Leptospirose | JJ5: Sim | JK5: Sim | JL5: Sim | JM5: Sim | JN5: Sim | JO5: Sim | JP5: Sim | JQ5: Sim | JR5: Sim | JS5: Sim | JT5: Teste da caneca, Pré-dipping, Pós-dipping, Linha de ordenha, Alimentação durante a ordenha, Alimentação após a ordenha | JU5: Sim | JV5: Sim | JW5: Sim | JX5: Sim | JY5: Sim | JZ5: Sim | KB5: Inseminação artificial/IATF | KD5: Sim | KG5: Artificial | KH5: Idade e peso das novilhas | KI5: Ano todo | KJ5: Sim | KK5: Silagem de milho | KO5: Sim | KU5: 4 | KV5: 2.52 | KW5: 2.2 | KX5: 2.8 | KY5: Nível de CCS, Nível de CBT, Teor de gordura, Teor de proteína | LA5: Sim | LB5: Sim | LC5: Sim | LD5: Sim | LG5: Concorda | LH5: Concorda | LI5: Concorda | LJ5: Sim | LK5: Muito importante
B6: Cajuri | C6: Não familiar | D6: 5) Acima de 2501 | E6: Suavemente acidentado ou acidentado | F6: Intensivo | G6: Mista | H6: Mista | I6: Madeira | J6: CAR - Cadastro Ambiental Rural, Cursos d’água/riacho/nascentes/mina, Vegetação nativa/mata/floresta, Área de preservação permanentes, Área de reserva legal, Serviço de água potável | K6: Sim | L6: Sim | M6: Sim | N6: Sim | O6: Sim | P6: Sim | S6: 66 | T6: 50 | U6: Masculino | V6: Ensino médio completo | W6: Na propriedade rural | X6: 23 | Y6: 77 | Z6: 0 | AA6: 0 | AB6: 0 | AC6: 0 | AD6: 50 | AE6: 50 | AF6: 0 | AG6: 0 | AH6: 0 | AI6: Não | AJ6: 90 | AK6: 0 | AL6: 10 | AM6: 0 | AN6: 0 | AO6: 90 | AP6: 10 | AQ6: 0 | AR6: Não recebe benefício do governo | BB6: Sim | BC6: Bom | BD6: Sim | BE6: Por ser uma atividade lucrativa | BG6: Sim | BO6: Falta de mão de obra, Deficiência na qualificação da mão de obra, Falta de crédito rural, com taxas de juros compatíveis com a atividade | BP6: Sim | BQ6: Sim | BR6: Sim | CB6: Mão de obra qualificada, Sanidade do rebanho, Alimentação do rebanho | CC6: Sim | CD6: Sim | CF6: Sim | CL6: Aumentar a produção | CM6: Filhos continuarão com a produção de leite | CN6: Não | CO6: Não utilizou crédito | CV6: Sim | CW6: Não precisou de crédito | DB6: Sim | DD6: 10000 | DE6: 9000 | DF6: 11000 | DG6: 28 | DH6: 26 | DI6: 30 | DJ6: 95 | DK6: 0 | DL6: 0 | DM6: 0 | DN6: 5 | DO6: 200 | DP6: 70 | DQ6: Sim | DR6: Sim | DS6: Sim | DT6: 1.6109589 | DU6: 18 | DV6: =DT6+DU6 -> 19.610959 | DW6: 400 | DX6: 80 | DY6: 70 | DZ6: 20 | EA6: 200 | EB6: 150 | EC6: 0 | ED6: 2 | EE6: 3 | EF6: 0 | EG6: 0 | EH6: 0 | EI6: 0 | EJ6: 100 | EK6: 0 | EL6: 0 | EM6: 0 | EN6: 0 | EO6: 0 | EP6: 0 | EQ6: 0 | ER6: 100 | ES6: 0 | ET6: 0 | EU6: 0 | EV6: Tanque de expansão | EW6: Sim | EX6: Sim | EY6: Sala de ordenha com fosso | EZ6: Sim | FA6: Sim | FB6: Mecânica | FC6: 2 | FD6: 2 | FE6: Todos os dias | FF6: Plantada | FG6: Cynodon | FN6: Sim | FQ6: Correção e adubação do solo na implantação | FR6: Sim | FZ6: Apenas o(a) proprietário(a) | GA6: Produção de leite, Produtividade, Receitas | GB6: Sim | GC6: Sim | GD6: Sim | GI6: Utiliza os indicadores econômicos de forma sistemática para tomada de decisão | GJ6: Sim | GK6: 2.6 | GL6: Assistência técnica | GM6: Sim | GS6: 120 | GT6: Planejamento da empresa rural, Cálculo do custo de produção, Sanidade do rebanho | GU6: Sim | GV6: Sim | GY6: Sim | HF6: Gerenciamento da produção | HN6: Sim | HR6: 30 | HS6: 70 | HT6: 0 | HU6: 0 | HV6: 0 | HW6: Galpão coberto, Ventiladores mecânicos, Sistema de resfriamento evaporativo, Bebedouros, Controle automatizado de temperatura/umidade | HX6: Sim | IB6: Sim | ID6: Sim | IE6: Sim | IF6: Sim | IH6: Residência e locais de produção | II6: Em toda fazenda | IJ6: Balança para os animais, Trator, Vagão forrageiro, Plantadeira, Grade, Ensiladeira, Distribuidor de calcário, Misturador de ração | IL6: Sim | IM6: Sim | IN6: Sim | IO6: Sim | IP6: Sim | IR6: Sim | IS6: Sim | IT6: Sim | IU6: Não tem destino certo | IV6: Plantio direto, Cobertura do solo, Descarte adequado de embalagens (herbicida e defensivos), Rotação de culturas | IW6: Sim | IX6: Sim | IY6: Sim | JA6: Sim | JB6: 3 | JC6: 3 | JD6: 120 | JE6: 23 | JF6: 14 | JG6: 3 | JH6: 3 | JI6: Manqueira, Brucelose, Paratifo, Raiva, Enterotoxemia, Vermifugação, Carrapaticida, IBR/BVD, Leptospirose | JJ6: Sim | JK6: Sim | JL6: Sim | JM6: Sim | JN6: Sim | JP6: Sim | JQ6: Sim | JR6: Sim | JS6: Sim | JT6: Teste da caneca, Pré-dipping, Pós-dipping, Linha de ordenha, Alimentação após a ordenha, Identificação de animais tratados com antibiótico | JU6: Sim | JV6: Sim | JW6: Sim | JX6: Sim | JZ6: Sim | KA6: Sim | KB6: Inseminação artificial/IATF | KD6: Sim | KG6: Artificial | KH6: Idade e peso das novilhas | KI6: Ano todo | KJ6: Sim | KK6: Silagem de milho | KO6: Sim | KU6: 8 | KV6: 2.76 | KW6: 2.4 | KX6: 3 | KY6: Volume de leite entregue, Nível de CCS, Nível de CBT, Teor de gordura, Teor de proteína | KZ6: Sim | LA6: Sim | LB6: Sim | LC6: Sim | LD6: Sim | LG6: Concorda | LH6: Concorda | LI6: Concorda | LJ6: Sim | LK6: Muito importante
B7: Cajuri | C7: Familiar | D7: 3) 501 a 1000 | E7: Extremamente acidentado | F7: Intensivo | G7: Alvenaria | H7: Não possui | I7: Alvenaria | J7: CAR - Cadastro Ambiental Rural, Cursos d’água/riacho/nascentes/mina, Vegetação nativa/mata/floresta, Área de preservação permanentes, Área de reserva legal, Serviço de telefonia | K7: Sim | L7: Sim | M7: Sim | N7: Sim | O7: Sim | R7: Sim | S7: 50 | T7: 15 | U7: Masculino | V7: Ensino fundamental incompleto | W7: Na propriedade rural | X7: 0 | Y7: 0 | Z7: 0 | AA7: 100 | AB7: 0 | AC7: 0 | AI7: Não | AJ7: 90 | AK7: 0 | AL7: 0 | AM7: 0 | AN7: 10 | AO7: 99 | AP7: 1 | AQ7: 0 | AR7: PRONAF | AU7: Sim | BC7: Muito bom | BD7: Sim | BE7: Por gostar, Por ser uma atividade lucrativa, Por proporcionar renda mensal | BF7: Sim | BG7: Sim | BH7: Sim | BO7: Deficiência de informações de mercado | BT7: Sim | CB7: Qualidade genética dos animais, Alimentação do rebanho, Reprodução do rebanho | CE7: Sim | CF7: Sim | CH7: Sim | CL7: Aumentar a produção | CM7: Não sabe | CN7: Sim | CO7: PRONAF | CP7: Sim | CW7: Utilizou crédito | DC7: Sim | DD7: 733.33333 | DE7: 650 | DF7: 750 | DG7: 31.333333 | DH7: 28 | DI7: 32 | DJ7: 96 | DK7: 0 | DL7: 1 | DM7: 1 | DN7: 2 | DP7: 6.2 | DQ7: Sim | DR7: Sim | DS7: Sim | DT7: 1.0001096 | DU7: 0 | DV7: =DT7+DU7 -> 1.0001096 | DW7: 28 | DX7: 4 | DY7: 2 | DZ7: 1 | EA7: 19 | EB7: 13 | EC7: 1 | ED7: 0 | EE7: 0 | EF7: 0 | EG7: 100 | EH7: 0 | EI7: 0 | EJ7: 0 | EK7: 0 | EL7: 0 | EM7: 0 | EN7: 0 | EO7: 0 | EP7: 10 | EQ7: 90 | ER7: 0 | ES7: 0 | ET7: 0 | EU7: 0 | EV7: Tanque de expansão | EW7: Sim | EX7: Sim | EY7: Sala de ordenha com fosso | EZ7: Sim | FA7: Sim | FB7: Mecânica | FC7: 2 | FD7: 2 | FE7: De 2 em 2 dias | FF7: Plantada | FG7: Brachiaria, Tifton | FH7: Sim | FO7: Sim | FQ7: Controle de plantas invasoras, Divisão em piquetes, Cerca elétrica nos piquetes | FV7: Sim | FW7: Sim | FZ7: Apenas o(a) proprietário(a) | GA7: Produtividade, Receitas | GC7: Sim | GD7: Sim | GI7: Utiliza os indicadores econômicos de forma sistemática para tomada de decisão | GJ7: Sim | GK7: 2.35 | GL7: Assistência técnica, Outras mídias sociais | GM7: Sim | GR7: Sim | GS7: 20 | GT7: Planejamento da empresa rural, Alimentação do rebanho, Qualidade do leite | GU7: Sim | GX7: Sim | HD7: Sim | HF7: Mercado do leite | HI7: Sim | HR7: 0 | HS7: 100 | HT7: 0 | HU7: 0 | HV7: 0 | HW7: Galpão coberto, Cobertura vegetal (árvores, sombra natural), Ventiladores mecânicos, Aspersores ou nebulizadores, Bebedouros, Controle automatizado de temperatura/umidade | HX7: Sim | HZ7: Sim | IB7: Sim | IE7: Sim | IF7: Sim | IH7: Residência e locais de produção | II7: Somente na residência | IJ7: Trator, Plantadeira, Grade, Ensiladeira, Misturador de ração | IM7: Sim | IO7: Sim | IP7: Sim | IR7: Sim | IT7: Sim | IU7: Não tem destino certo | IV7: Rotação de culturas | JA7: Sim | JB7: 0 | JC7: 2.5 | JD7: 120 | JE7: 24 | JF7: 14 | JG7: 0 | JH7: 0 | JI7: Manqueira, Brucelose, Raiva, Botulismo, Vermifugação, IBR/BVD, Leptospirose | JJ7: Sim | JK7: Sim | JM7: Sim | JO7: Sim | JP7: Sim | JR7: Sim | JS7: Sim | JT7: Pré-dipping, Pós-dipping, Linha de ordenha | JV7: Sim | JW7: Sim | JX7: Sim | KB7: Inseminação artificial/IATF, Natural não controlada | KD7: Sim | KF7: Sim | KG7: Artificial | KH7: Não tem critério definido | KI7: Ano todo | KJ7: Sim | KK7: Silagem de milho | KO7: Sim | KU7: 5 | KV7: 3.04 | KW7: 2.8 | KX7: 2.8 | KY7: Volume de leite entregue, Nível de CCS, Nível de CBT, Teor de gordura, Teor de proteína | KZ7: Sim | LA7: Sim | LB7: Sim | LC7: Sim | LD7: Sim | LG7: Concorda | LH7: Concorda | LI7: Concorda | LJ7: Sim | LK7: Pouco importante
B8: Presidente Bernardes | C8: Não familiar | D8: 4) 1001 a 2500 | E8: Suavemente acidentado ou acidentado | F8: Intensivo | G8: Alvenaria | H8: Não possui | I8: Alvenaria | J8: CAR - Cadastro Ambiental Rural, Cursos d’água/riacho/nascentes/mina, Vegetação nativa/mata/floresta, Área de preservação permanentes | K8: Sim | L8: Sim | M8: Sim | N8: Sim | S8: 31 | T8: 19 | U8: Masculino | V8: Ensino médio completo | W8: Na propriedade rural | X8: 99 | Y8: 1 | Z8: 0 | AA8: 0 | AB8: 0 | AC8: 0 | AD8: 10 | AE8: 90 | AF8: 0 | AG8: 0 | AH8: 0 | AI8: Não | AJ8: 40 | AK8: 0 | AL8: 0 | AM8: 0 | AN8: 60 | AO8: 90 | AP8: 10 | AQ8: 0 | AR8: Não recebe benefício do governo | BB8: Sim | BC8: Muito bom | BD8: Sim | BE8: Por gostar, Por ser uma atividade lucrativa, Por proporcionar renda mensal | BF8: Sim | BG8: Sim | BH8: Sim | BO8: Falta de mão de obra, Deficiência na qualificação da mão de obra, Custo dos insumos | BP8: Sim | BQ8: Sim | BU8: Sim | CB8: Sanidade do rebanho, Qualidade genética dos animais, Preço do leite | CD8: Sim | CE8: Sim | CI8: Sim | CL8: Continuar como está | CM8: Filhos continuarão com a produção de leite | CN8: Não | CO8: Não utilizou crédito | CV8: Sim | CW8: Não precisou de crédito | DB8: Sim | DD8: 1613.3333 | DE8: 1600 | DF8: 1620 | DG8: 31.333333 | DH8: 30 | DI8: 32 | DJ8: 80 | DK8: 1 | DL8: 0 | DM8: 2 | DN8: 17 | DO8: 46 | DP8: 17 | DQ8: Não | DR8: Não | DS8: Não | DT8: 0.49315068 | DU8: 11 | DV8: =DT8+DU8 -> 11.493151 | DW8: 53 | DX8: 9 | DY8: 19 | DZ8: 0 | EA8: 35 | EB8: 15 | EC8: 0 | ED8: 0 | EE8: 0 | EF8: 0 | EG8: 0 | EH8: 0 | EI8: 0 | EJ8: 95 | EK8: 0 | EL8: 5 | EM8: 0 | EN8: 0 | EO8: 1 | EP8: 0 | EQ8: 0 | ER8: 99 | ES8: 0 | ET8: 0 | EU8: 0 | EV8: Tanque de expansão | EW8: Sim | EX8: Sim | EY8: Sala de ordenha com fosso | EZ8: Sim | FA8: Sim | FB8: Mecânica | FC8: 2 | FD8: 2 | FE8: De 2 em 2 dias | FF8: Não tem pastagem | FG8: Não tem pastagem plantada | FP8: Sim | FQ8: Não utiliza pastagens | FY8: Sim | FZ8: Proprietário(a) e família | GA8: Produtividade, Venda de genética, Venda de animais | GC8: Sim | GF8: Sim | GG8: Sim | GI8: Utiliza os indicadores econômicos de forma sistemática para tomada de decisão | GJ8: Não | GL8: Assistência técnica, Treinamento (curso, palestra, etc.), Outras mídias sociais | GM8: Sim | GO8: Sim | GR8: Sim | GS8: 26 | GT8: Sanidade do rebanho, Manejo do rebanho, Melhoramento genético | GY8: Sim | GZ8: Sim | HA8: Sim | HF8: Mercado do leite | HI8: Sim | HR8: 0 | HS8: 100 | HT8: 0 | HU8: 0 | HV8: 0 | HW8: Galpão coberto, Ventiladores mecânicos, Aspersores ou nebulizadores, Sistema de resfriamento evaporativo, Bebedouros | HX8: Sim | IB8: Sim | ID8: Sim | IE8: Sim | IH8: Residência e locais de produção | II8: Em toda fazenda | IJ8: Picadeira, Balança para os animais, Trator, Vagão forrageiro, Grade, Misturador de ração | IK8: Sim | IL8: Sim | IM8: Sim | IN8: Sim | IP8: Sim | IT8: Sim | IU8: Chorumeira | IV8: Plantio direto, Cobertura do solo, Descarte adequado de embalagens (herbicida e defensivos), Tratamento de efluentes da residência, Rotação de culturas | IW8: Sim | IX8: Sim | IY8: Sim | IZ8: Sim | JA8: Sim | JB8: 0 | JC8: 3 | JD8: 110 | JE8: 23 | JF8: 13 | JG8: 1 | JH8: 1.6 | JI8: Manqueira, Brucelose, Raiva, Enterotoxemia, Botulismo, Vermifugação, Carrapaticida, IBR/BVD, Leptospirose | JJ8: Sim | JK8: Sim | JM8: Sim | JN8: Sim | JO8: Sim | JP8: Sim | JQ8: Sim | JR8: Sim | JS8: Sim | JT8: Teste da caneca, Pré-dipping, Pós-dipping, Alimentação após a ordenha, Identificação de animais tratados com antibiótico | JU8: Sim | JV8: Sim | JW8: Sim | JZ8: Sim | KA8: Sim | KB8: FIV/TE, Inseminação artificial/IATF | KC8: Sim | KD8: Sim | KG8: Natural | KH8: Idade e peso das novilhas | KI8: Ano todo | KJ8: Sim | KK8: Cana-de-açúcar, Capineira, Silagem de milho | KL8: Sim | KM8: Sim | KO8: Sim | KU8: 5 | KV8: 3 | KW8: 2.5 | KX8: 2.95 | KY8: Nível de CCS, Nível de CBT, Teor de gordura, Teor de proteína | LA8: Sim | LB8: Sim | LC8: Sim | LD8: Sim | LG8: Concorda | LH8: Concorda | LI8: Concorda | LJ8: Não | LK8: Muito importante
B9: Coimbra | C9: Não familiar | D9: 3) 501 a 1000 | E9: Suavemente acidentado ou acidentado | F9: Intensivo | G9: Alvenaria | H9: Alvenaria | I9: Mista | J9: CAR - Cadastro Ambiental Rural, Cursos d’água/riacho/nascentes/mina, Vegetação nativa/mata/floresta, Área de preservação permanentes, Área de reserva legal, Serviço de água potável | K9: Sim | L9: Sim | M9: Sim | N9: Sim | O9: Sim | P9: Sim | S9: 60 | T9: 5 | U9: Masculino | V9: Ensino médio completo | W9: Na cidade | X9: 70 | Y9: 30 | Z9: 0 | AA9: 0 | AB9: 0 | AC9: 0 | AD9: 0 | AE9: 100 | AF9: 0 | AG9: 0 | AH9: 0 | AI9: Não | AJ9: 50 | AK9: 0 | AL9: 0 | AM9: 0 | AN9: 50 | AO9: 97 | AP9: 3 | AQ9: 0 | AR9: Aposentadoria | AT9: Sim | BC9: Regular | BD9: Não | BE9: Por gostar, A atividade leiteira é uma tradição na família | BF9: Sim | BI9: Sim | BO9: Deficiência na qualificação da mão de obra, Falta de crédito rural, com taxas de juros compatíveis com a atividade, Custo dos insumos | BQ9: Sim | BR9: Sim | BU9: Sim | CB9: Mão de obra qualificada, Qualidade genética dos animais, Manejo do rebanho | CC9: Sim | CE9: Sim | CG9: Sim | CL9: Aumentar a produção | CM9: Filhos continuarão com a produção de leite | CN9: Sim | CO9: PRONAMPE | CR9: Sim | CW9: Utilizou crédito | DC9: Sim | DD9: 800 | DE9: 800 | DF9: 800 | DG9: 27 | DH9: 27 | DI9: 27 | DJ9: 95 | DK9: 0 | DL9: 0 | DM9: 0.5 | DN9: 4.5 | DO9: 15 | DP9: 25 | DQ9: Sim | DR9: Sim | DS9: Sim | DT9: 0.032876712 | DU9: 3 | DV9: =DT9+DU9 -> 3.0328767 | DW9: 38 | DX9: 3 | DY9: 10 | DZ9: 0 | EA9: 20 | EB9: 10 | EC9: 1 | ED9: 0 | EE9: 1 | EF9: 0 | EG9: 0 | EH9: 5 | EI9: 0 | EJ9: 95 | EK9: 0 | EL9: 0 | EM9: 0 | EN9: 0 | EO9: 5 | EP9: 90 | EQ9: 0 | ER9: 5 | ES9: 0 | ET9: 0 | EU9: 0 | EV9: Tanque de expansão | EW9: Sim | EX9: Sim | EY9: Sala de ordenha com fosso | EZ9: Sim | FA9: Sim | FB9: Mecânica | FC9: 2 | FD9: 2 | FE9: De 2 em 2 dias | FF9: Plantada | FG9: Brachiaria, Tifton | FH9: Sim | FO9: Sim | FQ9: Correção e adubação do solo na implantação, Controle de plantas invasoras, Rotação de pastagens, Divisão em piquetes | FR9: Sim | FU9: Sim | FV9: Sim | FZ9: Proprietário(a) e família | GA9: Produção de leite, Produtividade | GB9: Sim | GC9: Sim | GI9: Acompanha o fluxo de caixa e calcula periodicamente custos de produção e margens | GJ9: Sim | GK9: 2.48 | GL9: Assistência técnica, Treinamento (curso, palestra, etc.), Outras mídias sociais | GM9: Sim | GO9: Sim | GR9: Sim | GS9: 25 | GT9: Cálculo do custo de produção, Alimentação do rebanho, Sanidade do rebanho | GV9: Sim | GX9: Sim | GY9: Sim | HF9: Mercado do leite, Produção de leite e meio ambiente | HI9: Sim | HO9: Sim | HR9: 0 | HS9: 100 | HT9: 0 | HU9: 0 | HV9: 0 | HW9: Galpão coberto, Sombrite ou tela de sombreamento, Cobertura vegetal (árvores, sombra natural), Ventiladores mecânicos, Aspersores ou nebulizadores, Sistema de resfriamento evaporativo, Bebedouros | HX9: Sim | HY9: Sim | HZ9: Sim | IB9: Sim | ID9: Sim | IE9: Sim | IH9: Residência e locais de produção | II9: Em toda fazenda | IJ9: Picadeira, Trator, Misturador de ração | IK9: Sim | IM9: Sim | IT9: Sim | IU9: “Raspado” e/ou armazenado | IV9: Cobertura do solo, Descarte adequado de embalagens (herbicida e defensivos) | IX9: Sim | IY9: Sim | JB9: 0 | JC9: 3 | JD9: 110 | JE9: 23 | JF9: 13 | JG9: 3 | JH9: 6 | JI9: Manqueira, Brucelose, Raiva, Enterotoxemia, Botulismo, Vermifugação, Carrapaticida, IBR/BVD, Leptospirose | JJ9: Sim | JK9: Sim | JM9: Sim | JN9: Sim | JO9: Sim | JP9: Sim | JQ9: Sim | JR9: Sim | JS9: Sim | JT9: Teste da caneca, Pré-dipping, Pós-dipping, Alimentação após a ordenha, Identificação de animais tratados com antibiótico | JU9: Sim | JV9: Sim | JW9: Sim | JZ9: Sim | KA9: Sim | KB9: Inseminação artificial/IATF | KD9: Sim | KG9: Artificial | KH9: Idade e peso das novilhas | KI9: Ano todo | KJ9: Sim | KK9: Capineira, Silagem de milho | KM9: Sim | KO9: Sim | KU9: 0.6 | KV9: 2.75 | KW9: 2.3 | KX9: 2.5 | KY9: Volume de leite entregue, Nível de CCS, Nível de CBT, Teor de gordura, Teor de proteína | KZ9: Sim | LA9: Sim | LB9: Sim | LC9: Sim | LD9: Sim | LG9: Concorda | LH9: Concorda | LI9: Concorda | LJ9: Não | LK9: Pouco importante
B10: Teixeiras | C10: Não familiar | D10: 4) 1001 a 2500 | E10: Fortemente acidentado | F10: Intensivo | G10: Alvenaria | H10: Alvenaria | I10: Madeira | J10: CAR - Cadastro Ambiental Rural, Cursos d’água/riacho/nascentes/mina, Vegetação nativa/mata/floresta, Área de preservação permanentes, Área de reserva legal, Serviço de telefonia | K10: Sim | L10: Sim | M10: Sim | N10: Sim | O10: Sim | R10: Sim | S10: 60 | T10: 24 | U10: Masculino | V10: Ensino médio completo | W10: Na cidade | X10: 60 | Y10: 40 | Z10: 0 | AA10: 0 | AB10: 0 | AC10: 0 | AD10: 90 | AE10: 10 | AF10: 0 | AG10: 0 | AH10: 0 | AI10: Não | AJ10: 10 | AK10: 0 | AL10: 0 | AM10: 0 | AN10: 90 | AO10: 95 | AP10: 5 | AQ10: 0 | AR10: Não recebe benefício do governo | BB10: Sim | BC10: Bom | BD10: Sim | BE10: Por gostar | BF10: Sim | BO10: Deficiência na qualificação da mão de obra | BQ10: Sim | CB10: Mão de obra qualificada, Sanidade do rebanho, Qualidade genética dos animais | CC10: Sim | CD10: Sim | CE10: Sim | CL10: Aumentar a produção | CM10: Filhos continuarão com a produção de leite | CN10: Não | CO10: Não utilizou crédito | CV10: Sim | CW10: Documentação pessoal incompleta, Não precisou de crédito | CX10: Sim | DB10: Sim | DD10: 1300 | DE10: 1300 | DF10: 1300 | DG10: 22 | DH10: 22 | DI10: 22 | DJ10: 94 | DK10: 0 | DL10: 0 | DM10: 0 | DN10: 6 | DO10: 80.6 | DP10: 50 | DQ10: Sim | DR10: Sim | DS10: Não | DT10: 0.098630137 | DU10: 5 | DV10: =DT10+DU10 -> 5.0986301 | DW10: 64 | DX10: 14 | DY10: 8 | DZ10: 2 | EA10: 47 | EB10: 22 | EC10: 12 | ED10: 0 | EE10: 0 | EF10: 0 | EG10: 0 | EH10: 0 | EI10: 100 | EJ10: 0 | EK10: 0 | EL10: 0 | EM10: 0 | EN10: 0 | EO10: 0 | EP10: 80 | EQ10: 20 | ER10: 0 | ES10: 0 | ET10: 0 | EU10: 0 | EV10: Tanque de expansão | EW10: Sim | EX10: Sim | EY10: Sala de ordenha com fosso | EZ10: Sim | FA10: Sim | FB10: Mecânica | FC10: 2 | FD10: 2 | FE10: De 2 em 2 dias | FF10: Plantada | FG10: Brachiaria | FH10: Sim | FQ10: Correção e adubação do solo na implantação, Controle de plantas invasoras, Rotação de pastagens, Divisão em piquetes | FR10: Sim | FU10: Sim | FV10: Sim | FZ10: Apenas o(a) proprietário(a) | GA10: Produção de leite, Produtividade, Receitas | GB10: Sim | GC10: Sim | GD10: Sim | GI10: Acompanha o fluxo de caixa e calcula periodicamente custos de produção e margens | GJ10: Sim | GK10: 2.21 | GL10: Assistência técnica | GM10: Sim | GS10: 84 | GT10: Cálculo do custo de produção, Alimentação do rebanho, Sanidade do rebanho, Melhoramento genético | GV10: Sim | GX10: Sim | GY10: Sim | HA10: Sim | HF10: Mercado do leite | HI10: Sim | HR10: 0 | HS10: 100 | HT10: 0 | HU10: 0 | HV10: 0 | HW10: Galpão coberto, Ventiladores mecânicos, Bebedouros | HX10: Sim | IB10: Sim | IE10: Sim | IH10: Residência e locais de produção | II10: Em toda fazenda | IJ10: Picadeira, Trator, Vagão forrageiro, Plantadeira, Grade, Ensiladeira, Misturador de ração | IK10: Sim | IM10: Sim | IN10: Sim | IO10: Sim | IP10: Sim | IR10: Sim | IT10: Sim | IU10: Chorumeira | IV10: Plantio direto, Cobertura do solo | IW10: Sim | IX10: Sim | JB10: 1 | JC10: 2.5 | JD10: 120 | JE10: 29.6 | JF10: 15.5 | JG10: 3 | JH10: 3 | JI10: Manqueira, Brucelose, Raiva, Enterotoxemia, Vermifugação, Carrapaticida, IBR/BVD, Leptospirose | JJ10: Sim | JK10: Sim | JM10: Sim | JN10: Sim | JP10: Sim | JQ10: Sim | JR10: Sim | JS10: Sim | JT10: Teste da caneca, Pré-dipping, Pós-dipping, Linha de ordenha, Alimentação durante a ordenha | JU10: Sim | JV10: Sim | JW10: Sim | JX10: Sim | JY10: Sim | KB10: FIV/TE, Inseminação artificial/IATF | KC10: Sim | KD10: Sim | KG10: Artificial | KH10: Idade e peso das novilhas | KI10: Ano todo | KJ10: Sim | KK10: Cana-de-açúcar, Silagem de capim, Silagem de milho | KL10: Sim | KN10: Sim | KO10: Sim | KU10: 24 | KV10: 3.25 | KW10: 2.8 | KX10: 3.25 | KY10: Volume de leite entregue, Nível de CCS, Nível de CBT, Teor de gordura, Teor de proteína | KZ10: Sim | LA10: Sim | LB10: Sim | LC10: Sim | LD10: Sim | LG10: Concorda | LH10: Concorda | LI10: Não concorda | LJ10: Sim | LK10: Muito importante
B11: Viçosa | C11: Não familiar | D11: 2) 201 a 500 | E11: Suavemente acidentado ou acidentado | F11: Semiextensivo | G11: Alvenaria | H11: Não possui | I11: Madeira | J11: CAR - Cadastro Ambiental Rural, Cursos d’água/riacho/nascentes/mina, Vegetação nativa/mata/floresta, Área de preservação permanentes, Área de reserva legal, Serviço de telefonia | K11: Sim | L11: Sim | M11: Sim | N11: Sim | O11: Sim | R11: Sim | S11: 36 | T11: 1 | U11: Masculino | V11: Ensino superior completo | W11: Na cidade | X11: 0 | Y11: 100 | Z11: 0 | AA11: 0 | AB11: 0 | AC11: 0 | AD11: 0 | AE11: 0 | AF11: 0 | AG11: 100 | AH11: 0 | AI11: Não | AJ11: 100 | AK11: 0 | AL11: 0 | AM11: 0 | AN11: 0 | AO11: 80 | AP11: 20 | AQ11: 0 | AR11: PRONAMPE | AV11: Sim | BC11: Regular | BD11: Não | BE11: Por ser uma atividade lucrativa, Por proporcionar renda mensal, Tem mercado garantido | BG11: Sim | BH11: Sim | BK11: Sim | BO11: Falta de crédito rural, com taxas de juros compatíveis com a atividade, Instabilidade de políticas públicas | BR11: Sim | BW11: Sim | CB11: Qualidade genética dos animais, Alimentação do rebanho, Conhecimento de técnicas eficientes | CE11: Sim | CF11: Sim | CJ11: Sim | CL11: Aumentar a produção | CM11: Não sabe | CN11: Sim | CO11: PRONAMPE | CR11: Sim | CW11: Utilizou crédito | DC11: Sim | DD11: 500 | DE11: 500 | DF11: 500 | DG11: 16.833333 | DH11: 16 | DI11: 18 | DJ11: 85 | DK11: 0 | DL11: 0 | DM11: 0 | DN11: 15 | DP11: 30 | DQ11: Sim | DR11: Sim | DS11: Não | DT11: 0.92054795 | DU11: 3 | DV11: =DT11+DU11 -> 3.9205479 | DW11: 41 | DX11: 8 | DY11: 1 | DZ11: 6 | EA11: 22 | EB11: 19 | EC11: 17 | ED11: 1 | EE11: 7 | EF11: 0 | EG11: 0 | EH11: 30 | EI11: 0 | EJ11: 70 | EK11: 0 | EL11: 0 | EM11: 0 | EN11: 50 | EO11: 50 | EP11: 0 | EQ11: 0 | ER11: 0 | ES11: 0 | ET11: 0 | EU11: 0 | EV11: Tanque de expansão | EW11: Sim | EX11: Sim | EY11: Sala de ordenha cimentada ou calçada | EZ11: Sim | FA11: Sim | FB11: Mecânica | FC11: 2 | FD11: 2 | FE11: De 2 em 2 dias | FF11: Plantada | FG11: Brachiaria, Panicum, Tifton | FH11: Sim | FI11: Sim | FO11: Sim | FQ11: Correção e adubação do solo na implantação, Adubação anual de cobertura, Controle de plantas invasoras, Rotação de pastagens, Divisão em piquetes, Cerca elétrica nos piquetes | FR11: Sim | FU11: Sim | FV11: Sim | FW11: Sim | FZ11: Apenas o(a) proprietário(a) | GA11: Produção de leite, Produtividade, Receitas, Despesas, Venda de animais | GB11: Sim | GC11: Sim | GD11: Sim | GE11: Sim | GG11: Sim | GI11: Utiliza os indicadores econômicos de forma sistemática para tomada de decisão | GJ11: Sim | GK11: 2.7 | GL11: Assistência técnica | GM11: Sim | GS11: 24 | GT11: Planejamento da empresa rural, Sanidade do rebanho, Manejo do rebanho | GU11: Sim | GY11: Sim | GZ11: Sim | HF11: Melhoramento genético | HM11: Sim | HR11: 0 | HS11: 0 | HT11: 0 | HU11: 100 | HV11: 0 | HW11: Aspersores ou nebulizadores | IH11: Residência e locais de produção | II11: Em toda fazenda | IJ11: Picadeira, Misturador de ração | IK11: Sim | IT11: Sim | IU11: Não tem destino certo | IV11: Plantio direto, Descarte adequado de embalagens (herbicida e defensivos) | IW11: Sim | IY11: Sim | JB11: 10 | JC11: 2.5 | JD11: 100 | JE11: 29 | JF11: 13 | JG11: 8 | JH11: 0 | JI11: Manqueira, Brucelose, Raiva, Enterotoxemia, Botulismo, Vermifugação, Carrapaticida, IBR/BVD, Leptospirose | JJ11: Sim | JK11: Sim | JM11: Sim | JN11: Sim | JO11: Sim | JP11: Sim | JQ11: Sim | JR11: Sim | JS11: Sim | JT11: Teste da caneca, Pré-dipping, Pós-dipping, Alimentação durante a ordenha, Alimentação após a ordenha | JU11: Sim | JV11: Sim | JW11: Sim | JY11: Sim | JZ11: Sim | KB11: FIV/TE, Inseminação artificial/IATF | KC11: Sim | KD11: Sim | KG11: Artificial | KH11: Peso das novilhas | KI11: Ano todo | KJ11: Sim | KK11: Cana-de-açúcar, Silagem de milho | KL11: Sim | KO11: Sim | KU11: 1 | KV11: 2.93 | KW11: 2.3 | KX11: 2.8 | KY11: Volume de leite entregue, Nível de CCS, Nível de CBT, Teor de gordura, Teor de proteína | KZ11: Sim | LA11: Sim | LB11: Sim | LC11: Sim | LD11: Sim | LG11: Não concorda | LH11: Concorda | LI11: Concorda | LJ11: Não | LK11: Muito importante
B12: Viçosa | C12: Não familiar | D12: 4) 1001 a 2500 | E12: Fortemente acidentado | F12: Intensivo | G12: Alvenaria | H12: Alvenaria | I12: Alvenaria | J12: CAR - Cadastro Ambiental Rural, Cursos d’água/riacho/nascentes/mina, Vegetação nativa/mata/floresta, Área de preservação permanentes | K12: Sim | L12: Sim | M12: Sim | N12: Sim | S12: 58 | T12: 28 | U12: Masculino | V12: Ensino fundamental completo | W12: Na propriedade rural | X12: 80 | Y12: 20 | Z12: 0 | AA12: 0 | AB12: 0 | AC12: 0 | AD12: 9 | AE12: 91 | AF12: 0 | AG12: 0 | AH12: 0 | AI12: Não | AJ12: 100 | AK12: 0 | AL12: 0 | AM12: 0 | AN12: 0 | AO12: 85 | AP12: 15 | AQ12: 0 | AR12: PRONAMPE | AV12: Sim | BC12: Regular | BD12: Sim | BE12: Por proporcionar renda mensal, Tem mercado garantido | BH12: Sim | BK12: Sim | BO12: Custo dos insumos, Instabilidade de políticas públicas | BU12: Sim | BW12: Sim | CB12: Qualidade genética dos animais, Manejo do rebanho, Reprodução do rebanho | CE12: Sim | CG12: Sim | CH12: Sim | CL12: Continuar como está | CM12: Propriedade será vendida | CN12: Sim | CO12: PRONAMPE | CR12: Sim | CW12: Utilizou crédito | DC12: Sim | DD12: 1500 | DE12: 1500 | DF12: 1500 | DG12: 28 | DH12: 28 | DI12: 28 | DJ12: 97.4 | DK12: 0 | DL12: 0 | DM12: 0.1 | DN12: 2.5 | DO12: 40 | DP12: 46 | DQ12: Sim | DR12: Sim | DS12: Não | DT12: 1.2328767 | DU12: 2 | DV12: =DT12+DU12 -> 3.2328767 | DW12: 56 | DX12: 11 | DY12: 7 | DZ12: 0 | EA12: 16 | EB12: 19 | EC12: 0 | ED12: 1 | EE12: 0 | EF12: 0 | EG12: 0 | EH12: 0 | EI12: 0 | EJ12: 100 | EK12: 0 | EL12: 0 | EM12: 0 | EN12: 0 | EO12: 0 | EP12: 0 | EQ12: 100 | ER12: 0 | ES12: 0 | ET12: 0 | EU12: 0 | EV12: Tanque de expansão | EW12: Sim | EX12: Sim | EY12: Sala de ordenha com fosso | EZ12: Sim | FA12: Sim | FB12: Mecânica | FC12: 3 | FD12: 3 | FE12: De 2 em 2 dias | FF12: Plantada | FG12: Brachiaria | FH12: Sim | FQ12: Correção e adubação do solo na implantação, Controle de plantas invasoras, Rotação de pastagens, Divisão em piquetes | FR12: Sim | FU12: Sim | FV12: Sim | FZ12: Apenas o(a) proprietário(a) | GA12: Não estabelece metas | GH12: Sim | GI12: Utiliza os indicadores econômicos de forma sistemática para tomada de decisão | GJ12: Sim | GK12: 2.1 | GL12: Assistência técnica, Treinamento (curso, palestra, etc.), Outras mídias sociais | GM12: Sim | GO12: Sim | GR12: Sim | GS12: 24 | GT12: Alimentação do rebanho, Melhoramento genético, Qualidade do leite | GX12: Sim | HA12: Sim | HD12: Sim | HF12: Mercado do leite | HI12: Sim | HR12: 0 | HS12: 100 | HT12: 0 | HU12: 0 | HV12: 0 | HW12: Galpão coberto, Sombrite ou tela de sombreamento, Cobertura vegetal (árvores, sombra natural), Ventiladores mecânicos, Bebedouros | HX12: Sim | HY12: Sim | HZ12: Sim | IB12: Sim | IE12: Sim | IH12: Residência e locais de produção | II12: Em toda fazenda | IJ12: Trator, Vagão forrageiro, Misturador de ração | IM12: Sim | IN12: Sim | IT12: Sim | IU12: “Raspado” e/ou armazenado | IV12: Plantio direto, Cobertura do solo, Rotação de culturas | IW12: Sim | IX12: Sim | JA12: Sim | JB12: 0 | JC12: 3 | JD12: 120 | JE12: 30 | JF12: 13 | JG12: 3 | JH12: 1 | JI12: Manqueira, Brucelose, Raiva, Enterotoxemia, Botulismo, Vermifugação, Carrapaticida, IBR/BVD, Leptospirose | JJ12: Sim | JK12: Sim | JM12: Sim | JN12: Sim | JO12: Sim | JP12: Sim | JQ12: Sim | JR12: Sim | JS12: Sim | JT12: Teste da caneca, Pré-dipping, Pós-dipping, Linha de ordenha, Alimentação após a ordenha, Identificação de animais tratados com antibiótico | JU12: Sim | JV12: Sim | JW12: Sim | JX12: Sim | JZ12: Sim | KA12: Sim | KB12: Inseminação artificial/IATF, Natural controlada | KD12: Sim | KE12: Sim | KG12: Artificial | KH12: Peso das novilhas | KI12: Ano todo | KJ12: Sim | KK12: Silagem de milho | KO12: Sim | KU12: 20 | KV12: 2.56 | KW12: 2.3 | KX12: 2.7 | KY12: Volume de leite entregue, Nível de CCS, Nível de CBT, Teor de gordura | KZ12: Sim | LA12: Sim | LB12: Sim | LC12: Sim | LG12: Concorda | LH12: Concorda | LI12: Concorda | LJ12: Não | LK12: Não é importante
B13: Presidente Bernardes | C13: Não familiar | D13: 3) 501 a 1000 | E13: Suavemente acidentado ou acidentado | F13: Semiextensivo | G13: Alvenaria | H13: Não possui | I13: Mista | J13: CAR - Cadastro Ambiental Rural, Cursos d’água/riacho/nascentes/mina, Vegetação nativa/mata/floresta, Área de preservação permanentes, Área de reserva legal | K13: Sim | L13: Sim | M13: Sim | N13: Sim | O13: Sim | S13: 41 | T13: 18 | U13: Masculino | V13: Ensino médio completo | W13: Na propriedade rural | X13: 96 | Y13: 4 | Z13: 0 | AA13: 0 | AB13: 0 | AC13: 0 | AD13: 50 | AE13: 50 | AF13: 0 | AG13: 0 | AH13: 0 | AI13: Sim | AJ13: 90 | AK13: 3 | AL13: 0 | AM13: 7 | AN13: 0 | AO13: 80 | AP13: 20 | AQ13: 0 | AR13: Não recebe benefício do governo | BB13: Sim | BC13: Muito bom | BD13: Sim | BE13: Por gostar, Por ser uma atividade lucrativa, Tem mercado garantido | BF13: Sim | BG13: Sim | BK13: Sim | BO13: Custo dos insumos, Deficiência na infraestrutura de transporte/estradas | BU13: Sim | BV13: Sim | CB13: Alimentação do rebanho, Reprodução do rebanho | CF13: Sim | CH13: Sim | CL13: Aumentar a produção | CM13: Não sabe | CN13: Não | CO13: Não utilizou crédito | CV13: Sim | CW13: Não precisou de crédito | DB13: Sim | DD13: 658.33333 | DE13: 600 | DF13: 700 | DG13: 19.541667 | DH13: 17.5 | DI13: 21 | DJ13: 90 | DK13: 1 | DL13: 0 | DM13: 1 | DN13: 8 | DO13: 96 | DP13: 48 | DQ13: Sim | DR13: Sim | DS13: Não | DT13: 1.2328767 | DU13: 3 | DV13: =DT13+DU13 -> 4.2328767 | DW13: 34 | DX13: 4 | DY13: 2 | DZ13: 10 | EA13: 29 | EB13: 6 | EC13: 0 | ED13: 0 | EE13: 2 | EF13: 0 | EG13: 25 | EH13: 0 | EI13: 0 | EJ13: 70 | EK13: 0 | EL13: 5 | EM13: 0 | EN13: 0 | EO13: 70 | EP13: 0 | EQ13: 0 | ER13: 30 | ES13: 0 | ET13: 0 | EU13: 0 | EV13: Tanque de expansão | EW13: Sim | EX13: Sim | EY13: Sala de ordenha com fosso | EZ13: Sim | FA13: Sim | FB13: Mecânica | FC13: 2 | FD13: 2 | FE13: De 2 em 2 dias | FF13: Plantada | FG13: Brachiaria, Tifton | FH13: Sim | FO13: Sim | FQ13: Controle de plantas invasoras | FZ13: Apenas o(a) proprietário(a) | GA13: Produção de leite, Produtividade, Venda de genética | GB13: Sim | GC13: Sim | GF13: Sim | GI13: Utiliza os indicadores econômicos de forma sistemática para tomada de decisão | GJ13: Sim | GK13: 1.95 | GL13: Assistência técnica, Treinamento (curso, palestra, etc.), Outras mídias sociais | GM13: Sim | GO13: Sim | GR13: Sim | GS13: 15 | GT13: Cálculo do custo de produção, Alimentação do rebanho, Sanidade do rebanho | GV13: Sim | GX13: Sim | GY13: Sim | HF13: Mercado do leite, Produção de leite e meio ambiente | HI13: Sim | HO13: Sim | HR13: 0 | HS13: 0 | HT13: 100 | HU13: 0 | HV13: 0 | HW13: Cobertura vegetal (árvores, sombra natural), Ventiladores mecânicos, Aspersores ou nebulizadores, Sistema de resfriamento evaporativo, Bebedouros | HZ13: Sim | IB13: Sim | ID13: Sim | IE13: Sim | IH13: Residência e locais de produção | II13: Somente na residência | IJ13: Picadeira, Trator, Plantadeira, Grade, Ensiladeira, Distribuidor de calcário, Misturador de ração | IK13: Sim | IM13: Sim | IO13: Sim | IP13: Sim | IR13: Sim | IS13: Sim | IT13: Sim | IU13: “Raspado” e/ou armazenado | IV13: Descarte adequado de embalagens (herbicida e defensivos), Tratamento de efluentes da residência, Rotação de culturas | IY13: Sim | IZ13: Sim | JA13: Sim | JB13: 18 | JC13: 2.5 | JD13: 110 | JE13: 26 | JF13: 14 | JG13: 2 | JH13: 2 | JI13: Manqueira, Brucelose, Raiva, Enterotoxemia, Botulismo, Vermifugação, Carrapaticida, IBR/BVD, Leptospirose | JJ13: Sim | JK13: Sim | JM13: Sim | JN13: Sim | JO13: Sim | JP13: Sim | JQ13: Sim | JR13: Sim | JS13: Sim | JT13: Teste da caneca, Pré-dipping, Pós-dipping, Linha de ordenha, Alimentação após a ordenha | JU13: Sim | JV13: Sim | JW13: Sim | JX13: Sim | JZ13: Sim | KB13: Inseminação artificial/IATF | KD13: Sim | KG13: Natural | KH13: Idade e peso das novilhas | KI13: Ano todo | KJ13: Sim | KK13: Capineira, Silagem de milho | KM13: Sim | KO13: Sim | KU13: 7 | KV13: 2.51 | KW13: 2 | KX13: 2.7 | KY13: Nível de CCS, Nível de CBT, Teor de gordura, Teor de proteína | LA13: Sim | LB13: Sim | LC13: Sim | LD13: Sim | LG13: Concorda | LH13: Concorda | LI13: Concorda | LJ13: Não | LK13: Muito importante
B14: Teixeiras | C14: Familiar | D14: 3) 501 a 1000 | E14: Suavemente acidentado ou acidentado | F14: Intensivo | G14: Alvenaria | H14: Alvenaria | I14: Madeira | J14: CAR - Cadastro Ambiental Rural, Cursos d’água/riacho/nascentes/mina, Vegetação nativa/mata/floresta, Área de preservação permanentes, Área de reserva legal, Serviço de água potável, Serviço de telefonia | K14: Sim | L14: Sim | M14: Sim | N14: Sim | O14: Sim | P14: Sim | R14: Sim | S14: 51 | T14: 35 | U14: Masculino | V14: Ensino fundamental incompleto | W14: Na propriedade rural | X14: 60 | Y14: 40 | Z14: 0 | AA14: 0 | AB14: 0 | AC14: 0 | AD14: 60 | AE14: 40 | AF14: 0 | AG14: 0 | AH14: 0 | AI14: Não | AJ14: 95 | AK14: 5 | AL14: 0 | AM14: 0 | AN14: 0 | AO14: 100 | AP14: 0 | AQ14: 0 | AR14: PRONAF | AU14: Sim | BC14: Regular | BD14: Não | BE14: Por proporcionar renda mensal, A atividade leiteira é uma tradição na família, Combina com outras explorações da propriedade | BH14: Sim | BI14: Sim | BJ14: Sim | BO14: Falta de mão de obra, Falta de crédito rural, com taxas de juros compatíveis com a atividade, Instabilidade de políticas públicas | BP14: Sim | BR14: Sim | BW14: Sim | CB14: Qualidade genética dos animais, Alimentação do rebanho, Preço do leite | CE14: Sim | CF14: Sim | CI14: Sim | CL14: Aumentar a produção | CM14: Filhos trocarão de atividade rural | CN14: Sim | CO14: PRONAMPE | CR14: Sim | CW14: Utilizou crédito | DC14: Sim | DD14: 1000 | DE14: 1000 | DF14: 1000 | DG14: 19 | DH14: 19 | DI14: 19 | DJ14: 90 | DK14: 0 | DL14: 0 | DM14: 2 | DN14: 8 | DO14: 52 | DP14: 37 | DQ14: Sim | DR14: Sim | DS14: Sim | DT14: 4.0767123 | DU14: 1 | DV14: =DT14+DU14 -> 5.0767123 | DW14: 55 | DX14: 11 | DY14: 9 | DZ14: 1 | EA14: 26 | EB14: 7 | EC14: 0 | ED14: 0 | EE14: 0 | EF14: 0 | EG14: 0 | EH14: 0 | EI14: 0 | EJ14: 100 | EK14: 0 | EL14: 0 | EM14: 0 | EN14: 0 | EO14: 0 | EP14: 50 | EQ14: 0 | ER14: 50 | ES14: 0 | ET14: 0 | EU14: 0 | EV14: Tanque de expansão | EW14: Sim | EX14: Sim | EY14: Sala de ordenha com fosso | EZ14: Sim | FA14: Sim | FB14: Mecânica | FC14: 2 | FD14: 2 | FE14: De 2 em 2 dias | FF14: Mista | FG14: Brachiaria, Capim-elefante | FH14: Sim | FJ14: Sim | FQ14: Correção e adubação do solo na implantação, Adubação anual de cobertura, Controle de plantas invasoras | FR14: Sim | FZ14: Proprietário(a) e família | GA14: Produção de leite, Produtividade, Receitas, Despesas | GB14: Sim | GC14: Sim | GD14: Sim | GE14: Sim | GI14: Utiliza os indicadores econômicos de forma sistemática para tomada de decisão | GJ14: Sim | GK14: 2.37 | GL14: Assistência técnica | GM14: Sim | GS14: 36 | GT14: Alimentação do rebanho, Sanidade do rebanho, Qualidade do leite | GX14: Sim | GY14: Sim | HD14: Sim | HF14: Planejamento da empresa rural, Mercado do leite, Melhoramento genético | HG14: Sim | HI14: Sim | HM14: Sim | HR14: 0 | HS14: 100 | HT14: 0 | HU14: 0 | HV14: 0 | HW14: Galpão coberto, Exaustores ou sistemas de ventilação forçada, Ventiladores mecânicos, Bebedouros | HX14: Sim | IA14: Sim | IB14: Sim | IE14: Sim | IH14: Residência e locais de produção | II14: Em toda fazenda | IJ14: Picadeira, Trator, Plantadeira, Grade, Ensiladeira, Misturador de ração | IK14: Sim | IM14: Sim | IO14: Sim | IP14: Sim | IR14: Sim | IT14: Sim | IU14: Composteira | IV14: Plantio direto, Cobertura do solo, Descarte adequado de embalagens (herbicida e defensivos) | IW14: Sim | IX14: Sim | IY14: Sim | JB14: 1 | JC14: 3 | JD14: 100 | JE14: 27 | JF14: 14 | JG14: 3 | JH14: 0 | JI14: Manqueira, Brucelose, Raiva, Vermifugação, IBR/BVD, Leptospirose | JJ14: Sim | JK14: Sim | JM14: Sim | JP14: Sim | JR14: Sim | JS14: Sim | JT14: Teste da caneca, Pré-dipping, Pós-dipping, Alimentação após a ordenha, Identificação de animais tratados com antibiótico | JU14: Sim | JV14: Sim | JW14: Sim | JZ14: Sim | KA14: Sim | KB14: Inseminação artificial/IATF | KD14: Sim | KG14: Artificial | KH14: Idade e peso das novilhas | KI14: Ano todo | KJ14: Sim | KK14: Capineira, Silagem de milho | KM14: Sim | KO14: Sim | KU14: 4 | KV14: 2.5 | KW14: 2.2 | KX14: 2.5 | KY14: Volume de leite entregue, Nível de CCS, Nível de CBT | KZ14: Sim | LA14: Sim | LB14: Sim | LG14: Concorda | LH14: Concorda | LI14: Não concorda | LJ14: Não | LK14: Muito importante
B15: Porto Firme | C15: Não familiar | D15: 4) 1001 a 2500 | E15: Suavemente acidentado ou acidentado | F15: Semiextensivo | G15: Mista | H15: Mista | I15: Mista | J15: CAR - Cadastro Ambiental Rural, Cursos d’água/riacho/nascentes/mina, Vegetação nativa/mata/floresta, Área de preservação permanentes, Área de reserva legal, Serviço de água potável, Serviço de esgoto doméstico tratado, Serviço de telefonia | K15: Sim | L15: Sim | M15: Sim | N15: Sim | O15: Sim | P15: Sim | Q15: Sim | R15: Sim | S15: 63 | T15: 50 | U15: Masculino | V15: Ensino médio completo | W15: Na propriedade rural | X15: 70 | Y15: 30 | Z15: 0 | AA15: 0 | AB15: 0 | AC15: 0 | AD15: 100 | AE15: 0 | AF15: 0 | AG15: 0 | AH15: 0 | AI15: Não | AJ15: 50 | AK15: 0 | AL15: 0 | AM15: 0 | AN15: 50 | AO15: 60 | AP15: 20 | AQ15: 20 | AR15: Não recebe benefício do governo | BB15: Sim | BC15: Regular | BD15: Sim | BE15: Por gostar, Por ser uma atividade lucrativa, A atividade leiteira é uma tradição na família | BF15: Sim | BG15: Sim | BI15: Sim | BO15: Falta de mão de obra, Falta de crédito rural, com taxas de juros compatíveis com a atividade, Custo dos insumos | BP15: Sim | BR15: Sim | BU15: Sim | CB15: Sanidade do rebanho, Alimentação do rebanho, Manejo do rebanho | CD15: Sim | CF15: Sim | CG15: Sim | CL15: Aumentar a produção | CM15: Filhos continuarão com a produção de leite | CN15: Sim | CO15: PRONAMPE | CR15: Sim | CW15: Utilizou crédito | DC15: Sim | DD15: 1155 | DE15: 1160 | DF15: 1150 | DG15: 21 | DH15: 21 | DI15: 21 | DJ15: 93 | DK15: 0 | DL15: 0 | DM15: 2 | DN15: 5 | DO15: 38 | DP15: 30 | DQ15: Sim | DR15: Sim | DS15: Sim | DT15: 0.55479452 | DU15: 3.1643836 | DV15: =DT15+DU15 -> 3.7191781 | DW15: 45 | DX15: 15 | DY15: 21 | DZ15: 2 | EA15: 45 | EB15: 24 | EC15: 0 | ED15: 0 | EE15: 1 | EF15: 0 | EG15: 0 | EH15: 60 | EI15: 0 | EJ15: 20 | EK15: 0 | EL15: 20 | EM15: 0 | EN15: 0 | EO15: 0 | EP15: 60 | EQ15: 0 | ER15: 30 | ES15: 0 | ET15: 10 | EU15: 0 | EV15: Tanque de expansão | EW15: Sim | EX15: Sim | EY15: Sala de ordenha com fosso | EZ15: Sim | FA15: Sim | FB15: Mecânica | FC15: 2 | FD15: 2 | FE15: De 2 em 2 dias | FF15: Plantada | FG15: Brachiaria, Capim-elefante | FH15: Sim | FJ15: Sim | FQ15: Correção e adubação do solo na implantação, Adubação anual de cobertura, Divisão em piquetes, Cerca elétrica nos piquetes | FR15: Sim | FV15: Sim | FW15: Sim | FZ15: Proprietário(a) e família | GA15: Produção de leite, Produtividade, Receitas, Despesas | GB15: Sim | GC15: Sim | GD15: Sim | GE15: Sim | GI15: Utiliza os indicadores econômicos de forma sistemática para tomada de decisão | GJ15: Sim | GK15: 2.2 | GL15: Assistência técnica, Vizinho, amigo ou parente | GM15: Sim | GN15: Sim | GS15: 36 | GT15: Cálculo do custo de produção, Sanidade do rebanho, Qualidade do leite | GV15: Sim | GY15: Sim | HD15: Sim | HF15: Planejamento da empresa rural, Cálculo do custo de produção, Melhoramento genético | HG15: Sim | HH15: Sim | HM15: Sim | HR15: 0 | HS15: 0 | HT15: 100 | HU15: 0 | HV15: 0 | HW15: Sombrite ou tela de sombreamento, Cobertura vegetal (árvores, sombra natural), Exaustores ou sistemas de ventilação forçada, Ventiladores mecânicos, Aspersores ou nebulizadores, Sistema de resfriamento evaporativo, Bebedouros | HY15: Sim | HZ15: Sim | IA15: Sim | IB15: Sim | ID15: Sim | IE15: Sim | IH15: Residência e locais de produção | II15: Em toda fazenda | IJ15: Picadeira, Trator, Misturador de ração | IK15: Sim | IM15: Sim | IT15: Sim | IU15: “Raspado” e/ou armazenado | IV15: Plantio direto, Cobertura do solo, Descarte adequado de embalagens (herbicida e defensivos), Tratamento de efluentes da residência, Rotação de culturas | IW15: Sim | IX15: Sim | IY15: Sim | IZ15: Sim | JA15: Sim | JB15: 0 | JC15: 3 | JD15: 100 | JE15: 27 | JF15: 419 | JG15: 2 | JH15: 1 | JI15: Manqueira, Brucelose, Raiva, Vermifugação, Carrapaticida, IBR/BVD, Leptospirose | JJ15: Sim | JK15: Sim | JM15: Sim | JP15: Sim | JQ15: Sim | JR15: Sim | JS15: Sim | JT15: Teste da caneca, Pré-dipping, Pós-dipping, Linha de ordenha, Alimentação após a ordenha, Identificação de animais tratados com antibiótico | JU15: Sim | JV15: Sim | JW15: Sim | JX15: Sim | JZ15: Sim | KA15: Sim | KB15: FIV/TE, Inseminação artificial/IATF | KC15: Sim | KD15: Sim | KG15: Artificial | KH15: Idade e peso das novilhas | KI15: Ano todo | KJ15: Sim | KK15: Cana-de-açúcar, Capineira, Silagem de capim, Silagem de milho | KL15: Sim | KM15: Sim | KN15: Sim | KO15: Sim | KU15: 20 | KV15: 3.15 | KW15: 2.9 | KX15: 3 | KY15: Nível de CCS, Nível de CBT, Teor de gordura, Teor de proteína | LA15: Sim | LB15: Sim | LC15: Sim | LD15: Sim | LG15: Concorda | LH15: Concorda | LI15: Concorda | LJ15: Sim | LK15: Muito importante
B16: Canaã | C16: Familiar | D16: 4) 1001 a 2500 | E16: Suavemente acidentado ou acidentado | F16: Intensivo | G16: Mista | H16: Não possui | I16: Alvenaria | J16: CAR - Cadastro Ambiental Rural, Área de preservação permanentes, Área de reserva legal | K16: Sim | N16: Sim | O16: Sim | S16: 40 | T16: 22 | U16: Masculino | V16: Ensino médio incompleto | W16: Na propriedade rural | X16: 20 | Y16: 80 | Z16: 0 | AA16: 0 | AB16: 0 | AC16: 0 | AD16: 0 | AE16: 0 | AF16: 0 | AG16: 0 | AH16: 100 | AI16: Não | AJ16: 100 | AK16: 0 | AL16: 0 | AM16: 0 | AN16: 0 | AO16: 99 | AP16: 1 | AQ16: 0 | AR16: PRONAF | AU16: Sim | BC16: Bom | BD16: Sim | BE16: Por gostar, Por proporcionar renda mensal | BF16: Sim | BH16: Sim | BO16: Falta de mão de obra, Instabilidade de políticas públicas | BP16: Sim | BW16: Sim | CB16: Qualidade genética dos animais, Alimentação do rebanho, Manejo do rebanho | CE16: Sim | CF16: Sim | CG16: Sim | CL16: Aumentar a produção | CM16: Filhos continuarão com a produção de leite | CN16: Não | CO16: Não utilizou crédito | CV16: Sim | CW16: Não precisou de crédito | DB16: Sim | DD16: 1916.6667 | DE16: 1800 | DF16: 2000 | DG16: 32.916667 | DH16: 30 | DI16: 35 | DJ16: 91.9 | DK16: 0 | DL16: 0 | DM16: 0.1 | DN16: 8 | DO16: 6 | DP16: 0.17 | DQ16: Sim | DR16: Sim | DS16: Não | DT16: 1.4794521 | DU16: 2 | DV16: =DT16+DU16 -> 3.4794521 | DW16: 70 | DX16: 7 | DY16: 14 | DZ16: 0 | EA16: 36 | EB16: 35 | EC16: 0 | ED16: 0 | EE16: 0 | EF16: 0 | EG16: 0 | EH16: 0 | EI16: 0 | EJ16: 100 | EK16: 0 | EL16: 0 | EM16: 0 | EN16: 0 | EO16: 0 | EP16: 0 | EQ16: 100 | ER16: 0 | ES16: 0 | ET16: 0 | EU16: 0 | EV16: Tanque de expansão | EW16: Não | EX16: Sim | EY16: Sala de ordenha cimentada ou calçada | EZ16: Sim | FA16: Sim | FB16: Mecânica | FC16: 2 | FD16: 2 | FE16: De 2 em 2 dias | FF16: Não tem pastagem | FG16: Não tem pastagem plantada | FP16: Sim | FQ16: Não utiliza pastagens | FY16: Sim | FZ16: Apenas o(a) proprietário(a) | GA16: Produtividade, Receitas, Despesas | GC16: Sim | GD16: Sim | GE16: Sim | GI16: Acompanha o fluxo de caixa e calcula periodicamente custos de produção e margens | GJ16: Sim | GK16: 2 | GL16: Assistência técnica | GM16: Sim | GS16: 36 | GT16: Cálculo do custo de produção, Alimentação do rebanho, Sanidade do rebanho | GV16: Sim | GX16: Sim | GY16: Sim | HF16: Mercado do leite | HI16: Sim | HR16: 0 | HS16: 100 | HT16: 0 | HU16: 0 | HV16: 0 | HW16: Galpão coberto, Ventiladores mecânicos, Bebedouros | HX16: Sim | IB16: Sim | IE16: Sim | IH16: Residência e locais de produção | II16: Somente na residência | IJ16: Picadeira, Trator, Vagão forrageiro | IK16: Sim | IM16: Sim | IN16: Sim | IU16: “Raspado” e/ou armazenado | IV16: Descarte adequado de embalagens (herbicida e defensivos) | IY16: Sim | JB16: 0 | JC16: 3 | JD16: 90 | JE16: 21 | JF16: 14 | JG16: 2 | JH16: 1 | JI16: Manqueira, Brucelose, Raiva, Enterotoxemia, Botulismo, Vermifugação, IBR/BVD, Leptospirose | JJ16: Sim | JK16: Sim | JM16: Sim | JN16: Sim | JO16: Sim | JP16: Sim | JR16: Sim | JS16: Sim | JT16: Pré-dipping, Pós-dipping | JV16: Sim | JW16: Sim | KB16: Inseminação artificial/IATF | KD16: Sim | KG16: Artificial | KH16: Idade e peso das novilhas | KI16: Ano todo | KJ16: Sim | KK16: Cana-de-açúcar, Capineira, Silagem de milho | KL16: Sim | KM16: Sim | KO16: Sim | KU16: 12 | KV16: 2.65 | KW16: 2.4 | KX16: 2.7 | KY16: Volume de leite entregue, Nível de CCS, Nível de CBT, Teor de gordura | KZ16: Sim | LA16: Sim | LB16: Sim | LC16: Sim | LG16: Concorda | LH16: Concorda | LI16: Concorda | LJ16: Não | LK16: Muito importante
B17: Canaã | C17: Familiar | D17: 3) 501 a 1000 | E17: Suavemente acidentado ou acidentado | F17: Intensivo | G17: Mista | H17: Não possui | I17: Alvenaria | J17: Área de reserva legal | O17: Sim | S17: 47 | T17: 14 | U17: Masculino | V17: Ensino médio completo | W17: Na propriedade rural | X17: 100 | Y17: 0 | Z17: 0 | AA17: 0 | AB17: 0 | AC17: 0 | AD17: 0 | AE17: 100 | AF17: 0 | AG17: 0 | AH17: 0 | AI17: Não | AJ17: 100 | AK17: 0 | AL17: 0 | AM17: 0 | AN17: 0 | AO17: 90 | AP17: 10 | AQ17: 0 | AR17: PRONAF | AU17: Sim | BC17: Bom | BD17: Sim | BE17: Por gostar, Por ser uma atividade lucrativa, Por proporcionar renda mensal | BF17: Sim | BG17: Sim | BH17: Sim | BO17: Falta de mão de obra, Falta de crédito rural, com taxas de juros compatíveis com a atividade, Custo dos insumos | BP17: Sim | BR17: Sim | BU17: Sim | CB17: Qualidade genética dos animais, Reprodução do rebanho, Preço do leite | CE17: Sim | CH17: Sim | CI17: Sim | CL17: Continuar como está | CM17: Filhos continuarão com a produção de leite | CN17: Sim | CO17: PRONAF | CP17: Sim | CW17: Utilizou crédito | DC17: Sim | DD17: 900 | DE17: 900 | DF17: 900 | DG17: 35 | DH17: 35 | DI17: 35 | DJ17: 95.5 | DK17: 0 | DL17: 0 | DM17: 4 | DN17: 0.5 | DO17: 5.7 | DP17: 0.5 | DQ17: Sim | DR17: Sim | DS17: Não | DT17: 1.7260274 | DU17: 1 | DV17: =DT17+DU17 -> 2.7260274 | DW17: 41 | DX17: 5 | DY17: 8 | DZ17: 0 | EA17: 18 | EB17: 19 | EC17: 0 | ED17: 1 | EE17: 0 | EF17: 0 | EG17: 0 | EH17: 0 | EI17: 0 | EJ17: 100 | EK17: 0 | EL17: 0 | EM17: 0 | EN17: 0 | EO17: 0 | EP17: 20 | EQ17: 0 | ER17: 80 | ES17: 0 | ET17: 0 | EU17: 0 | EV17: Tanque de expansão | EW17: Sim | EX17: Sim | EY17: Sala de ordenha com fosso | EZ17: Sim | FA17: Sim | FB17: Mecânica | FC17: 2 | FD17: 2 | FE17: De 2 em 2 dias | FF17: Não tem pastagem | FG17: Não tem pastagem plantada | FP17: Sim | FQ17: Não utiliza pastagens | FY17: Sim | FZ17: Apenas o(a) proprietário(a) | GA17: Produção de leite, Produtividade, Receitas, Despesas | GB17: Sim | GC17: Sim | GD17: Sim | GE17: Sim | GI17: Utiliza os indicadores econômicos de forma sistemática para tomada de decisão | GJ17: Sim | GK17: 1.8 | GL17: Assistência técnica, Vizinho, amigo ou parente | GM17: Sim | GN17: Sim | GS17: 36 | GT17: Alimentação do rebanho, Sanidade do rebanho | GX17: Sim | GY17: Sim | HF17: Mercado do leite | HI17: Sim | HR17: 0 | HS17: 100 | HT17: 0 | HU17: 0 | HV17: 0 | HW17: Galpão coberto, Ventiladores mecânicos | HX17: Sim | IB17: Sim | IH17: Residência e locais de produção | II17: Somente na residência | IJ17: Picadeira, Trator, Vagão forrageiro, Misturador de ração | IK17: Sim | IM17: Sim | IN17: Sim | IT17: Sim | IU17: “Raspado” e/ou armazenado | IV17: Descarte adequado de embalagens (herbicida e defensivos) | IY17: Sim | JB17: 0 | JC17: 3 | JD17: 120 | JE17: 25 | JF17: 14 | JG17: 0 | JH17: 0 | JI17: Manqueira, Brucelose, Paratifo, Raiva, Enterotoxemia, Botulismo, Vermifugação, IBR/BVD, Leptospirose | JJ17: Sim | JK17: Sim | JL17: Sim | JM17: Sim | JN17: Sim | JO17: Sim | JP17: Sim | JR17: Sim | JS17: Sim | JT17: Pré-dipping, Pós-dipping | JV17: Sim | JW17: Sim | KB17: Inseminação artificial/IATF | KD17: Sim | KG17: Artificial | KH17: Idade e peso das novilhas | KI17: Ano todo | KJ17: Sim | KK17: Capineira, Silagem de milho | KM17: Sim | KO17: Sim | KU17: 12 | KV17: 2.56 | KW17: 2.5 | KX17: 2.7 | KY17: Volume de leite entregue, Nível de CCS, Nível de CBT, Teor de gordura | KZ17: Sim | LA17: Sim | LB17: Sim | LC17: Sim | LG17: Concorda | LH17: Concorda | LI17: Não concorda | LJ17: Não | LK17: Pouco importante
B18: Ubari | C18: Não familiar | D18: 2) 201 a 500 | E18: Fortemente acidentado | F18: Intensivo | G18: Alvenaria | H18: Não possui | I18: Alvenaria | J18: Nenhum dos anteriores | S18: 49 | T18: 4 | U18: Masculino | V18: Ensino superior incompleto | W18: Na cidade | X18: 100 | Y18: 0 | Z18: 0 | AA18: 0 | AB18: 0 | AC18: 0 | AD18: 0 | AE18: 100 | AF18: 0 | AG18: 0 | AH18: 0 | AI18: Não | AJ18: 100 | AK18: 0 | AL18: 0 | AM18: 0 | AN18: 0 | AO18: 90 | AP18: 10 | AQ18: 0 | AR18: Não recebe benefício do governo | BB18: Sim | BC18: Regular | BD18: Sim | BE18: Por gostar, Por ser uma atividade lucrativa | BF18: Sim | BG18: Sim | BO18: Baixa capacidade de endividamento | BZ18: Sim | CB18: Qualidade genética dos animais, Reprodução do rebanho, Preço do leite | CE18: Sim | CH18: Sim | CI18: Sim | CL18: Aumentar a produção | CM18: Filhos continuarão com a produção de leite | CN18: Não | CO18: Não utilizou crédito | CV18: Sim | CW18: Não tem capacidade para endividamento | CZ18: Sim | DD18: 450 | DE18: 450 | DF18: 450 | DG18: 23 | DH18: 23 | DI18: 23 | DJ18: 94 | DK18: 0 | DL18: 0 | DM18: 1 | DN18: 5 | DO18: 3 | DP18: 12 | DQ18: Sim | DR18: Sim | DS18: Não | DT18: 1.1506849 | DU18: 1.5 | DV18: =DT18+DU18 -> 2.6506849 | DW18: 18 | DX18: 4 | DY18: 3 | DZ18: 0 | EA18: 9 | EB18: 9 | EC18: 0 | ED18: 0 | EE18: 0 | EF18: 0 | EG18: 0 | EH18: 75 | EI18: 0 | EJ18: 25 | EK18: 0 | EL18: 0 | EM18: 0 | EN18: 15 | EO18: 30 | EP18: 50 | EQ18: 5 | ER18: 0 | ES18: 0 | ET18: 0 | EU18: 0 | EV18: Tanque de expansão | EW18: Sim | EX18: Sim | EY18: Sala de ordenha com fosso | EZ18: Sim | FA18: Sim | FB18: Mecânica | FC18: 2 | FD18: 2 | FE18: De 2 em 2 dias | FF18: Plantada | FG18: Brachiaria | FH18: Sim | FQ18: Nenhuma das anteriores | FX18: Sim | FZ18: Proprietário(a) e família | GA18: Produção de leite, Despesas | GB18: Sim | GE18: Sim | GI18: Acompanha o fluxo de caixa e calcula periodicamente custos de produção e margens | GJ18: Sim | GK18: 2.2 | GL18: Assistência técnica, Outras mídias sociais | GM18: Sim | GR18: Sim | GS18: 5 | GT18: Cálculo do custo de produção, Alimentação do rebanho | GV18: Sim | GX18: Sim | HF18: Planejamento da empresa rural | HG18: Sim | HR18: 0 | HS18: 100 | HT18: 0 | HU18: 0 | HV18: 0 | HW18: Galpão coberto, Aspersores ou nebulizadores, Bebedouros | HX18: Sim | IE18: Sim | IH18: Residência e locais de produção | II18: Somente na residência | IJ18: Trator, Ensiladeira | IM18: Sim | IR18: Sim | IU18: “Raspado” e/ou armazenado | IV18: Descarte adequado de embalagens (herbicida e defensivos), Tratamento de efluentes da residência, Rotação de culturas | IY18: Sim | IZ18: Sim | JA18: Sim | JB18: 0.2 | JC18: 2.8 | JD18: 100 | JE18: 24 | JF18: 14 | JG18: 0 | JH18: 0 | JI18: Manqueira, Brucelose, Raiva, Enterotoxemia, Botulismo, Vermifugação, Carrapaticida, IBR/BVD, Leptospirose | JJ18: Sim | JK18: Sim | JM18: Sim | JN18: Sim | JO18: Sim | JP18: Sim | JQ18: Sim | JR18: Sim | JS18: Sim | JT18: Teste da caneca, Pré-dipping, Pós-dipping, Alimentação após a ordenha | JU18: Sim | JV18: Sim | JW18: Sim | JZ18: Sim | KB18: FIV/TE, Inseminação artificial/IATF, Natural controlada | KC18: Sim | KD18: Sim | KE18: Sim | KG18: Artificial | KH18: Idade e peso das novilhas | KI18: Ano todo | KJ18: Sim | KK18: Silagem de milho, Silagem de sorgo, Feno | KO18: Sim | KP18: Sim | KU18: 1 | KV18: 2.75 | KW18: 2.5 | KX18: 2.5 | KZ18: Sim | LA18: Sim | LB18: Sim | LC18: Sim | LG18: Concorda | LH18: Concorda | LI18: Não concorda | LJ18: Não | LK18: Muito importante
B19: Paula Cândido | C19: Familiar | D19: 1) Até 200 | E19: Suavemente acidentado ou acidentado | F19: Semiextensivo | G19: Não possui | H19: Não possui | I19: Alvenaria | J19: CAR - Cadastro Ambiental Rural, Cursos d’água/riacho/nascentes/mina, Vegetação nativa/mata/floresta, Área de preservação permanentes, Serviço de água potável | K19: Sim | L19: Sim | M19: Sim | N19: Sim | P19: Sim | S19: 25 | T19: 0.2 | U19: Feminino | V19: Ensino superior completo | W19: Na propriedade rural | X19: 100 | Y19: 0 | Z19: 0 | AA19: 0 | AB19: 0 | AC19: 0 | AD19: 0 | AE19: 100 | AF19: 0 | AG19: 0 | AH19: 0 | AI19: Não | AJ19: 100 | AK19: 0 | AL19: 0 | AM19: 0 | AN19: 0 | AO19: 100 | AP19: 0 | AQ19: 0 | AR19: Não recebe benefício do governo | BB19: Sim | BC19: Bom | BD19: Sim | BE19: Por gostar, Tem mercado garantido, Outro | BF19: Sim | BK19: Sim | BO19: Deficiência na qualificação da mão de obra | BQ19: Sim | CB19: Alimentação do rebanho, Reprodução do rebanho, Conhecimento de técnicas eficientes | CF19: Sim | CH19: Sim | CJ19: Sim | CL19: Aumentar a produção | CM19: Não sabe | CN19: Não | CO19: Não utilizou crédito | CV19: Sim | CW19: Não precisou de crédito | DB19: Sim | DD19: 130 | DE19: 130 | DF19: 130 | DG19: 11.5 | DH19: 11.5 | DI19: 11.5 | DJ19: 100 | DK19: 0 | DL19: 0 | DM19: 0 | DN19: 0 | DO19: 36 | DP19: 26 | DQ19: Sim | DR19: Não | DS19: Não | DT19: 1.4794521 | DU19: 0 | DV19: =DT19+DU19 -> 1.4794521 | DW19: 13 | DX19: 10 | DY19: 2 | DZ19: 1 | EA19: 2 | EB19: 1 | EC19: 0 | ED19: 0 | EE19: 1 | EF19: 0 | EG19: 0 | EH19: 0 | EI19: 0 | EJ19: 100 | EK19: 0 | EL19: 0 | EM19: 0 | EN19: 80 | EO19: 10 | EP19: 0 | EQ19: 0 | ER19: 0 | ES19: 0 | ET19: 0 | EU19: 10 | EV19: Leite não é resfriado na fazenda | EW19: Sim | EX19: Sim | EY19: Sala de ordenha cimentada ou calçada | EZ19: Sim | FA19: Sim | FB19: Mecânica | FC19: 2 | FD19: 2 | FE19: De 2 em 2 dias | FF19: Plantada | FG19: Brachiaria | FH19: Sim | FQ19: Correção e adubação do solo na implantação | FR19: Sim | FZ19: Proprietário(a) e família | GA19: Produção de leite, Produtividade | GB19: Sim | GC19: Sim | GI19: Acompanha o fluxo de caixa e calcula periodicamente custos de produção e margens | GJ19: Sim | GK19: 1.8 | GL19: Assistência técnica, Treinamento (curso, palestra, etc.) | GM19: Sim | GO19: Sim | GS19: 5 | GT19: Alimentação do rebanho, Sanidade do rebanho, Melhoramento genético | GX19: Sim | GY19: Sim | HA19: Sim | HF19: Cálculo do custo de produção, Sanidade do rebanho, Melhoramento genético | HH19: Sim | HK19: Sim | HM19: Sim | HR19: 0 | HS19: 0 | HT19: 100 | HU19: 0 | HV19: 0 | HW19: Galpão coberto, Cobertura vegetal (árvores, sombra natural), Bebedouros | HX19: Sim | HZ19: Sim | IE19: Sim | IH19: Residência e locais de produção | II19: Não tem acesso à internet | IJ19: Nenhum dos anteriores | IU19: “Raspado” e/ou armazenado | IV19: Plantio direto, Cobertura do solo, Descarte adequado de embalagens (herbicida e defensivos) | IW19: Sim | IX19: Sim | IY19: Sim | JB19: 0.1 | JC19: 2.5 | JD19: 80 | JE19: 26 | JF19: 14 | JG19: 0 | JH19: 0 | JI19: Raiva, Vermifugação, Carrapaticida, IBR/BVD, Leptospirose | JK19: Sim | JM19: Sim | JP19: Sim | JQ19: Sim | JR19: Sim | JS19: Sim | JT19: Teste da caneca, Pré-dipping, Pós-dipping, Linha de ordenha, Alimentação durante a ordenha | JU19: Sim | JV19: Sim | JW19: Sim | JX19: Sim | JY19: Sim | KB19: Inseminação artificial/IATF | KD19: Sim | KG19: Artificial | KH19: Peso das novilhas | KI19: Ano todo | KJ19: Sim | KK19: Capineira, Silagem de sorgo | KM19: Sim | KP19: Sim | KU19: 0.2 | KV19: 2.64 | KW19: 2.5 | KX19: 2.5 | KY19: Volume de leite entregue, Nível de CCS, Nível de CBT, Teor de gordura, Teor de proteína | KZ19: Sim | LA19: Sim | LB19: Sim | LC19: Sim | LD19: Sim | LG19: Não concorda | LH19: Concorda | LI19: Concorda | LJ19: Sim | LK19: Muito importante
B20: Viçosa | C20: Familiar | D20: 3) 501 a 1000 | E20: Suavemente acidentado ou acidentado | F20: Intensivo | G20: Alvenaria | H20: Não possui | I20: Madeira | J20: CAR - Cadastro Ambiental Rural, Serviço de telefonia | K20: Sim | R20: Sim | S20: 36 | T20: 10 | U20: Masculino | V20: Ensino médio completo | W20: Na propriedade rural | X20: 5 | Y20: 95 | Z20: 0 | AA20: 0 | AB20: 0 | AC20: 0 | AD20: 100 | AE20: 0 | AF20: 0 | AG20: 0 | AH20: 0 | AI20: Não | AJ20: 98 | AK20: 2 | AL20: 0 | AM20: 0 | AN20: 0 | AO20: 93 | AP20: 7 | AQ20: 0 | AR20: PRONAF, PRONAMPE | AU20: Sim | AV20: Sim | BC20: Regular | BD20: Não | BE20: Por gostar, Por ser uma atividade lucrativa | BF20: Sim | BG20: Sim | BO20: Falta de mão de obra, Custo dos insumos | BP20: Sim | BU20: Sim | CB20: Qualidade genética dos animais, Reprodução do rebanho | CE20: Sim | CH20: Sim | CL20: Aumentar a produção | CM20: Não sabe | CN20: Sim | CO20: PRONAMPE | CR20: Sim | CW20: Utilizou crédito | DC20: Sim | DD20: 733.33333 | DE20: 500 | DF20: 900 | DG20: 29.083333 | DH20: 25 | DI20: 32 | DJ20: 92 | DK20: 0 | DL20: 0 | DM20: 0.3 | DN20: 7.7 | DO20: 1.5 | DP20: 1.5 | DQ20: Sim | DR20: Sim | DS20: Não | DT20: 1.5001644 | DU20: 1 | DV20: =DT20+DU20 -> 2.5001644 | DW20: 40 | DX20: 7 | DY20: 8 | DZ20: 1 | EA20: 10 | EB20: 8 | EC20: 0 | ED20: 0 | EE20: 1 | EF20: 0 | EG20: 0 | EH20: 0 | EI20: 0 | EJ20: 100 | EK20: 0 | EL20: 0 | EM20: 0 | EN20: 0 | EO20: 0 | EP20: 0 | EQ20: 0 | ER20: 100 | ES20: 0 | ET20: 0 | EU20: 0 | EV20: Tanque de expansão | EW20: Sim | EX20: Sim | EY20: Sala de ordenha com fosso | EZ20: Sim | FA20: Sim | FB20: Mecânica | FC20: 2 | FD20: 2 | FE20: Todos os dias | FF20: Não tem pastagem | FG20: Não tem pastagem plantada | FP20: Sim | FQ20: Não utiliza pastagens | FY20: Sim | FZ20: Apenas o(a) proprietário(a) | GA20: Produção de leite, Produtividade, Despesas, Venda de animais | GB20: Sim | GC20: Sim | GE20: Sim | GG20: Sim | GI20: Acompanha o fluxo de caixa e calcula periodicamente custos de produção e margens | GJ20: Não | GL20: Assistência técnica, Treinamento (curso, palestra, etc.) | GM20: Sim | GO20: Sim | GS20: 36 | GT20: Alimentação do rebanho, Sanidade do rebanho, Gerenciamento da produção | GX20: Sim | GY20: Sim | HB20: Sim | HF20: Mercado do leite | HI20: Sim | HR20: 0 | HS20: 100 | HT20: 0 | HU20: 0 | HV20: 0 | HW20: Galpão coberto, Ventiladores mecânicos, Bebedouros | HX20: Sim | IB20: Sim | IE20: Sim | IH20: Residência e locais de produção | II20: Em toda fazenda | IJ20: Trator, Vagão forrageiro, Plantadeira, Grade, Ensiladeira | IM20: Sim | IN20: Sim | IO20: Sim | IP20: Sim | IR20: Sim | IU20: Chorumeira | IV20: Descarte adequado de embalagens (herbicida e defensivos) | IY20: Sim | JB20: 0 | JC20: 3 | JD20: 100 | JE20: 26 | JF20: 14 | JG20: 0 | JH20: 0 | JI20: Manqueira, Brucelose, Raiva, Botulismo, Vermifugação, Carrapaticida, IBR/BVD, Leptospirose | JJ20: Sim | JK20: Sim | JM20: Sim | JO20: Sim | JP20: Sim | JQ20: Sim | JR20: Sim | JS20: Sim | JT20: Teste da caneca, Pré-dipping, Pós-dipping, Alimentação após a ordenha, Identificação de animais tratados com antibiótico | JU20: Sim | JV20: Sim | JW20: Sim | JZ20: Sim | KA20: Sim | KB20: Inseminação artificial/IATF | KD20: Sim | KG20: Artificial | KH20: Peso das novilhas | KI20: Ano todo | KJ20: Sim | KK20: Silagem de milho | KO20: Sim | KU20: 2 | KV20: 2.86 | KW20: 2.2 | KX20: 2.9 | KY20: Volume de leite entregue, Nível de CCS, Nível de CBT, Teor de gordura | KZ20: Sim | LA20: Sim | LB20: Sim | LC20: Sim | LG20: Concorda | LH20: Concorda | LI20: Concorda | LJ20: Não | LK20: Muito importante
B21: Piranga | C21: Não familiar | D21: 4) 1001 a 2500 | E21: Suavemente acidentado ou acidentado | F21: Intensivo | G21: Alvenaria | H21: Alvenaria | I21: Madeira | J21: CAR - Cadastro Ambiental Rural, Cursos d’água/riacho/nascentes/mina, Vegetação nativa/mata/floresta, Área de preservação permanentes, Área de reserva legal, Serviço de água potável, Serviço de esgoto doméstico tratado, Serviço de telefonia | K21: Sim | L21: Sim | M21: Sim | N21: Sim | O21: Sim | P21: Sim | Q21: Sim | R21: Sim | S21: 32 | T21: 10 | U21: Feminino | V21: Pós-graduação | W21: Na cidade | X21: 69 | Y21: 31 | Z21: 0 | AA21: 0 | AB21: 0 | AC21: 0 | AD21: 100 | AE21: 0 | AF21: 0 | AG21: 0 | AH21: 0 | AI21: Sim | AJ21: 70 | AK21: 25 | AL21: 5 | AM21: 0 | AN21: 0 | AO21: 83.65 | AP21: 16.35 | AQ21: 0 | AR21: PRONAMPE | AV21: Sim | BC21: Bom | BD21: Sim | BE21: Por gostar, Por ser uma atividade lucrativa, A atividade leiteira é uma tradição na família | BF21: Sim | BG21: Sim | BI21: Sim | BO21: Falta de mão de obra, Falta de crédito rural, com taxas de juros compatíveis com a atividade, Instabilidade de políticas públicas | BP21: Sim | BR21: Sim | BW21: Sim | CB21: Mão de obra qualificada, Qualidade genética dos animais, Preço do leite | CC21: Sim | CE21: Sim | CI21: Sim | CL21: Aumentar a produção | CM21: Não sabe | CN21: Sim | CO21: PRONAMPE | CR21: Sim | CW21: Utilizou crédito | DC21: Sim | DD21: 1745.8333 | DE21: 1600 | DF21: 1850 | DG21: 20.583333 | DH21: 20 | DI21: 21 | DJ21: 95.9 | DK21: 0 | DL21: 0 | DM21: 0.1 | DN21: 4 | DO21: 300 | DP21: 43 | DQ21: Sim | DR21: Não | DS21: Não | DT21: 2.9589041 | DU21: 8 | DV21: =DT21+DU21 -> 10.958904 | DW21: 63 | DX21: 19 | DY21: 15 | DZ21: 5 | EA21: 48 | EB21: 21 | EC21: 0 | ED21: 1 | EE21: 0 | EF21: 1 | EG21: 9 | EH21: 0 | EI21: 0 | EJ21: 90 | EK21: 0 | EL21: 0 | EM21: 0 | EN21: 0 | EO21: 30 | EP21: 70 | EQ21: 0 | ER21: 0 | ES21: 0 | ET21: 0 | EU21: 0 | EV21: Tanque de expansão | EW21: Sim | EX21: Sim | EY21: Sala de ordenha com fosso | EZ21: Sim | FA21: Sim | FB21: Mecânica | FC21: 2 | FD21: 2 | FE21: De 2 em 2 dias | FF21: Plantada | FG21: Brachiaria, Cynodon | FH21: Sim | FN21: Sim | FQ21: Correção e adubação do solo na implantação, Controle de plantas invasoras, Rotação de pastagens | FR21: Sim | FU21: Sim | FZ21: Proprietário(a) e família | GA21: Produção de leite, Produtividade, Receitas, Despesas, Venda de genética, Venda de animais | GB21: Sim | GC21: Sim | GD21: Sim | GE21: Sim | GF21: Sim | GG21: Sim | GI21: Utiliza os indicadores econômicos de forma sistemática para tomada de decisão | GJ21: Sim | GK21: 2.3 | GL21: Assistência técnica, Treinamento (curso, palestra, etc.), Outras mídias sociais | GM21: Sim | GO21: Sim | GR21: Sim | GS21: 80 | GT21: Alimentação do rebanho, Manejo do rebanho, Qualidade do leite | GX21: Sim | GZ21: Sim | HD21: Sim | HF21: Mercado do leite | HI21: Sim | HR21: 0 | HS21: 75 | HT21: 25 | HU21: 0 | HV21: 0 | HW21: Galpão coberto, Cobertura vegetal (árvores, sombra natural), Ventiladores mecânicos, Aspersores ou nebulizadores, Sistema de resfriamento evaporativo, Bebedouros, Controle automatizado de temperatura/umidade | HX21: Sim | HZ21: Sim | IB21: Sim | ID21: Sim | IE21: Sim | IF21: Sim | IH21: Residência e locais de produção | II21: Em toda fazenda | IJ21: Balança para os animais, Trator, Vagão forrageiro, Plantadeira, Grade, Arado, Ensiladeira, Distribuidor de calcário, Misturador de ração | IL21: Sim | IM21: Sim | IN21: Sim | IO21: Sim | IP21: Sim | IQ21: Sim | IR21: Sim | IS21: Sim | IT21: Sim | IU21: “Raspado” e/ou armazenado | IV21: Tratamento de efluentes da residência | IZ21: Sim | JB21: 24 | JC21: 3 | JD21: 110 | JE21: 28 | JF21: 14 | JG21: 0 | JH21: 3 | JI21: Manqueira, Brucelose, Paratifo, Raiva, Enterotoxemia, Botulismo, Vermifugação, Carrapaticida, IBR/BVD, Leptospirose | JJ21: Sim | JK21: Sim | JL21: Sim | JM21: Sim | JN21: Sim | JO21: Sim | JP21: Sim | JQ21: Sim | JR21: Sim | JS21: Sim | JT21: Teste da caneca, Pré-dipping, Pós-dipping, Linha de ordenha, Alimentação após a ordenha, Identificação de animais tratados com antibiótico | JU21: Sim | JV21: Sim | JW21: Sim | JX21: Sim | JZ21: Sim | KA21: Sim | KB21: FIV/TE, Inseminação artificial/IATF, Natural controlada | KC21: Sim | KD21: Sim | KE21: Sim | KG21: Artificial | KH21: Peso das novilhas | KI21: Ano todo | KJ21: Sim | KK21: Cana-de-açúcar, Silagem de milho | KL21: Sim | KO21: Sim | KU21: 28 | KV21: 2.82 | KW21: 2.35 | KX21: 2.9 | KY21: Volume de leite entregue, Nível de CCS, Nível de CBT, Teor de gordura, Teor de proteína, Critérios de sustentabilidade e BPA | KZ21: Sim | LA21: Sim | LB21: Sim | LC21: Sim | LD21: Sim | LE21: Sim | LG21: Concorda | LH21: Concorda | LI21: Concorda | LJ21: Não | LK21: Não é importante
B22: Piranga | C22: Não familiar | D22: 2) 201 a 500 | E22: Suavemente acidentado ou acidentado | F22: Semiextensivo | G22: Alvenaria | H22: Não possui | I22: Mista | J22: CAR - Cadastro Ambiental Rural, Cursos d’água/riacho/nascentes/mina, Vegetação nativa/mata/floresta, Área de preservação permanentes, Área de reserva legal, Serviço de telefonia | K22: Sim | L22: Sim | M22: Sim | N22: Sim | O22: Sim | R22: Sim | S22: 39 | T22: 4 | U22: Masculino | V22: Ensino médio completo | W22: Na cidade | X22: 80 | Y22: 20 | Z22: 0 | AA22: 0 | AB22: 0 | AC22: 0 | AD22: 0 | AE22: 0 | AF22: 0 | AG22: 0 | AH22: 100 | AI22: Não | AJ22: 65 | AK22: 35 | AL22: 0 | AM22: 0 | AN22: 0 | AO22: 90 | AP22: 10 | AQ22: 0 | AR22: Não recebe benefício do governo | BB22: Sim | BC22: Bom | BD22: Sim | BE22: Por proporcionar renda mensal | BH22: Sim | BO22: Não sabe | CA22: Sim | CB22: Manejo do rebanho, Preço do leite | CG22: Sim | CI22: Sim | CL22: Aumentar a produção | CM22: Não sabe | CN22: Não | CO22: Não utilizou crédito | CV22: Sim | CW22: Dificuldade para obter financiamento | DA22: Sim | DD22: 350 | DE22: 350 | DF22: 350 | DG22: 17.166667 | DH22: 16 | DI22: 18 | DJ22: 84 | DK22: 5 | DL22: 0 | DM22: 0 | DN22: 11 | DO22: 90 | DP22: 30 | DQ22: Sim | DR22: Sim | DS22: Não | DT22: 0.85479452 | DU22: 1 | DV22: =DT22+DU22 -> 1.8547945 | DW22: 23 | DX22: 5 | DY22: 2 | DZ22: 3 | EA22: 3 | EB22: 5 | EC22: 0 | ED22: 1 | EE22: 1 | EF22: 0 | EG22: 0 | EH22: 0 | EI22: 0 | EJ22: 0 | EK22: 0 | EL22: 100 | EM22: 0 | EN22: 0 | EO22: 50 | EP22: 50 | EQ22: 0 | ER22: 0 | ES22: 0 | ET22: 0 | EU22: 0 | EV22: Tanque de expansão | EW22: Sim | EX22: Sim | EY22: Sala de ordenha cimentada ou calçada | EZ22: Sim | FA22: Sim | FB22: Mecânica | FC22: 2 | FD22: 2 | FE22: De 2 em 2 dias | FF22: Plantada | FG22: Brachiaria | FH22: Sim | FQ22: Controle de plantas invasoras | FZ22: Apenas o(a) proprietário(a) | GA22: Produção de leite | GB22: Sim | GI22: Utiliza os indicadores econômicos de forma sistemática para tomada de decisão | GJ22: Sim | GK22: 2.58 | GL22: Assistência técnica | GM22: Sim | GS22: 26 | GT22: Planejamento da empresa rural, Cálculo do custo de produção, Sanidade do rebanho, Manejo do rebanho | GU22: Sim | GV22: Sim | GY22: Sim | GZ22: Sim | HF22: Não sabe | HQ22: Sim | HR22: 0 | HS22: 0 | HT22: 100 | HU22: 0 | HV22: 0 | HW22: Cobertura vegetal (árvores, sombra natural), Bebedouros | HZ22: Sim | IE22: Sim | IH22: Residência e locais de produção | II22: Somente na residência | IJ22: Picadeira, Trator, Plantadeira, Ensiladeira | IK22: Sim | IM22: Sim | IO22: Sim | IR22: Sim | IU22: Não tem destino certo | IV22: Nenhuma das anteriores | JB22: 3 | JC22: 3 | JD22: 100 | JE22: 27 | JF22: 13 | JG22: 3 | JH22: 3 | JI22: Manqueira, Brucelose, Raiva, Enterotoxemia, Botulismo, Vermifugação, Carrapaticida, IBR/BVD, Leptospirose | JJ22: Sim | JK22: Sim | JM22: Sim | JN22: Sim | JO22: Sim | JP22: Sim | JQ22: Sim | JR22: Sim | JS22: Sim | JT22: Teste da caneca, Pré-dipping, Pós-dipping, Linha de ordenha, Identificação de animais tratados com antibiótico | JU22: Sim | JV22: Sim | JW22: Sim | JX22: Sim | KA22: Sim | KB22: Inseminação artificial/IATF, Natural controlada | KD22: Sim | KE22: Sim | KG22: Artificial | KH22: Idade e peso das novilhas | KI22: Ano todo | KJ22: Sim | KK22: Cana-de-açúcar, Capineira, Silagem de milho | KL22: Sim | KM22: Sim | KO22: Sim | KU22: 4 | KV22: 2.45 | KW22: 1.99 | KX22: 2.55 | KY22: Volume de leite entregue, Nível de CCS, Nível de CBT, Teor de gordura, Teor de proteína | KZ22: Sim | LA22: Sim | LB22: Sim | LC22: Sim | LD22: Sim | LG22: Não sabe | LH22: Concorda | LI22: Concorda | LJ22: Não | LK22: Não sabe
B23: Coimbra | C23: Familiar | D23: 2) 201 a 500 | E23: Suavemente acidentado ou acidentado | F23: Intensivo | G23: Alvenaria | H23: Não possui | I23: Alvenaria | J23: CAR - Cadastro Ambiental Rural, Cursos d’água/riacho/nascentes/mina, Vegetação nativa/mata/floresta, Área de preservação permanentes, Área de reserva legal, Serviço de telefonia | K23: Sim | L23: Sim | M23: Sim | N23: Sim | O23: Sim | R23: Sim | S23: 25 | T23: 5 | U23: Masculino | V23: Ensino fundamental completo | W23: Na propriedade rural | X23: 70 | Y23: 30 | Z23: 0 | AA23: 0 | AB23: 0 | AC23: 0 | AD23: 100 | AE23: 0 | AF23: 0 | AG23: 0 | AH23: 0 | AI23: Não | AJ23: 70 | AK23: 0 | AL23: 0 | AM23: 15 | AN23: 15 | AO23: 95 | AP23: 5 | AQ23: 0 | AR23: Não recebe benefício do governo | BB23: Sim | BC23: Regular | BD23: Sim | BE23: Por gostar, Por proporcionar renda mensal, Combina com outras explorações da propriedade | BF23: Sim | BH23: Sim | BJ23: Sim | BO23: Custo dos insumos | BU23: Sim | CB23: Qualidade genética dos animais, Alimentação do rebanho, Conhecimento de técnicas eficientes | CE23: Sim | CF23: Sim | CJ23: Sim | CL23: Aumentar a produção | CM23: Não sabe | CN23: Não | CO23: Não utilizou crédito | CV23: Sim | CW23: Não precisou de crédito | DB23: Sim | DD23: 400 | DE23: 400 | DF23: 400 | DG23: 27.916667 | DH23: 25 | DI23: 30 | DJ23: 95 | DK23: 0 | DL23: 0 | DM23: 1 | DN23: 4 | DO23: 12 | DP23: 16.5 | DQ23: Sim | DR23: Não | DS23: Não | DT23: 1.4794521 | DU23: 0 | DV23: =DT23+DU23 -> 1.4794521 | DW23: 15 | DX23: 2 | DY23: 3 | DZ23: 0 | EA23: 10 | EB23: 8 | EC23: 0 | ED23: 0 | EE23: 1 | EF23: 0 | EG23: 60 | EH23: 40 | EI23: 0 | EJ23: 0 | EK23: 0 | EL23: 0 | EM23: 0 | EN23: 0 | EO23: 60 | EP23: 40 | EQ23: 0 | ER23: 0 | ES23: 0 | ET23: 0 | EU23: 0 | EV23: Tanque de expansão | EW23: Sim | EX23: Sim | EY23: Sala de ordenha com fosso | EZ23: Sim | FA23: Sim | FB23: Mecânica | FC23: 2 | FD23: 2 | FE23: De 2 em 2 dias | FF23: Plantada | FG23: Brachiaria, Panicum | FH23: Sim | FI23: Sim | FQ23: Controle de plantas invasoras | FZ23: Apenas o(a) proprietário(a) | GA23: Produção de leite, Produtividade | GB23: Sim | GC23: Sim | GI23: Utiliza os indicadores econômicos de forma sistemática para tomada de decisão | GJ23: Sim | GK23: 2.35 | GL23: Assistência técnica, Treinamento (curso, palestra, etc.), Outras mídias sociais | GM23: Sim | GO23: Sim | GR23: Sim | GS23: 36 | GT23: Alimentação do rebanho, Qualidade do leite | GX23: Sim | HD23: Sim | HF23: Mercado do leite | HI23: Sim | HR23: 0 | HS23: 100 | HT23: 0 | HU23: 0 | HV23: 0 | HW23: Galpão coberto, Ventiladores mecânicos, Bebedouros | HX23: Sim | IB23: Sim | IE23: Sim | IH23: Residência e locais de produção | II23: Somente na residência | IJ23: Picadeira, Misturador de ração | IK23: Sim | IT23: Sim | IU23: Composteira | IV23: Plantio direto, Cobertura do solo, Descarte adequado de embalagens (herbicida e defensivos), Rotação de culturas | IW23: Sim | IX23: Sim | IY23: Sim | JA23: Sim | JB23: 0 | JC23: 3 | JD23: 100 | JE23: 23 | JF23: 12 | JG23: 0 | JH23: 3 | JI23: Manqueira, Brucelose, Raiva, Botulismo, Vermifugação, Carrapaticida, IBR/BVD, Leptospirose | JJ23: Sim | JK23: Sim | JM23: Sim | JO23: Sim | JP23: Sim | JQ23: Sim | JR23: Sim | JS23: Sim | JT23: Teste da caneca, Pré-dipping, Pós-dipping, Linha de ordenha, Alimentação após a ordenha | JU23: Sim | JV23: Sim | JW23: Sim | JX23: Sim | JZ23: Sim | KB23: Inseminação artificial/IATF | KD23: Sim | KG23: Artificial | KH23: Idade e peso das novilhas | KI23: Ano todo | KJ23: Sim | KK23: Silagem de milho | KO23: Sim | KU23: 5 | KV23: 2.8 | KW23: 2.3 | KX23: 2.9 | KY23: Nível de CCS, Nível de CBT, Teor de gordura, Teor de proteína | LA23: Sim | LB23: Sim | LC23: Sim | LD23: Sim | LG23: Não concorda | LH23: Concorda | LI23: Concorda | LJ23: Não | LK23: Muito importante
B24: Guiricema | C24: Não familiar | D24: 3) 501 a 1000 | E24: Suavemente acidentado ou acidentado | F24: Semiextensivo | G24: Alvenaria | H24: Alvenaria | I24: Alvenaria | J24: CAR - Cadastro Ambiental Rural, Cursos d’água/riacho/nascentes/mina, Vegetação nativa/mata/floresta, Área de preservação permanentes | K24: Sim | L24: Sim | M24: Sim | N24: Sim | S24: 45 | T24: 23 | U24: Masculino | V24: Ensino médio completo | W24: Na cidade | X24: 0 | Y24: 0 | Z24: 0 | AA24: 100 | AB24: 0 | AC24: 0 | AI24: Não | AJ24: 60 | AK24: 15 | AL24: 15 | AM24: 0 | AN24: 10 | AR24: Não recebe benefício do governo | BB24: Sim | BC24: Ruim | BD24: Não | BE24: A atividade leiteira é uma tradição na família, Combina com outras explorações da propriedade, Tem mercado garantido | BI24: Sim | BJ24: Sim | BK24: Sim | BO24: Deficiência na qualificação da mão de obra, Custo dos insumos, Deficiência na infraestrutura de transporte/estradas | BQ24: Sim | BU24: Sim | BV24: Sim | CB24: Mão de obra qualificada, Sanidade do rebanho, Conhecimento de técnicas eficientes | CC24: Sim | CD24: Sim | CJ24: Sim | CL24: Não sabe | CM24: Não sabe | CN24: Sim | CO24: Plano Safra | CT24: Sim | CW24: Utilizou crédito | DC24: Sim | DD24: 530 | DE24: 530 | DF24: 530 | DG24: 18.9 | DH24: 18.9 | DI24: 18.9 | DJ24: 95 | DK24: 0 | DL24: 0 | DM24: 1 | DN24: 4 | DO24: 47 | DP24: 23 | DQ24: Sim | DR24: Sim | DS24: Não | DT24: 0.24657534 | DU24: 2 | DV24: =DU24+DT24 -> 2.2465753 | DW24: 28 | DX24: 7 | DY24: 7 | DZ24: 4 | EA24: 11 | EB24: 13 | EC24: 0 | ED24: 2 | EE24: 0 | EF24: 0 | EG24: 0 | EH24: 0 | EI24: 0 | EJ24: 0 | EK24: 0 | EL24: 100 | EM24: 0 | EN24: 0 | EO24: 50 | EP24: 50 | EQ24: 0 | ER24: 0 | ES24: 0 | ET24: 0 | EU24: 0 | EV24: Tanque de expansão | EW24: Sim | EX24: Sim | EY24: Sala de ordenha com fosso | EZ24: Sim | FA24: Sim | FB24: Mecânica | FC24: 2 | FD24: 2 | FE24: De 2 em 2 dias | FF24: Plantada | FG24: Brachiaria, Panicum | FH24: Sim | FI24: Sim | FQ24: Adubação anual de cobertura, Controle de plantas invasoras, Rotação de pastagens, Divisão em piquetes, Cerca elétrica nos piquetes | FU24: Sim | FV24: Sim | FW24: Sim | FZ24: Apenas o(a) proprietário(a) | GA24: Não estabelece metas | GH24: Sim | GI24: Utiliza os indicadores econômicos de forma sistemática para tomada de decisão | GJ24: Sim | GK24: 2.16 | GL24: Assistência técnica, Outras mídias sociais | GM24: Sim | GR24: Sim | GS24: 12 | GT24: Cálculo do custo de produção, Alimentação do rebanho, Melhoramento genético | GV24: Sim | GX24: Sim | HA24: Sim | HF24: Não sabe | HQ24: Sim | HR24: 0 | HS24: 0 | HT24: 75 | HU24: 0 | HV24: 25 | HW24: Cobertura vegetal (árvores, sombra natural), Bebedouros | HZ24: Sim | IE24: Sim | IH24: Residência e locais de produção | II24: Somente na residência | IJ24: Picadeira, Trator, Distribuidor de calcário, Misturador de ração | IK24: Sim | IM24: Sim | IS24: Sim | IT24: Sim | IU24: “Raspado” e/ou armazenado | IV24: Plantio direto, Cobertura do solo, Descarte adequado de embalagens (herbicida e defensivos) | IW24: Sim | IX24: Sim | IY24: Sim | JB24: 6 | JC24: 3 | JD24: 110 | JE24: 19 | JF24: 15 | JG24: 0 | JH24: 0 | JI24: Manqueira, Brucelose, Raiva, Enterotoxemia, Botulismo, Vermifugação, Carrapaticida, IBR/BVD, Leptospirose | JJ24: Sim | JK24: Sim | JM24: Sim | JN24: Sim | JO24: Sim | JP24: Sim | JQ24: Sim | JR24: Sim | JS24: Sim | JT24: Teste da caneca, Pré-dipping, Pós-dipping, Linha de ordenha, Alimentação após a ordenha, Identificação de animais tratados com antibiótico | JU24: Sim | JV24: Sim | JW24: Sim | JX24: Sim | JZ24: Sim | KA24: Sim | KB24: FIV/TE, Inseminação artificial/IATF, Natural controlada | KC24: Sim | KD24: Sim | KE24: Sim | KG24: Artificial | KH24: Idade e peso das novilhas | KI24: Ano todo | KJ24: Sim | KK24: Cana-de-açúcar, Capineira, Silagem de milho | KL24: Sim | KM24: Sim | KO24: Sim | KU24: 8 | KV24: 2.45 | KW24: 2.3 | KX24: 2.7 | KY24: Volume de leite entregue, Nível de CCS, Nível de CBT | KZ24: Sim | LA24: Sim | LB24: Sim | LG24: Não concorda | LH24: Concorda | LI24: Concorda | LJ24: Não | LK24: Muito importante
B25: Presidente Bernardes | C25: Familiar | D25: 2) 201 a 500 | E25: Suavemente acidentado ou acidentado | F25: Semiextensivo | G25: Alvenaria | H25: Não possui | I25: Alvenaria | J25: CAR - Cadastro Ambiental Rural, Cursos d’água/riacho/nascentes/mina, Vegetação nativa/mata/floresta, Área de preservação permanentes, Área de reserva legal | K25: Sim | L25: Sim | M25: Sim | N25: Sim | O25: Sim | S25: 59 | T25: 16 | U25: Masculino | V25: Ensino superior completo | W25: Na propriedade rural | X25: 100 | Y25: 0 | Z25: 0 | AA25: 0 | AB25: 0 | AC25: 0 | AD25: 10 | AE25: 90 | AF25: 0 | AG25: 0 | AH25: 0 | AI25: Sim | AJ25: 80 | AK25: 0 | AL25: 0 | AM25: 0 | AN25: 20 | AR25: Não recebe benefício do governo | BB25: Sim | BC25: Bom | BD25: Não | BE25: Por gostar, A atividade leiteira é uma tradição na família | BF25: Sim | BI25: Sim | BO25: Falta de mão de obra, Custo dos insumos, Legislação ambiental | BP25: Sim | BU25: Sim | BX25: Sim | CB25: Sanidade do rebanho, Qualidade genética dos animais, Manejo do rebanho | CD25: Sim | CE25: Sim | CG25: Sim | CL25: Aumentar a produção | CM25: Filhos continuarão com a produção de leite | CN25: Sim | CO25: PRONAF | CP25: Sim | CW25: Utilizou crédito | DC25: Sim | DD25: 450 | DE25: 450 | DF25: 450 | DG25: 15 | DH25: 15 | DI25: 15 | DJ25: 100 | DK25: 0 | DL25: 0 | DM25: 0 | DN25: 0 | DO25: 65 | DP25: 49 | DQ25: Sim | DR25: Sim | DS25: Sim | DT25: 3.4273973 | DU25: 1 | DV25: =DU25+DT25 -> 4.4273973 | DW25: 32 | DX25: 16 | DY25: 4 | DZ25: 1 | EA25: 44 | EB25: 4 | EC25: 0 | ED25: 1 | EE25: 1 | EF25: 0 | EG25: 0 | EH25: 0 | EI25: 25 | EJ25: 25 | EK25: 0 | EL25: 50 | EM25: 0 | EN25: 0 | EO25: 50 | EP25: 50 | EQ25: 0 | ER25: 0 | ES25: 0 | ET25: 0 | EU25: 0 | EV25: Tanque de expansão | EW25: Sim | EX25: Sim | EY25: Sala de ordenha com fosso | EZ25: Sim | FA25: Sim | FB25: Mecânica | FC25: 2 | FD25: 2 | FE25: De 2 em 2 dias | FF25: Mista | FG25: Brachiaria, Capim-elefante | FH25: Sim | FJ25: Sim | FQ25: Controle de plantas invasoras, Divisão em piquetes | FV25: Sim | FZ25: Proprietário(a) e família | GA25: Produção de leite, Produtividade, Venda de genética | GB25: Sim | GC25: Sim | GF25: Sim | GI25: Acompanha o fluxo de caixa e calcula periodicamente custos de produção e margens | GJ25: Não | GL25: Assistência técnica, Treinamento (curso, palestra, etc.), Outras mídias sociais | GM25: Sim | GO25: Sim | GR25: Sim | GS25: 24 | GT25: Alimentação do rebanho, Sanidade do rebanho, Manejo do rebanho | GX25: Sim | GY25: Sim | GZ25: Sim | HF25: Planejamento da empresa rural, Melhoramento genético, Gerenciamento da produção | HG25: Sim | HM25: Sim | HN25: Sim | HR25: 0 | HS25: 0 | HT25: 100 | HU25: 0 | HV25: 0 | HW25: Cobertura vegetal (árvores, sombra natural), Bebedouros | HZ25: Sim | IE25: Sim | IH25: Residência e locais de produção | II25: Somente na residência | IJ25: Picadeira, Trator, Vagão forrageiro, Plantadeira, Grade, Arado, Ensiladeira, Distribuidor de calcário, Misturador de ração | IK25: Sim | IM25: Sim | IN25: Sim | IO25: Sim | IP25: Sim | IQ25: Sim | IR25: Sim | IS25: Sim | IT25: Sim | IU25: Chorumeira | IV25: Plantio direto, Cobertura do solo | IW25: Sim | IX25: Sim | JB25: 3 | JC25: 3 | JD25: 90 | JE25: 30 | JF25: 15 | JG25: 12 | JH25: 1 | JI25: Manqueira, Brucelose, Raiva, Botulismo, Vermifugação, Carrapaticida, IBR/BVD, Leptospirose | JJ25: Sim | JK25: Sim | JM25: Sim | JO25: Sim | JP25: Sim | JQ25: Sim | JR25: Sim | JS25: Sim | JT25: Teste da caneca, Pré-dipping, Pós-dipping, Linha de ordenha, Alimentação após a ordenha, Identificação de animais tratados com antibiótico | JU25: Sim | JV25: Sim | JW25: Sim | JX25: Sim | JZ25: Sim | KA25: Sim | KB25: FIV/TE, Inseminação artificial/IATF, Natural controlada | KC25: Sim | KD25: Sim | KE25: Sim | KG25: Artificial | KH25: Peso das novilhas | KI25: Ano todo | KJ25: Sim | KK25: Capineira, Silagem de capim, Silagem de milho | KM25: Sim | KN25: Sim | KO25: Sim | KU25: 5 | KV25: 2.6 | KW25: 2.57 | KX25: 2.79 | KY25: Nível de CCS, Nível de CBT, Teor de gordura, Teor de proteína | LA25: Sim | LB25: Sim | LC25: Sim | LD25: Sim | LG25: Concorda | LH25: Concorda | LI25: Não concorda | LJ25: Sim | LK25: Muito importante
B26: Coimbra | C26: Não familiar | D26: 5) Acima de 2501 | E26: Suavemente acidentado ou acidentado | F26: Intensivo | G26: Alvenaria | H26: Alvenaria | I26: Alvenaria | J26: CAR - Cadastro Ambiental Rural, Cursos d’água/riacho/nascentes/mina, Vegetação nativa/mata/floresta, Área de preservação permanentes, Área de reserva legal | K26: Sim | L26: Sim | M26: Sim | N26: Sim | O26: Sim | S26: 71 | T26: 28 | U26: Masculino | V26: Ensino médio completo | W26: Na cidade | X26: 100 | Y26: 0 | Z26: 0 | AA26: 0 | AB26: 0 | AC26: 0 | AD26: 0 | AE26: 100 | AF26: 0 | AG26: 0 | AH26: 0 | AI26: Não | AJ26: 13 | AK26: 2 | AL26: 18 | AM26: 2 | AN26: 65 | AR26: Não recebe benefício do governo | BB26: Sim | BC26: Bom | BD26: Sim | BE26: Por gostar, Por ser uma atividade lucrativa, Combina com outras explorações da propriedade | BF26: Sim | BG26: Sim | BJ26: Sim | BO26: Falta de mão de obra, Deficiência na qualificação da mão de obra | BP26: Sim | BQ26: Sim | CB26: Sanidade do rebanho, Alimentação do rebanho, Manejo do rebanho | CD26: Sim | CF26: Sim | CG26: Sim | CL26: Aumentar a produção | CM26: Filhos continuarão com a produção de leite | CN26: Sim | CO26: Cooperativas de crédito ou bancos privados | CS26: Sim | CW26: Utilizou crédito | DC26: Sim | DD26: 6500 | DE26: 6500 | DF26: 6500 | DG26: 30 | DH26: 30 | DI26: 30 | DJ26: 99 | DK26: 0 | DL26: 0 | DM26: 0.5 | DN26: 0.5 | DO26: 170 | DP26: 120 | DQ26: Sim | DR26: Sim | DS26: Sim | DT26: 0.27123288 | DU26: 9 | DV26: =DU26+DT26 -> 9.2712329 | DW26: 244 | DX26: 34 | DY26: 19 | DZ26: 6 | EA26: 67 | EB26: 97 | EC26: 0 | ED26: 0 | EE26: 1 | EF26: 0 | EG26: 0 | EH26: 0 | EI26: 0 | EJ26: 100 | EK26: 0 | EL26: 0 | EM26: 0 | EN26: 0 | EO26: 0 | EP26: 15 | EQ26: 85 | ER26: 0 | ES26: 0 | ET26: 0 | EU26: 0 | EV26: Tanque de expansão | EW26: Sim | EX26: Sim | EY26: Sala de ordenha com fosso | EZ26: Sim | FA26: Sim | FB26: Mecânica | FC26: 2 | FD26: 2 | FE26: Todos os dias | FF26: Plantada | FG26: Brachiaria | FH26: Sim | FQ26: Divisão em piquetes | FV26: Sim | FZ26: Proprietário(a) e família | GA26: Não estabelece metas | GH26: Sim | GI26: Utiliza os indicadores econômicos de forma sistemática para tomada de decisão | GJ26: Sim | GK26: 2.16 | GL26: Assistência técnica, Treinamento (curso, palestra, etc.), Outras mídias sociais | GM26: Sim | GO26: Sim | GR26: Sim | GS26: 72 | GT26: Alimentação do rebanho, Sanidade do rebanho, Melhoramento genético | GX26: Sim | GY26: Sim | HA26: Sim | HF26: Cálculo do custo de produção, Mercado do leite, Qualidade do leite | HH26: Sim | HI26: Sim | HP26: Sim | HR26: 0 | HS26: 100 | HT26: 0 | HU26: 0 | HV26: 0 | HW26: Galpão coberto, Ventiladores mecânicos, Aspersores ou nebulizadores, Piso emborrachado ou drenante nas áreas de espera, Bebedouros | HX26: Sim | IB26: Sim | IE26: Sim | IG26: Sim | IH26: Residência e locais de produção | II26: Em toda fazenda | IJ26: Trator, Vagão forrageiro, Plantadeira, Grade, Ensiladeira, Distribuidor de calcário, Misturador de ração | IM26: Sim | IN26: Sim | IO26: Sim | IP26: Sim | IR26: Sim | IS26: Sim | IT26: Sim | IU26: “Raspado” e/ou armazenado | IV26: Plantio direto, Cobertura do solo, Descarte adequado de embalagens (herbicida e defensivos) | IW26: Sim | IX26: Sim | IY26: Sim | JB26: 18 | JC26: 2.5 | JD26: 100 | JE26: 29 | JF26: 15 | JG26: 9.4 | JH26: 11.5 | JI26: Manqueira, Brucelose, Raiva, Botulismo, Vermifugação, Carrapaticida, IBR/BVD, Leptospirose | JJ26: Sim | JK26: Sim | JM26: Sim | JO26: Sim | JP26: Sim | JQ26: Sim | JR26: Sim | JS26: Sim | JT26: Teste da caneca, Pré-dipping, Pós-dipping, Alimentação após a ordenha, Identificação de animais tratados com antibiótico | JU26: Sim | JV26: Sim | JW26: Sim | JZ26: Sim | KA26: Sim | KB26: Inseminação artificial/IATF | KD26: Sim | KG26: Artificial | KH26: Peso das novilhas | KI26: Ano todo | KJ26: Sim | KK26: Silagem de milho | KO26: Sim | KU26: 4 | KV26: 2.5 | KW26: 3 | KX26: 2.6 | KY26: Não sabe | LF26: Sim | LG26: Concorda | LH26: Concorda | LI26: Não concorda | LJ26: Não | LK26: Não sabe
B27: Viçosa | C27: Não familiar | D27: 3) 501 a 1000 | E27: Fortemente acidentado | F27: Semiextensivo | G27: Alvenaria | H27: Alvenaria | I27: Mista | J27: CAR - Cadastro Ambiental Rural, Cursos d’água/riacho/nascentes/mina, Vegetação nativa/mata/floresta, Área de preservação permanentes, Área de reserva legal, Serviço de água potável | K27: Sim | L27: Sim | M27: Sim | N27: Sim | O27: Sim | P27: Sim | S27: 70 | T27: 10 | U27: Feminino | V27: Ensino superior completo | W27: Na cidade | X27: 100 | Y27: 0 | Z27: 0 | AA27: 0 | AB27: 0 | AC27: 0 | AD27: 100 | AE27: 0 | AF27: 0 | AG27: 0 | AH27: 0 | AI27: Não | AJ27: 95 | AK27: 0 | AL27: 0 | AM27: 0 | AN27: 5 | AR27: Não recebe benefício do governo | BB27: Sim | BC27: Regular | BD27: Não | BE27: Por gostar, Por proporcionar renda mensal, A atividade leiteira é uma tradição na família | BF27: Sim | BH27: Sim | BI27: Sim | BO27: Falta de mão de obra, Deficiência na qualificação da mão de obra | BP27: Sim | BQ27: Sim | CB27: Sanidade do rebanho, Qualidade genética dos animais, Reprodução do rebanho | CD27: Sim | CE27: Sim | CH27: Sim | CL27: Continuar como está | CM27: Filhos deixarão o meio rural | CN27: Não | CO27: PRONAF | CP27: Sim | CW27: Utilizou crédito | DC27: Sim | DD27: 800 | DE27: 800 | DF27: 800 | DG27: 26.5 | DH27: 27 | DI27: 26 | DJ27: 90 | DK27: 0 | DL27: 0 | DM27: 1 | DN27: 9 | DO27: 32 | DP27: 10 | DQ27: Não | DR27: Sim | DS27: Sim | DT27: 1.5342466 | DU27: 3 | DV27: =DU27+DT27 -> 4.5342466 | DW27: 32 | DX27: 5 | DY27: 9 | DZ27: 0 | EA27: 19 | EB27: 18 | EC27: 0 | ED27: 0 | EE27: 2 | EF27: 0 | EG27: 0 | EH27: 0 | EI27: 0 | EJ27: 50 | EK27: 0 | EL27: 50 | EM27: 0 | EN27: 20 | EO27: 0 | EP27: 0 | EQ27: 80 | ER27: 0 | ES27: 0 | ET27: 0 | EU27: 0 | EV27: Tanque de expansão | EW27: Sim | EX27: Sim | EY27: Sala de ordenha com fosso | EZ27: Sim | FA27: Sim | FB27: Mecânica | FC27: 2 | FD27: 2 | FE27: De 2 em 2 dias | FF27: Mista | FG27: Brachiaria, Capim-elefante | FH27: Sim | FJ27: Sim | FQ27: Adubação anual de cobertura, Controle de plantas invasoras | FZ27: Proprietário(a) e família | GA27: Produtividade | GC27: Sim | GI27: Acompanha o fluxo de caixa e calcula periodicamente custos de produção e margens | GJ27: Não | GL27: Assistência técnica, Vizinho, amigo ou parente | GM27: Sim | GN27: Sim | GS27: 60 | GT27: Mercado do leite, Sanidade do rebanho, Melhoramento genético | GW27: Sim | GY27: Sim | HA27: Sim | HF27: Planejamento da empresa rural, Cálculo do custo de produção, Gerenciamento da produção | HG27: Sim | HH27: Sim | HN27: Sim | HR27: 0 | HS27: 0 | HT27: 50 | HU27: 0 | HV27: 50 | HW27: Sombrite ou tela de sombreamento, Cobertura vegetal (árvores, sombra natural), Ventiladores mecânicos, Bebedouros | HY27: Sim | HZ27: Sim | IB27: Sim | IE27: Sim | IH27: Residência e locais de produção | II27: Em toda fazenda | IJ27: Picadeira, Trator, Misturador de ração | IK27: Sim | IM27: Sim | IT27: Sim | IU27: “Raspado” e/ou armazenado | IV27: Plantio direto, Cobertura do solo, Rotação de culturas | IW27: Sim | IX27: Sim | JA27: Sim | JB27: 1 | JC27: 3 | JD27: 100 | JE27: 22 | JF27: 9.5 | JG27: 0 | JH27: 0 | JI27: Manqueira, Brucelose, Raiva, Botulismo, Vermifugação, Carrapaticida, IBR/BVD, Leptospirose | JJ27: Sim | JK27: Sim | JM27: Sim | JO27: Sim | JP27: Sim | JQ27: Sim | JR27: Sim | JS27: Sim | JT27: Teste da caneca, Pré-dipping, Pós-dipping, Linha de ordenha, Identificação de animais tratados com antibiótico | JU27: Sim | JV27: Sim | JW27: Sim | JX27: Sim | KA27: Sim | KB27: Inseminação artificial/IATF | KD27: Sim | KG27: Artificial | KH27: Idade e peso das novilhas | KI27: Ano todo | KJ27: Sim | KK27: Cana-de-açúcar, Capineira, Silagem de milho | KL27: Sim | KM27: Sim | KO27: Sim | KU27: 15 | KV27: 2.6 | KW27: 2.75 | KX27: 2.95 | KY27: Volume de leite entregue, Nível de CCS, Nível de CBT, Teor de gordura, Teor de proteína | KZ27: Sim | LA27: Sim | LB27: Sim | LC27: Sim | LD27: Sim | LG27: Concorda | LH27: Concorda | LI27: Concorda | LJ27: Não | LK27: Muito importante
B28: Porto Firme | C28: Familiar | D28: 4) 1001 a 2500 | E28: Suavemente acidentado ou acidentado | F28: Intensivo | G28: Alvenaria | H28: Não possui | I28: Mista | J28: CAR - Cadastro Ambiental Rural, Cursos d’água/riacho/nascentes/mina, Vegetação nativa/mata/floresta, Área de preservação permanentes, Área de reserva legal, Serviço de esgoto doméstico tratado, Serviço de telefonia | K28: Sim | L28: Sim | M28: Sim | N28: Sim | O28: Sim | Q28: Sim | R28: Sim | S28: 84 | T28: 50 | U28: Masculino | V28: Ensino fundamental incompleto | W28: Na propriedade rural | X28: 77 | Y28: 23 | Z28: 0 | AA28: 0 | AB28: 0 | AC28: 0 | AD28: 100 | AE28: 0 | AF28: 0 | AG28: 0 | AH28: 0 | AI28: Não | AJ28: 95 | AK28: 5 | AL28: 0 | AM28: 0 | AN28: 0 | AR28: PRONAF, Seguro Safra | AU28: Sim | AW28: Sim | BC28: Muito bom | BD28: Sim | BE28: Por ser uma atividade lucrativa, A atividade leiteira é uma tradição na família, Tem mercado garantido | BG28: Sim | BI28: Sim | BK28: Sim | BO28: Falta de mão de obra | BP28: Sim | CB28: Mão de obra qualificada, Alimentação do rebanho, Reprodução do rebanho | CC28: Sim | CF28: Sim | CH28: Sim | CL28: Aumentar a produção | CM28: Filhos continuarão com a produção de leite | CN28: Não | CO28: Não utilizou crédito | CV28: Sim | CW28: Não precisou de crédito | DB28: Sim | DD28: 1325 | DE28: 1250 | DF28: 1400 | DG28: 27 | DH28: 26 | DI28: 28 | DJ28: 100 | DK28: 0 | DL28: 0 | DM28: 0 | DN28: 0 | DO28: 130 | DP28: 50 | DQ28: Sim | DR28: Sim | DS28: Sim | DT28: 4.4876712 | DU28: 0 | DV28: =DU28+DT28 -> 4.4876712 | DW28: 55 | DX28: 8 | DY28: 8 | DZ28: 3 | EA28: 25 | EB28: 15 | EC28: 0 | ED28: 0 | EE28: 0 | EF28: 0 | EG28: 0 | EH28: 0 | EI28: 50 | EJ28: 50 | EK28: 0 | EL28: 0 | EM28: 0 | EN28: 30 | EO28: 30 | EP28: 40 | EQ28: 0 | ER28: 0 | ES28: 0 | ET28: 0 | EU28: 0 | EV28: Tanque de expansão | EW28: Sim | EX28: Sim | EY28: Sala de ordenha com fosso | EZ28: Sim | FA28: Sim | FB28: Mecânica | FC28: 2 | FD28: 2 | FE28: De 2 em 2 dias | FF28: Mista | FG28: Brachiaria | FH28: Sim | FQ28: Controle de plantas invasoras | FZ28: Proprietário(a) e família | GA28: Produção de leite, Produtividade | GB28: Sim | GC28: Sim | GI28: Utiliza os indicadores econômicos de forma sistemática para tomada de decisão | GJ28: Sim | GK28: 2.42 | GL28: Assistência técnica, Treinamento (curso, palestra, etc.) | GM28: Sim | GO28: Sim | GS28: 30 | GT28: Planejamento da empresa rural, Cálculo do custo de produção, Alimentação do rebanho | GU28: Sim | GV28: Sim | GX28: Sim | HF28: Produção de leite e meio ambiente | HO28: Sim | HR28: 0 | HS28: 95 | HT28: 0 | HU28: 0 | HV28: 5 | HW28: Galpão coberto, Sombrite ou tela de sombreamento, Cobertura vegetal (árvores, sombra natural), Ventiladores mecânicos, Bebedouros | HX28: Sim | HY28: Sim | HZ28: Sim | IB28: Sim | IE28: Sim | IH28: Residência e locais de produção | II28: Em toda fazenda | IJ28: Picadeira, Balança para os animais, Trator, Plantadeira, Grade, Arado, Ensiladeira, Distribuidor de calcário, Misturador de ração | IK28: Sim | IL28: Sim | IM28: Sim | IO28: Sim | IP28: Sim | IQ28: Sim | IR28: Sim | IS28: Sim | IT28: Sim | IU28: “Raspado” e/ou armazenado | IV28: Cobertura do solo, Descarte adequado de embalagens (herbicida e defensivos), Tratamento de efluentes da residência | IX28: Sim | IY28: Sim | IZ28: Sim | JB28: 3 | JC28: 3 | JD28: 80 | JE28: 26 | JF28: 15.4 | JG28: 8 | JH28: 5 | JI28: Manqueira, Brucelose, Paratifo, Raiva, Botulismo, Vermifugação, Carrapaticida, IBR/BVD, Leptospirose | JJ28: Sim | JK28: Sim | JL28: Sim | JM28: Sim | JO28: Sim | JP28: Sim | JQ28: Sim | JR28: Sim | JS28: Sim | JT28: Pré-dipping, Pós-dipping, Alimentação após a ordenha | JV28: Sim | JW28: Sim | JZ28: Sim | KB28: FIV/TE, Inseminação artificial/IATF, Natural controlada | KC28: Sim | KD28: Sim | KE28: Sim | KG28: Artificial | KH28: Idade e peso das novilhas | KI28: Ano todo | KJ28: Sim | KK28: Silagem de milho | KO28: Sim | KU28: 5 | KV28: 2.82 | KW28: 2.7 | KX28: 3.3 | KY28: Nível de CCS, Nível de CBT, Teor de gordura, Teor de proteína | LA28: Sim | LB28: Sim | LC28: Sim | LD28: Sim | LG28: Concorda | LH28: Concorda | LI28: Concorda | LJ28: Sim | LK28: Pouco importante
B29: Teixeiras | C29: Não familiar | D29: 3) 501 a 1000 | E29: Suavemente acidentado ou acidentado | F29: Semiextensivo | G29: Alvenaria | H29: Alvenaria | I29: Alvenaria | J29: CAR - Cadastro Ambiental Rural, Cursos d’água/riacho/nascentes/mina, Vegetação nativa/mata/floresta, Área de preservação permanentes, Serviço de água potável, Serviço de telefonia | K29: Sim | L29: Sim | M29: Sim | N29: Sim | P29: Sim | R29: Sim | S29: 57 | T29: 31 | U29: Masculino | V29: Ensino superior completo | W29: Na cidade | X29: 100 | Y29: 0 | Z29: 0 | AA29: 0 | AB29: 0 | AC29: 0 | AD29: 100 | AE29: 0 | AF29: 0 | AG29: 0 | AH29: 0 | AI29: Não | AJ29: 50 | AK29: 0 | AL29: 0 | AM29: 0 | AN29: 50 | AR29: Não recebe benefício do governo | BB29: Sim | BC29: Regular | BD29: Não | BE29: Por gostar, Por ser uma atividade lucrativa | BF29: Sim | BG29: Sim | BO29: Falta de mão de obra | BP29: Sim | CB29: Mão de obra qualificada, Sanidade do rebanho, Manejo do rebanho | CC29: Sim | CD29: Sim | CG29: Sim | CL29: Aumentar a produção | CM29: Não sabe | CN29: Não | CO29: Não utilizou crédito | CV29: Sim | CW29: Não precisou de crédito | DB29: Sim | DD29: 700 | DE29: 700 | DF29: 700 | DG29: 24 | DH29: 24 | DI29: 24 | DJ29: 98 | DK29: 0 | DL29: 0 | DM29: 0 | DN29: 2 | DO29: 22 | DP29: 11.7 | DQ29: Sim | DR29: Sim | DS29: Não | DT29: 0.40273973 | DU29: 3 | DV29: =DU29+DT29 -> 3.4027397 | DW29: 33 | DX29: 7 | DY29: 5 | DZ29: 0 | EA29: 20 | EB29: 15 | EC29: 1 | ED29: 0 | EE29: 2 | EF29: 0 | EG29: 0 | EH29: 0 | EI29: 50 | EJ29: 50 | EK29: 0 | EL29: 0 | EM29: 0 | EN29: 0 | EO29: 20 | EP29: 60 | EQ29: 0 | ER29: 20 | ES29: 0 | ET29: 0 | EU29: 0 | EV29: Tanque de expansão | EW29: Sim | EX29: Sim | EY29: Sala de ordenha com fosso | EZ29: Sim | FA29: Sim | FB29: Mecânica | FC29: 2 | FD29: 2 | FE29: De 2 em 2 dias | FF29: Plantada | FG29: Brachiaria, Capim-elefante | FH29: Sim | FJ29: Sim | FQ29: Correção e adubação do solo na implantação, Controle de plantas invasoras, Divisão em piquetes, Cerca elétrica nos piquetes | FR29: Sim | FV29: Sim | FW29: Sim | FZ29: Apenas o(a) proprietário(a) | GA29: Produção de leite, Produtividade | GB29: Sim | GC29: Sim | GI29: Utiliza os indicadores econômicos de forma sistemática para tomada de decisão | GJ29: Sim | GK29: 2.33 | GL29: Assistência técnica, Jornais e revistas agropecuários, Outras mídias sociais | GM29: Sim | GP29: Sim | GR29: Sim | GS29: 12 | GT29: Planejamento da empresa rural, Cálculo do custo de produção, Manejo do rebanho | GU29: Sim | GV29: Sim | GZ29: Sim | HF29: Não sabe | HQ29: Sim | HR29: 35 | HS29: 0 | HT29: 0 | HU29: 0 | HV29: 65 | HW29: Galpão coberto, Sombrite ou tela de sombreamento, Ventiladores mecânicos, Aspersores ou nebulizadores, Sistema de resfriamento evaporativo, Bebedouros | HX29: Sim | HY29: Sim | IB29: Sim | ID29: Sim | IE29: Sim | IH29: Residência e locais de produção | II29: Somente na residência | IJ29: Picadeira, Balança para os animais, Misturador de ração | IK29: Sim | IL29: Sim | IT29: Sim | IU29: Composteira | IV29: Plantio direto, Cobertura do solo, Descarte adequado de embalagens (herbicida e defensivos) | IW29: Sim | IX29: Sim | IY29: Sim | JB29: 1 | JC29: 2 | JD29: 90 | JE29: 30 | JF29: 15 | JG29: 5 | JH29: 2 | JI29: Manqueira, Brucelose, Raiva, Botulismo, Vermifugação, Carrapaticida, IBR/BVD, Leptospirose | JJ29: Sim | JK29: Sim | JM29: Sim | JO29: Sim | JP29: Sim | JQ29: Sim | JR29: Sim | JS29: Sim | JT29: Teste da caneca, Pré-dipping, Pós-dipping, Linha de ordenha, Alimentação durante a ordenha, Alimentação após a ordenha, Identificação de animais tratados com antibiótico | JU29: Sim | JV29: Sim | JW29: Sim | JX29: Sim | JY29: Sim | JZ29: Sim | KA29: Sim | KB29: FIV/TE, Inseminação artificial/IATF, Natural controlada | KC29: Sim | KD29: Sim | KE29: Sim | KG29: Artificial | KH29: Peso das novilhas | KI29: Ano todo | KJ29: Sim | KK29: Cana-de-açúcar, Capineira, Silagem de milho, Silagem de sorgo | KL29: Sim | KM29: Sim | KO29: Sim | KP29: Sim | KU29: 15 | KV29: 2.7 | KW29: 2.7 | KX29: 3 | KY29: Volume de leite entregue, Nível de CCS, Nível de CBT, Teor de gordura, Teor de proteína | KZ29: Sim | LA29: Sim | LB29: Sim | LC29: Sim | LD29: Sim | LG29: Concorda | LH29: Concorda | LI29: Concorda | LJ29: Não | LK29: Muito importante
B30: Dores do Turvo | C30: Não familiar | D30: 5) Acima de 2501 | E30: Fortemente acidentado | F30: Intensivo | G30: Alvenaria | H30: Não possui | I30: Alvenaria | J30: CAR - Cadastro Ambiental Rural, Cursos d’água/riacho/nascentes/mina, Vegetação nativa/mata/floresta, Área de preservação permanentes, Área de reserva legal, Serviço de água potável, Serviço de telefonia | K30: Sim | L30: Sim | M30: Sim | N30: Sim | O30: Sim | P30: Sim | R30: Sim | S30: 58 | T30: 40 | U30: Masculino | V30: Ensino fundamental completo | W30: Na propriedade rural | X30: 100 | Y30: 0 | Z30: 0 | AA30: 0 | AB30: 0 | AC30: 0 | AD30: 100 | AE30: 0 | AF30: 0 | AG30: 0 | AH30: 0 | AI30: Não | AJ30: 100 | AK30: 0 | AL30: 0 | AM30: 0 | AN30: 0 | AR30: Não recebe benefício do governo | BB30: Sim | BC30: Bom | BD30: Sim | BE30: Por proporcionar renda mensal | BH30: Sim | BO30: Falta de mão de obra, Deficiência na qualificação da mão de obra, Custo dos insumos | BP30: Sim | BQ30: Sim | BU30: Sim | CB30: Alimentação do rebanho, Reprodução do rebanho, Preço do leite | CF30: Sim | CH30: Sim | CI30: Sim | CL30: Aumentar a produção | CM30: Filhos deixarão o meio rural | CN30: Sim | CO30: Cooperativas de crédito ou bancos privados | CS30: Sim | CW30: Utilizou crédito | DC30: Sim | DD30: 3600 | DE30: 3200 | DF30: 4000 | DG30: 19 | DH30: 19 | DI30: 19 | DJ30: 96.7 | DK30: 0 | DL30: 0 | DM30: 0.3 | DN30: 3 | DO30: 400 | DP30: 400 | DQ30: Sim | DR30: Sim | DS30: Não | DT30: 0.19726027 | DU30: 9 | DV30: =DU30+DT30 -> 9.1972603 | DW30: 150 | DX30: 60 | DY30: 20 | DZ30: 0 | EA30: 60 | EB30: 60 | EC30: 0 | ED30: 18 | EE30: 0 | EF30: 0 | EG30: 0 | EH30: 89 | EI30: 0 | EJ30: 0 | EK30: 0 | EL30: 11 | EM30: 0 | EN30: 0 | EO30: 0 | EP30: 100 | EQ30: 0 | ER30: 0 | ES30: 0 | ET30: 0 | EU30: 0 | EV30: Tanque de expansão | EW30: Sim | EX30: Sim | EY30: Sala de ordenha com fosso | EZ30: Sim | FA30: Sim | FB30: Mecânica | FC30: 2 | FD30: 2 | FE30: Todos os dias | FF30: Mista | FG30: Brachiaria | FH30: Sim | FQ30: Controle de plantas invasoras | FZ30: Proprietário(a) e família | GA30: Produção de leite, Produtividade, Venda de animais | GB30: Sim | GC30: Sim | GG30: Sim | GI30: Acompanha o fluxo de caixa e calcula periodicamente custos de produção e margens | GJ30: Sim | GK30: 2.39 | GL30: Assistência técnica | GM30: Sim | GS30: 48 | GT30: Planejamento da empresa rural, Alimentação do rebanho, Qualidade do leite | GU30: Sim | GX30: Sim | HD30: Sim | HF30: Sanidade do rebanho | HK30: Sim | HR30: 0 | HS30: 100 | HT30: 0 | HU30: 0 | HV30: 0 | HW30: Galpão coberto, Sombrite ou tela de sombreamento, Cobertura vegetal (árvores, sombra natural), Ventiladores mecânicos, Bebedouros | HX30: Sim | HY30: Sim | HZ30: Sim | IB30: Sim | IE30: Sim | IH30: Residência e locais de produção | II30: Somente na residência | IJ30: Balança para os animais, Trator, Vagão forrageiro, Grade, Misturador de ração | IL30: Sim | IM30: Sim | IN30: Sim | IP30: Sim | IT30: Sim | IU30: Composteira | IV30: Plantio direto, Cobertura do solo, Descarte adequado de embalagens (herbicida e defensivos) | IW30: Sim | IX30: Sim | IY30: Sim | JB30: 0 | JC30: 3 | JD30: 100 | JE30: 32 | JF30: 12 | JG30: 5 | JH30: 3 | JI30: Manqueira, Brucelose, Raiva, Vermifugação, Carrapaticida, Leptospirose | JJ30: Sim | JK30: Sim | JM30: Sim | JP30: Sim | JQ30: Sim | JS30: Sim | JT30: Teste da caneca, Pré-dipping, Pós-dipping, Alimentação após a ordenha, Identificação de animais tratados com antibiótico | JU30: Sim | JV30: Sim | JW30: Sim | JZ30: Sim | KA30: Sim | KB30: Natural não controlada | KF30: Sim | KG30: Artificial | KH30: Idade das novilhas | KI30: Ano todo | KJ30: Sim | KK30: Silagem de milho | KO30: Sim | KU30: 40 | KV30: 2.6 | KW30: 2.6 | KX30: 3.2 | KY30: Volume de leite entregue, Nível de CCS, Nível de CBT, Teor de gordura, Teor de proteína | KZ30: Sim | LA30: Sim | LB30: Sim | LC30: Sim | LD30: Sim | LG30: Concorda | LH30: Concorda | LI30: Concorda | LJ30: Não | LK30: Não é importante
B31: Ubá | C31: Não familiar | D31: 5) Acima de 2501 | E31: Fortemente acidentado | F31: Intensivo | G31: Alvenaria | H31: Não possui | I31: Alvenaria | J31: Cursos d’água/riacho/nascentes/mina, Vegetação nativa/mata/floresta, Área de reserva legal, Serviço de água potável, Serviço de telefonia | L31: Sim | M31: Sim | O31: Sim | P31: Sim | R31: Sim | S31: 55 | T31: 15 | U31: Masculino | V31: Ensino médio completo | W31: Na cidade | X31: 52 | Y31: 48 | Z31: 0 | AA31: 0 | AB31: 0 | AC31: 0 | AD31: 11 | AE31: 89 | AF31: 0 | AG31: 0 | AH31: 0 | AI31: Não | AJ31: 80 | AK31: 0 | AL31: 0 | AM31: 0 | AN31: 20 | AR31: Não recebe benefício do governo | BB31: Sim | BC31: Ruim | BD31: Sim | BE31: A atividade leiteira é uma tradição na família, Combina com outras explorações da propriedade | BI31: Sim | BJ31: Sim | BO31: Falta de mão de obra, Custo dos insumos, Legislação ambiental | BP31: Sim | BU31: Sim | BX31: Sim | CB31: Qualidade genética dos animais, Alimentação do rebanho | CE31: Sim | CF31: Sim | CL31: Aumentar a produção | CM31: Filhos deixarão o meio rural | CN31: Sim | CO31: PRONAMPE | CR31: Sim | CW31: Utilizou crédito | DC31: Sim | DD31: 3000 | DE31: 3000 | DF31: 3000 | DG31: 30 | DH31: 30 | DI31: 30 | DJ31: 96.95 | DK31: 0 | DL31: 0 | DM31: 0.05 | DN31: 3 | DO31: 105 | DP31: 70 | DQ31: Sim | DR31: Sim | DS31: Não | DT31: 0.98630137 | DU31: 10 | DV31: =DU31+DT31 -> 10.986301 | DW31: 100 | DX31: 20 | DY31: 12 | DZ31: 7 | EA31: 40 | EB31: 40 | EC31: 0 | ED31: 1 | EE31: 1 | EF31: 0 | EG31: 0 | EH31: 95 | EI31: 0 | EJ31: 5 | EK31: 0 | EL31: 0 | EM31: 0 | EN31: 0 | EO31: 33 | EP31: 33 | EQ31: 34 | ER31: 0 | ES31: 0 | ET31: 0 | EU31: 0 | EV31: Tanque de expansão | EW31: Sim | EX31: Sim | EY31: Sala de ordenha com fosso | EZ31: Sim | FA31: Sim | FB31: Mecânica | FC31: 2 | FD31: 2 | FE31: Todos os dias | FF31: Mista | FG31: Brachiaria, Panicum, Cynodon | FH31: Sim | FI31: Sim | FN31: Sim | FQ31: Nenhuma das anteriores | FX31: Sim | FZ31: Apenas o(a) proprietário(a) | GA31: Produção de leite, Produtividade | GB31: Sim | GC31: Sim | GI31: Acompanha o fluxo de caixa e calcula periodicamente custos de produção e margens | GJ31: Sim | GK31: 2.75 | GL31: Assistência técnica | GM31: Sim | GS31: 36 | GT31: Alimentação do rebanho, Sanidade do rebanho, Melhoramento genético | GX31: Sim | GY31: Sim | HA31: Sim | HF31: Cálculo do custo de produção | HH31: Sim | HR31: 0 | HS31: 100 | HT31: 0 | HU31: 0 | HV31: 0 | HW31: Galpão coberto, Ventiladores mecânicos, Aspersores ou nebulizadores, Bebedouros | HX31: Sim | IB31: Sim | IE31: Sim | IH31: Residência e locais de produção | II31: Em toda fazenda | IJ31: Balança para os animais, Trator, Vagão forrageiro, Plantadeira, Grade, Arado, Ensiladeira, Distribuidor de calcário, Misturador de ração | IL31: Sim | IM31: Sim | IN31: Sim | IO31: Sim | IP31: Sim | IQ31: Sim | IR31: Sim | IS31: Sim | IT31: Sim | IU31: Composteira | IV31: Cobertura do solo, Descarte adequado de embalagens (herbicida e defensivos) | IX31: Sim | IY31: Sim | JB31: 2 | JC31: 3 | JD31: 120 | JE31: 20 | JF31: 12 | JG31: 8.2 | JH31: 9.4 | JI31: Manqueira, Brucelose, Raiva, Botulismo, Vermifugação, Carrapaticida, IBR/BVD, Leptospirose | JJ31: Sim | JK31: Sim | JM31: Sim | JO31: Sim | JP31: Sim | JQ31: Sim | JR31: Sim | JS31: Sim | JT31: Teste da caneca, Pré-dipping, Pós-dipping, Linha de ordenha, Alimentação após a ordenha, Identificação de animais tratados com antibiótico | JU31: Sim | JV31: Sim | JW31: Sim | JX31: Sim | JZ31: Sim | KA31: Sim | KB31: Inseminação artificial/IATF, Natural controlada | KD31: Sim | KE31: Sim | KG31: Artificial | KH31: Idade e peso das novilhas | KI31: Ano todo | KJ31: Sim | KK31: Silagem de milho | KO31: Sim | KU31: 15 | KV31: 2.62 | KW31: 2.62 | KX31: 2.62 | KY31: Volume de leite entregue, Nível de CCS, Nível de CBT, Teor de gordura, Teor de proteína | KZ31: Sim | LA31: Sim | LB31: Sim | LC31: Sim | LD31: Sim | LG31: Concorda | LH31: Concorda | LI31: Concorda | LJ31: Não | LK31: Pouco importante

Sheet TABELA 1
A7: Rótulos de Linha | B7: Contagem de TIPOLOGIA DA PRODUÇÃO DE LEITE2 | C7: Contagem de TIPOLOGIA DA PRODUÇÃO DE LEITE
A8: Familiar | B8: 11 | C8: 0.36666667
A9: Não familiar | B9: 19 | C9: 0.63333333
A11: TOTAL | B11: =SUM(B8:B9) -> 30 | C11: =SUM(C8:C9) -> 1
A15: Rótulos de Linha | B15: Contagem de Município
A16: Cajuri | B16: 0.066666667
A17: Canaã | B17: 0.066666667
A18: Coimbra | B18: 0.16666667
A19: Dores do Turvo | B19: 0.033333333
A20: Guiricema | B20: 0.033333333
A21: Paula Cândido | B21: 0.1
A22: Piranga | B22: 0.066666667
A23: Porto Firme | B23: 0.066666667
A24: Presidente Bernardes | B24: 0.1
A25: Teixeiras | B25: 0.1
A26: Ubá | B26: 0.033333333
A27: Ubari | B27: 0.033333333
A28: Viçosa | B28: 0.13333333
A35: Rótulos de Linha | B35: Contagem de ESTRATO DE PRODUÇÃO (L/DIA)
A36: 1) Até 200 | B36: 0.066666667
A37: 2) 201 a 500 | B37: 0.2
A38: 3) 501 a 1000 | B38: 0.3
A39: 4) 1001 a 2500 | B39: 0.3
A40: 5) Acima de 2501 | B40: 0.13333333
A47: Rótulos de Linha | B47: Contagem de 1.2. Topografia/relevo predominante da propriedade rural:
A48: Suavemente acidentado ou acidentado | B48: 0.66666667
A49: Fortemente acidentado | B49: 0.3
A50: Extremamente acidentado | B50: 0.033333333
A57: Rótulos de Linha | B57: Contagem de 1.5. Sistema de produção de leite cru?
A58: Semiextensivo | B58: 0.36666667
A59: Intensivo | B59: 0.63333333
A66: Valores
A67: Média de 2.1. Idade (anos) | B67: 50.166667
A68: Média de 2.2. Tempo que é produtor(a) de leite (anos) | B68: 20.306667
A74: Rótulos de Linha | B74: Contagem de 2.3. Sexo
A75: Feminino | B75: 0.1
A76: Masculino | B76: 0.9
A83: Rótulos de Linha | B83: Contagem de 2.4. Escolaridade:
A84: Ensino fundamental incompleto | B84: 0.1
A85: Ensino fundamental completo | B85: 0.1
A86: Ensino médio incompleto | B86: 0.066666667
A87: Ensino médio completo | B87: 0.46666667
A88: Ensino superior incompleto | B88: 0.033333333
A89: Ensino superior completo | B89: 0.16666667
A90: Pós-graduação | B90: 0.066666667
A97: Rótulos de Linha | B97: Contagem de 2.5. Residência principal (mais de 50% do tempo):
A98: Na cidade | B98: 0.43333333
A99: Na propriedade rural | B99: 0.56666667
A106: Valores
A107: Média de 2.6. Distribuição da área utilizada na produção leiteira: Própria (%) | B107: 67.366667
A108: Média de 2.6. Distribuição da área utilizada na produção leiteira: Arrendada (%) | B108: 25.966667
A109: Média de 2.6. Distribuição da área utilizada na produção leiteira: Parceria (%) | B109: 0
A110: Média de 2.6. Distribuição da área utilizada na produção leiteira: Comodato (%) | B110: 6.6666667
A111: Média de 2.6. Distribuição da área utilizada na produção leiteira: Assentamento (%) | B111: 0
A112: Média de 2.6. Distribuição da área utilizada na produção leiteira: Como posseiro (%) | B112: 0
A118: Valores
A119: Média de 2.7. Origem da área própria utilizada na atividade leiteira: Herança ou doação (%) | B119: 42.678571
A120: Média de 2.7. Origem da área própria utilizada na atividade leiteira: Compra (%) | B120: 46.607143
A121: Média de 2.7. Origem da área própria utilizada na atividade leiteira: Posse ou usucapião (%) | B121: 0
A122: Média de 2.7. Origem da área própria utilizada na atividade leiteira: Titulação ou licença de ocupação (%) | B122: 3.5714286
A123: Média de 2.7. Origem da área própria utilizada na atividade leiteira: Outro (%) | B123: 7.1428571
A129: Rótulos de Linha | B129: Contagem de 2.8. Faz parte de alguma associação ou cooperativa relacionada à produção de leite?
A130: Sim | B130: 0.16666667
A131: Não | B131: 0.83333333
A138: Valores
A139: Média de 2.9. Composição da renda bruta do produtor rural: Pecuária de leite (%) | B139: 71.7
A140: Média de 2.9. Composição da renda bruta do produtor rural: Outras criações (%) | B140: 4.9
A141: Média de 2.9. Composição da renda bruta do produtor rural: Culturas permanentes (%) | B141: 2.6
A142: Média de 2.9. Composição da renda bruta do produtor rural: Culturas anuais (%) | B142: 5.1333333
A143: Média de 2.9. Composição da renda bruta do produtor rural: Fora da propriedade (%) | B143: 15.666667
A149: Valores
A150: Média de 2.10. Composição da renda bruta da atividade leiteira: Venda e consumo de leite (%) | B150: 86.893182
A151: Média de 2.10. Composição da renda bruta da atividade leiteira: Venda e consumo de animais (%) | B151: 12.197727
A152: Média de 2.10. Composição da renda bruta da atividade leiteira: Outro (%) | B152: 0.90909091
A158: Rótulos de Linha | B158: Contagem de 3.1. Atualmente, seu retorno financeiro na produção de leite pode ser considerado:
A159: Muito bom | B159: 0.13333333
A160: Bom | B160: 0.33333333
A161: Regular | B161: 0.46666667
A162: Ruim | B162: 0.066666667
A169: Rótulos de Linha | B169: Contagem de 3.2. Sua atividade leiteira se mantém sem recursos externos?
A170: Sim | B170: 0.66666667
A171: Não | B171: 0.33333333
A178: Rótulos de Linha | B178: Contagem de 3.7. Para os próximos 5 anos, o que pretende fazer com a produção de leite?
A179: Aumentar a produção | B179: 0.76666667
A180: Continuar como está | B180: 0.16666667
A181: Não sabe | B181: 0.066666667
A188: Rótulos de Linha | B188: Contagem de 3.8. Opinião do produtor sobre a sucessão em sua propriedade:
A189: Filhos continuarão com a produção de leite | B189: 0.46666667
A190: Filhos trocarão de atividade rural | B190: 0.033333333
A191: Filhos deixarão o meio rural | B191: 0.13333333
A192: Propriedade será vendida | B192: 0.033333333
A193: Não sabe | B193: 0.33333333
A200: Rótulos de Linha | B200: Contagem de 4.1. Utilizou crédito rural nos últimos 12 meses?
A201: Sim | B201: 0.56666667
A202: Não | B202: 0.43333333
A209: Valores
A210: Média de 5.2. Produção de leite média dos últimos 12 meses (consumido + vendido) (litros/dia) | B210: 1597.3611
A211: Média de 5.2.1. Produção nas águas (litros/dia) | B211: 1526.6667
A212: Média de 5.2.2. Produção na seca (litros/dia) | B212: 1660.3333
A218: Valores
...

Sheet TABELAS
C11: DISTRIBUIÇÃO DA AMOSTRA
C13: Tipologia da produção de leite
C14: Especificação | D14: Valor
C15: =IF('TABELA 1'!A8>0,'TABELA 1'!A8,"") -> Familiar | D15: =IF('TABELA 1'!C8>0,'TABELA 1'!C8,"") -> 0.36666667
C16: =IF('TABELA 1'!A9>0,'TABELA 1'!A9,"") -> Não familiar | D16: =IF('TABELA 1'!C9>0,'TABELA 1'!C9,"") -> 0.63333333
C17: Total | D17: =IF('TABELA 1'!C11>0,'TABELA 1'!C11,"") -> 1
C21: Localização da propriedade rural (município)
C22: Especificação | D22: Valor
C23: =IF('TABELA 1'!A16>0,'TABELA 1'!A16,"") -> Cajuri | D23: =IF('TABELA 1'!B16>0,'TABELA 1'!B16,"") -> 0.066666667
C24: =IF('TABELA 1'!A17>0,'TABELA 1'!A17,"") -> Canaã | D24: =IF('TABELA 1'!B17>0,'TABELA 1'!B17,"") -> 0.066666667
C25: =IF('TABELA 1'!A18>0,'TABELA 1'!A18,"") -> Coimbra | D25: =IF('TABELA 1'!B18>0,'TABELA 1'!B18,"") -> 0.16666667
C26: =IF('TABELA 1'!A19>0,'TABELA 1'!A19,"") -> Dores do Turvo | D26: =IF('TABELA 1'!B19>0,'TABELA 1'!B19,"") -> 0.033333333
C27: =IF('TABELA 1'!A20>0,'TABELA 1'!A20,"") -> Guiricema | D27: =IF('TABELA 1'!B20>0,'TABELA 1'!B20,"") -> 0.033333333
C28: =IF('TABELA 1'!A21>0,'TABELA 1'!A21,"") -> Paula Cândido | D28: =IF('TABELA 1'!B21>0,'TABELA 1'!B21,"") -> 0.1
C29: =IF('TABELA 1'!A22>0,'TABELA 1'!A22,"") -> Piranga | D29: =IF('TABELA 1'!B22>0,'TABELA 1'!B22,"") -> 0.066666667
C30: =IF('TABELA 1'!A23>0,'TABELA 1'!A23,"") -> Porto Firme | D30: =IF('TABELA 1'!B23>0,'TABELA 1'!B23,"") -> 0.066666667
C31: =IF('TABELA 1'!A24>0,'TABELA 1'!A24,"") -> Presidente Bernardes | D31: =IF('TABELA 1'!B24>0,'TABELA 1'!B24,"") -> 0.1
C32: =IF('TABELA 1'!A25>0,'TABELA 1'!A25,"") -> Teixeiras | D32: =IF('TABELA 1'!B25>0,'TABELA 1'!B25,"") -> 0.1
C33: =IF('TABELA 1'!A26>0,'TABELA 1'!A26,"") -> Ubá | D33: =IF('TABELA 1'!B26>0,'TABELA 1'!B26,"") -> 0.033333333
C34: =IF('TABELA 1'!A27>0,'TABELA 1'!A27,"") -> Ubari | D34: =IF('TABELA 1'!B27>0,'TABELA 1'!B27,"") -> 0.033333333
C35: =IF('TABELA 1'!A28>0,'TABELA 1'!A28,"") -> Viçosa | D35: =IF('TABELA 1'!B28>0,'TABELA 1'!B28,"") -> 0.13333333
C36: Total | D36: =SUM(D23:D35) -> 1
C40: Estratos de produção de leite
C41: Especificação | D41: Valor
C42: =IF('TABELA 1'!A36>0,'TABELA 1'!A36,"") -> 1) Até 200 | D42: =IF('TABELA 1'!B36>0,'TABELA 1'!B36,"") -> 0.066666667
C43: =IF('TABELA 1'!A37>0,'TABELA 1'!A37,"") -> 2) 201 a 500 | D43: =IF('TABELA 1'!B37>0,'TABELA 1'!B37,"") -> 0.2
C44: =IF('TABELA 1'!A38>0,'TABELA 1'!A38,"") -> 3) 501 a 1000 | D44: =IF('TABELA 1'!B38>0,'TABELA 1'!B38,"") -> 0.3
C45: =IF('TABELA 1'!A39>0,'TABELA 1'!A39,"") -> 4) 1001 a 2500 | D45: =IF('TABELA 1'!B39>0,'TABELA 1'!B39,"") -> 0.3
C46: =IF('TABELA 1'!A40>0,'TABELA 1'!A40,"") -> 5) Acima de 2501 | D46: =IF('TABELA 1'!B40>0,'TABELA 1'!B40,"") -> 0.13333333
C47: Total | D47: =SUM(D42:D46) -> 1
C51: CARACTERÍSTICAS GERAIS DA PROPRIEDADE RURAL
C54: Topografia/relevo predominante
C55: Especificação | D55: Valor
C56: =IF('TABELA 1'!A48>0,'TABELA 1'!A48,"") -> Suavemente acidentado ou acidentado | D56: =IF('TABELA 1'!B48>0,'TABELA 1'!B48,"") -> 0.66666667
C57: =IF('TABELA 1'!A49>0,'TABELA 1'!A49,"") -> Fortemente acidentado | D57: =IF('TABELA 1'!B49>0,'TABELA 1'!B49,"") -> 0.3
C58: =IF('TABELA 1'!A50>0,'TABELA 1'!A50,"") -> Extremamente acidentado | D58: =IF('TABELA 1'!B50>0,'TABELA 1'!B50,"") -> 0.033333333
C59: Total | D59: =SUM(D56:D58) -> 1
C63: Sistema de produção
C64: Especificação | D64: Valor
C65: =IF('TABELA 1'!A58>0,'TABELA 1'!A58,"") -> Semiextensivo | D65: =IF('TABELA 1'!B58>0,'TABELA 1'!B58,"") -> 0.36666667
C66: =IF('TABELA 1'!A59>0,'TABELA 1'!A59,"") -> Intensivo | D66: =IF('TABELA 1'!B59>0,'TABELA 1'!B59,"") -> 0.63333333
C67: Total | D67: =SUM(D65:D66) -> 1
C71: Disponibilidade de recursos hídricos e serviços na propriedade rural
C72: Especificação | D72: Valor
C73: CAR - Cadastro Ambiental Rural | D73: =IF('TABELA 1'!B574>0,'TABELA 1'!B574,0) -> 0.9
C74: Cursos d’água/riacho/nascentes/mina | D74: =IF('TABELA 1'!B575>0,'TABELA 1'!B575,0) -> 0.86666667
C75: Vegetação nativa/mata/floresta | D75: =IF('TABELA 1'!B576>0,'TABELA 1'!B576,0) -> 0.83333333
C76: Área de preservação permanentes | D76: =IF('TABELA 1'!B577>0,'TABELA 1'!B577,0) -> 0.86666667
C77: Área de reserva legal | D77: =IF('TABELA 1'!B578>0,'TABELA 1'!B578,0) -> 0.76666667
C78: Serviço de água potável | D78: =IF('TABELA 1'!B579>0,'TABELA 1'!B579,0) -> 0.43333333
C79: Serviço de esgoto doméstico tratado | D79: =IF('TABELA 1'!B580>0,'TABELA 1'!B580,0) -> 0.13333333
C80: Serviço de telefonia | D80: =IF('TABELA 1'!B581>0,'TABELA 1'!B581,0) -> 0.56666667
C84: Disponibilidade de recursos hídricos e serviços na propriedade rural
C106: PERFIL DO PRODUTOR RURAL
C110: Idade e tempo na produção de leite (anos) - valores médios
C111: Especificação | D111: Valor
C112: Idade | D112: =IF('TABELA 1'!B67>0,'TABELA 1'!B67,"") -> 50.166667
C113: Tempo que é produtor(a) de leite | D113: =IF('TABELA 1'!B68>0,'TABELA 1'!B68,"") -> 20.306667
C117: Sexo
C118: Especificação | D118: Valor
C119: =IF('TABELA 1'!A75>0,'TABELA 1'!A75,"") -> Feminino | D119: =IF('TABELA 1'!B75>0,'TABELA 1'!B75,"") -> 0.1
C120: =IF('TABELA 1'!A76>0,'TABELA 1'!A76,"") -> Masculino | D120: =IF('TABELA 1'!B76>0,'TABELA 1'!B76,"") -> 0.9
C121: Total | D121: =SUM(D119:D120) -> 1
C125: Escolaridade
C126: Especificação | D126: Valor
C127: =IF('TABELA 1'!A84>0,'TABELA 1'!A84,"") -> Ensino fundamental incompleto | D127: =IF('TABELA 1'!B84>0,'TABELA 1'!B84,"") -> 0.1
C128: =IF('TABELA 1'!A85>0,'TABELA 1'!A85,"") -> Ensino fundamental completo | D128: =IF('TABELA 1'!B85>0,'TABELA 1'!B85,"") -> 0.1
C129: =IF('TABELA 1'!A86>0,'TABELA 1'!A86,"") -> Ensino médio incompleto | D129: =IF('TABELA 1'!B86>0,'TABELA 1'!B86,"") -> 0.066666667
C130: =IF('TABELA 1'!A87>0,'TABELA 1'!A87,"") -> Ensino médio completo | D130: =IF('TABELA 1'!B87>0,'TABELA 1'!B87,"") -> 0.46666667
C131: =IF('TABELA 1'!A88>0,'TABELA 1'!A88,"") -> Ensino superior incompleto | D131: =IF('TABELA 1'!B88>0,'TABELA 1'!B88,"") -> 0.033333333
C132: =IF('TABELA 1'!A89>0,'TABELA 1'!A89,"") -> Ensino superior completo | D132: =IF('TABELA 1'!B89>0,'TABELA 1'!B89,"") -> 0.16666667
C133: =IF('TABELA 1'!A90>0,'TABELA 1'!A90,"") -> Pós-graduação | D133: =IF('TABELA 1'!B90>0,'TABELA 1'!B90,"") -> 0.066666667
C134: Total | D134: =SUM(D127:D133) -> 1
C138: Residência principal
C139: Especificação | D139: Valor
C140: =IF('TABELA 1'!A98>0,'TABELA 1'!A98,"") -> Na cidade | D140: =IF('TABELA 1'!B98>0,'TABELA 1'!B98,"") -> 0.43333333
C141: =IF('TABELA 1'!A99>0,'TABELA 1'!A99,"") -> Na propriedade rural | D141: =IF('TABELA 1'!B99>0,'TABELA 1'!B99,"") -> 0.56666667
C142: Total | D142: =SUM(D140:D141) -> 1
C146: Distribuição da área utilizada na produção leiteira
C147: Especificação | D147: Valor
C148: Própria | D148: =IF('TABELA 1'!B107/100>0,'TABELA 1'!B107/100,0) -> 0.67366667
C149: Arrendada | D149: =IF('TABELA 1'!B108/100>0,'TABELA 1'!B108/100,0) -> 0.25966667
C150: Parceria | D150: =IF('TABELA 1'!B109/100>0,'TABELA 1'!B109/100,0) -> 0
C151: Comodato | D151: =IF('TABELA 1'!B110/100>0,'TABELA 1'!B110/100,0) -> 0.066666667
C152: Assentamento | D152: =IF('TABELA 1'!B111/100>0,'TABELA 1'!B111/100,0) -> 0
C153: Como posseiro | D153: =IF('TABELA 1'!B112/100>0,'TABELA 1'!B112/100,0) -> 0
C154: Total | D154: =SUM(D148:D153) -> 1
C158: Origem da área própria utilizada na atividade leiteira
C159: Especificação | D159: Valor
C160: Herança ou doação | D160: =IF('TABELA 1'!B119/100>0,'TABELA 1'!B119/100,0) -> 0.42678571
C161: Compra | D161: =IF('TABELA 1'!B120/100>0,'TABELA 1'!B120/100,0) -> 0.46607143
C162: Posse ou usucapião | D162: =IF('TABELA 1'!B121/100>0,'TABELA 1'!B121/100,0) -> 0
C163: Titulação ou licença de ocupação | D163: =IF('TABELA 1'!B122/100>0,'TABELA 1'!B122/100,0) -> 0.035714286
C164: Outra | D164: =IF('TABELA 1'!B123/100>0,'TABELA 1'!B123/100,0) -> 0.071428571
C165: Total | D165: =SUM(D160:D164) -> 1
C169: Composição da renda bruta do produtor rural
C170: Especificação | D170: Valor
C171: Pecuária de leite | D171: =IF('TABELA 1'!B139/100>0,'TABELA 1'!B139/100,0) -> 0.717
C172: Outras criações | D172: =IF('TABELA 1'!B140/100>0,'TABELA 1'!B140/100,0) -> 0.049
C173: Culturas permanentes | D173: =IF('TABELA 1'!B141/100>0,'TABELA 1'!B141/100,0) -> 0.026
...
